Workbook

Sheet TOC
A1: Stanmere Capital Partners I, L.P.
A2: Fund Accounting & Financial Reporting Model — master case workbook
A4: DISCLAIMER: This model is for instructional purposes only. Stanmere Capital Partners I, L.P. and every
A5: entity named in this workbook are fictional. Any resemblance to an actual fund, firm or company is coincidental.
A7: HOW IT WORKS: there are TWO hard-keyed layers. (1) Journal Entries — the general ledger. (2) Allocations — the
A8: partner-level split of each component, produced by the allocation engine from the ledger and the LPA rules.
A9: Everything else derives by formula. Changing a journal entry updates the trial balance, every statement and
A10: the waterfall automatically, but Allocations must be regenerated for investor-level reports to follow.
A11: Tie-Out Checks includes six allocation controls proving Allocations agrees to the ledger component by component.
A13: SCOPE: this is a FIXED INSTRUCTIONAL CASE, not a live production model. The figures are complete and
A14: internally consistent as presented. To extend the case, regenerate the Allocations tab from the ledger
A15: using the fund's allocation rules (see Fund Terms), then confirm all twenty-two controls still pass.
A17: COLOUR: blue = hard-keyed input · black = formula · green = link to another tab
A19: Group | B19: Tab | C19: What it does
A20: 1. Setup | B20: FS Cover | C20: Report cover, period and contacts
B21: Fund Terms | C21: Economic terms — every formula references these cells
B22: Partners | C22: Commitments, ownership %, admission close
B23: Chart of Accounts | C23: Account number, name, type, statement classification, normal balance, and a note on unused accounts
A24: 2. Ledger | B24: Journal Entries | C24: The complete general ledger. Hard-keyed layer 1 of 2.
B25: Allocations | C25: Partner-level split of each component. Hard-keyed layer 2 of 2.
B26: Trial Balance | C26: Account by year, built with SUMIFS over Journal Entries
A27: 3. Statements | B27: Balance Sheet | C27: Statement of Assets and Liabilities, ASC 946
B28: Income Statement | C28: Statement of Operations
B29: Changes in Partners' Capital | C29: Contributions, allocations, distributions, ending capital
B30: Cash Flow Statement | C30: Indirect method, gross purchases and disposals, reconciled to the change in cash, plus non-cash disclosure
B31: Financial Highlights | C31: LP-class ratios before and after carried interest, total return and since-inception IRR - required by ASC 946-205-50
B32: Schedule of Investments | C32: Positions at 31 December 2026, cost, fair value, % of net assets
A33: 4. Investors | B33: Investor Allocations | C33: Allocation grid across the GP and six limited partners
B34: Investor Capital Accounts | C34: Per-investor capital account statement with a selector
A35: 5. Economics | B35: Management Fee | C35: Quarterly fee schedule, basis, offsets
B36: Waterfall | C36: European whole-fund distribution waterfall and clawback test
B37: Performance | C37: Cash flows, DPI, RVPI, TVPI, IRR
A38: 6. Control | B38: Bank Reconciliation | C38: Cash per bank against cash per books, by quarter
B39: Tie-Out Checks | C39: Every cross-statement check as a live formula
A40: 7. Reference | B40: Glossary | C40: Technical terms used throughout

Sheet FS Cover
A1: Stanmere Capital Partners I, L.P.
A2: Annual Financial Report
A4: Fund | B4: Stanmere Capital Partners I, L.P.
A5: Entity type | B5: Delaware limited partnership
A6: General partner | B6: Stanmere Capital GP I, LLC
A7: Management company | B7: Stanmere Capital Management, LLC
A8: Period from | B8: 2019-01-02
A9: Period to | B9: 2030-06-30
A10: Basis of presentation | B10: Investment company accounting, ASC 946
A11: Auditor | B11: [Independent registered public accounting firm]
A12: Administrator | B12: [Fund administrator]
A13: Report date | B13: 2030-06-30
A15: Stanmere Capital Partners I, L.P. is a fictional fund created for instructional purposes.
A16: Any resemblance to an actual fund, firm or company is coincidental.

Sheet Fund Terms
A1: Fund Terms
A2: Blue cells are the economic terms. Formulas across the workbook reference these cells.
A4: Term | B4: Value | C4: Note
A5: Total commitments | B5: 250000000 | C5: Across three closes
A6: GP commitment | B6: 5000000 | C6: 2.0%; fee-free
A7: Initial close | B7: 2019-01-02 | C7: Close 1
A8: Second close | B8: 2019-10-01 | C8: Close 2
A9: Final close | B9: 2020-06-30 | C9: Close 3 — 18-month offering period
A10: Investment period ends | B10: 2025-06-30 | C10: 5 years from final close
A11: Term ends | B11: 2030-06-30 | C11: 10 years from final close
A12: Management fee rate | B12: 0.02 | C12: Of commitments during the investment period
A13: Management fee offset | B13: 1 | C13: Of monitoring and transaction fees
A14: Preferred return | B14: 0.08 | C14: Accrued quarterly on unreturned capital only; unpaid pref does not itself earn a return
A15: Carry catch-up | B15: 1 | C15: 100% until the carry side holds 20% of profits
A16: Carried interest | B16: 0.2 | C16: European whole-fund waterfall
A17: Equalization interest | B17: 0.08 | C17: Simple, annualized
A18: Organizational costs | B18: 1200000 | C18: Expensed as incurred, ASC 720-15-25-1
A19: Offering costs | B19: 900000 | C19: Charged against partners' capital at the first closing - ASC 946-20-25-5; the fund is not in continuous offering

Sheet Partners
A1: Partners and Commitments
A4: Partner | B4: Type | C4: Commitment | D4: % of fund | E4: Admitted
A5: Stanmere Capital GP I, LLC | B5: GP | C5: 5000000 | D5: =C5/$C$12 -> 0.02 | E5: Close 1
A6: Kelbrook State Retirement System | B6: LP | C6: 75000000 | D6: =C6/$C$12 -> 0.3 | E6: Close 1
A7: Ashfield University Endowment | B7: LP | C7: 40000000 | D7: =C7/$C$12 -> 0.16 | E7: Close 1
A8: Pellham Mutual Insurance Company | B8: LP | C8: 35000000 | D8: =C8/$C$12 -> 0.14 | E8: Close 2
A9: Lanternwood Partners, L.P. (fund-of-funds) | B9: LP | C9: 25000000 | D9: =C9/$C$12 -> 0.1 | E9: Close 2
A10: Ellinwood Family Holdings, LLC | B10: LP | C10: 30000000 | D10: =C10/$C$12 -> 0.12 | E10: Close 3
A11: Northmoor Trust Company | B11: LP | C11: 40000000 | D11: =C11/$C$12 -> 0.16 | E11: Close 3
A12: Total | C12: =SUM(C5:C11) -> 250000000 | D12: =SUM(D5:D11) -> 1

Sheet Chart of Accounts
A1: Chart of Accounts
A4: Account no. | B4: Account name | C4: Type | D4: Statement | E4: Normal balance | F4: Note
A5: 1000 | B5: Cash and cash equivalents | C5: Asset | D5: Balance Sheet | E5: Debit
A6: 1050 | B6: Subscriptions receivable | C6: Asset | D6: Balance Sheet | E6: Debit
A7: 1100 | B7: Investments, at cost | C7: Asset | D7: Balance Sheet | E7: Debit
A8: 1110 | B8: Unrealized appreciation/(depreciation) on investments | C8: Asset | D8: Balance Sheet | E8: Debit
A9: 1150 | B9: Investments, at cost - bridge notes | C9: Asset | D9: Balance Sheet | E9: Debit | F9: Bridge notes to portfolio companies. On conversion the balance is reclassified to 1100 at cost - no cash, no gain or loss.
A10: 1200 | B10: Interest and PIK receivable | C10: Asset | D10: Balance Sheet | E10: Debit | F10: Retired. PIK interest is capitalised into the principal of the Verrick note and is carried in account 1100, so this account holds no balance. Retained so the trial balance, the balance sheet and the cash flow statement keep a line for a fund that does settle interest in cash.
A11: 1250 | B11: Prepaid management fee | C11: Asset | D11: Balance Sheet | E11: Debit
A12: 1300 | B12: Deferred offering costs | C12: Asset | D12: Balance Sheet | E12: Debit | F12: Not used by Stanmere. Retained so module 1.3 can post the contrasting deferral treatment; it is carried through the trial balance, the balance sheet and the cash flow statement.
A13: 2000 | B13: Accounts payable and accrued expenses | C13: Liability | D13: Balance Sheet | E13: Credit
A14: 2100 | B14: Management fee payable | C14: Liability | D14: Balance Sheet | E14: Credit
A15: 2300 | B15: Subscription line payable | C15: Liability | D15: Balance Sheet | E15: Credit
A16: 2400 | B16: Distributions payable | C16: Liability | D16: Balance Sheet | E16: Credit
A17: 3000 | B17: Partners' capital - contributions | C17: Capital | D17: Partners' Capital | E17: Credit
A18: 3050 | B18: Partners' capital - offering costs charged against capital | C18: Capital | D18: Partners' Capital | E18: Debit | F18: Offering costs charged directly against partners' capital (ASC 946-20-25-5).
A19: 3100 | B19: Partners' capital - distributions | C19: Capital | D19: Partners' Capital | E19: Debit
A20: 3900 | B20: Partners' capital - accumulated results | C20: Capital | D20: Partners' Capital | E20: Credit | F20: Not used by Stanmere - never posted. Results stay in the income and expense accounts and are not closed to capital, and the cash flow statement's financing section is derived on that basis; a posting to 3900 would be missed there and break the cash tie-out.
A21: 4000 | B21: Interest income - PIK | C21: Income | D21: Income Statement | E21: Credit
A22: 4010 | B22: Interest income - other | C22: Income | D22: Income Statement | E22: Credit
A23: 4030 | B23: Other income - monitoring fees | C23: Income | D23: Income Statement | E23: Credit | F23: Not used by Stanmere. Monitoring fees are earned by the manager, not by the fund; under the LPA they reduce the management fee the fund owes (account 5010). The fund therefore records no monitoring fee income.
A24: 5000 | B24: Management fee | C24: Expense | D24: Income Statement | E24: Debit
A25: 5010 | B25: Management fee offset | C25: Expense | D25: Income Statement | E25: Credit | F25: The 100% offset of monitoring and transaction fees. Dr 2100 / Cr 5010 reduces both the fee payable and the fee expense; the manager then refunds the cash to the fund (Dr 1000 / Cr 2100).
A26: 5100 | B26: Organizational costs | C26: Expense | D26: Income Statement | E26: Debit
A27: 5110 | B27: Amortization of deferred offering costs | C27: Expense | D27: Income Statement | E27: Debit | F27: Not used by Stanmere. Retained for the module 1.3 contrast; it is carried through the trial balance and appears as its own line on the statement of operations.
A28: 5200 | B28: Professional fees - audit and tax | C28: Expense | D28: Income Statement | E28: Debit
A29: 5210 | B29: Professional fees - legal | C29: Expense | D29: Income Statement | E29: Debit
A30: 5300 | B30: Fund administration fees | C30: Expense | D30: Income Statement | E30: Debit
A31: 5400 | B31: Custody and bank fees | C31: Expense | D31: Income Statement | E31: Debit
A32: 5500 | B32: Interest expense - subscription line | C32: Expense | D32: Income Statement | E32: Debit
A33: 5600 | B33: Other fund expenses | C33: Expense | D33: Income Statement | E33: Debit
A34: 6000 | B34: Net realized gain/(loss) on investments | C34: Income | D34: Income Statement | E34: Credit
A35: 6100 | B35: Net change in unrealized appreciation/(depreciation) | C35: Income | D35: Income Statement | E35: Credit

Sheet Journal Entries
A1: Journal Entries — general ledger
A2: Hard-keyed layer 1 of 2. The general ledger. Trial balance, statements and waterfall derive from it.
A4: Trans. date | B4: Month end | C4: Quarter | D4: Acct | E4: Account name | F4: Curriculum module | G4: Debit | H4: Credit | I4: Amount (Dr-Cr) | J4: Per#
A5: 43555 | B5: 43555 | C5: 2019Q1 | D5: 1000 | E5: Cash and cash equivalents | F5: 2.1 capital calls | G5: 3100000 | I5: 3100000 | J5: 0
A6: 43555 | B6: 43555 | C6: 2019Q1 | D6: 3000 | E6: Partners' capital - contributions | F6: 2.1 capital calls | H6: 3100000 | I6: -3100000 | J6: 0
A7: 43555 | B7: 43555 | C7: 2019Q1 | D7: 5100 | E7: Organizational costs | F7: 1.3 org vs offering | G7: 1200000 | I7: 1200000 | J7: 0
A8: 43555 | B8: 43555 | C8: 2019Q1 | D8: 1000 | E8: Cash and cash equivalents | F8: 1.3 org vs offering | H8: 1200000 | I8: -1200000 | J8: 0
A9: 43555 | B9: 43555 | C9: 2019Q1 | D9: 3050 | E9: Partners' capital - offering costs charged against capital | F9: 1.3 org vs offering | G9: 900000 | I9: 900000 | J9: 0
A10: 43555 | B10: 43555 | C10: 2019Q1 | D10: 1000 | E10: Cash and cash equivalents | F10: 1.3 org vs offering | H10: 900000 | I10: -900000 | J10: 0
A11: 43555 | B11: 43555 | C11: 2019Q1 | D11: 5000 | E11: Management fee | F11: 2.2 management fees | G11: 575000 | I11: 575000 | J11: 0
A12: 43555 | B12: 43555 | C12: 2019Q1 | D12: 2100 | E12: Management fee payable | F12: 2.2 management fees | H12: 575000 | I12: -575000 | J12: 0
A13: 43555 | B13: 43555 | C13: 2019Q1 | D13: 2100 | E13: Management fee payable | F13: 2.2 management fees | G13: 575000 | I13: 575000 | J13: 0
A14: 43555 | B14: 43555 | C14: 2019Q1 | D14: 1000 | E14: Cash and cash equivalents | F14: 2.2 management fees | H14: 575000 | I14: -575000 | J14: 0
A15: 43555 | B15: 43555 | C15: 2019Q1 | D15: 5300 | E15: Fund administration fees | F15: 4.1 accruals & expenses | G15: 45000 | I15: 45000 | J15: 0
A16: 43555 | B16: 43555 | C16: 2019Q1 | D16: 5200 | E16: Professional fees - audit and tax | F16: 4.1 accruals & expenses | G16: 30000 | I16: 30000 | J16: 0
A17: 43555 | B17: 43555 | C17: 2019Q1 | D17: 5210 | E17: Professional fees - legal | F17: 4.1 accruals & expenses | G17: 35000 | I17: 35000 | J17: 0
A18: 43555 | B18: 43555 | C18: 2019Q1 | D18: 5400 | E18: Custody and bank fees | F18: 4.1 accruals & expenses | G18: 5000 | I18: 5000 | J18: 0
A19: 43555 | B19: 43555 | C19: 2019Q1 | D19: 5600 | E19: Other fund expenses | F19: 4.1 accruals & expenses | G19: 12000 | I19: 12000 | J19: 0
A20: 43555 | B20: 43555 | C20: 2019Q1 | D20: 2000 | E20: Accounts payable and accrued expenses | F20: 4.1 accruals & expenses | H20: 127000 | I20: -127000 | J20: 0
A21: 43555 | B21: 43555 | C21: 2019Q1 | D21: 2000 | E21: Accounts payable and accrued expenses | F21: 4.1 accruals & expenses | G21: 127000 | I21: 127000 | J21: 0
A22: 43555 | B22: 43555 | C22: 2019Q1 | D22: 1000 | E22: Cash and cash equivalents | F22: 4.1 accruals & expenses | H22: 127000 | I22: -127000 | J22: 0
A23: 43646 | B23: 43646 | C23: 2019Q2 | D23: 1000 | E23: Cash and cash equivalents | F23: 2.1 capital calls | G23: 42700000 | I23: 42700000 | J23: 1
A24: 43646 | B24: 43646 | C24: 2019Q2 | D24: 3000 | E24: Partners' capital - contributions | F24: 2.1 capital calls | H24: 42700000 | I24: -42700000 | J24: 1
A25: 43646 | B25: 43646 | C25: 2019Q2 | D25: 5000 | E25: Management fee | F25: 2.2 management fees | G25: 575000 | I25: 575000 | J25: 1
A26: 43646 | B26: 43646 | C26: 2019Q2 | D26: 2100 | E26: Management fee payable | F26: 2.2 management fees | H26: 575000 | I26: -575000 | J26: 1
A27: 43646 | B27: 43646 | C27: 2019Q2 | D27: 2100 | E27: Management fee payable | F27: 2.2 management fees | G27: 575000 | I27: 575000 | J27: 1
A28: 43646 | B28: 43646 | C28: 2019Q2 | D28: 1000 | E28: Cash and cash equivalents | F28: 2.2 management fees | H28: 575000 | I28: -575000 | J28: 1
A29: 43646 | B29: 43646 | C29: 2019Q2 | D29: 5300 | E29: Fund administration fees | F29: 4.1 accruals & expenses | G29: 45000 | I29: 45000 | J29: 1
A30: 43646 | B30: 43646 | C30: 2019Q2 | D30: 5200 | E30: Professional fees - audit and tax | F30: 4.1 accruals & expenses | G30: 30000 | I30: 30000 | J30: 1
A31: 43646 | B31: 43646 | C31: 2019Q2 | D31: 5210 | E31: Professional fees - legal | F31: 4.1 accruals & expenses | G31: 35000 | I31: 35000 | J31: 1
A32: 43646 | B32: 43646 | C32: 2019Q2 | D32: 5400 | E32: Custody and bank fees | F32: 4.1 accruals & expenses | G32: 5000 | I32: 5000 | J32: 1
A33: 43646 | B33: 43646 | C33: 2019Q2 | D33: 5600 | E33: Other fund expenses | F33: 4.1 accruals & expenses | G33: 12000 | I33: 12000 | J33: 1
A34: 43646 | B34: 43646 | C34: 2019Q2 | D34: 2000 | E34: Accounts payable and accrued expenses | F34: 4.1 accruals & expenses | H34: 127000 | I34: -127000 | J34: 1
A35: 43646 | B35: 43646 | C35: 2019Q2 | D35: 2000 | E35: Accounts payable and accrued expenses | F35: 4.1 accruals & expenses | G35: 127000 | I35: 127000 | J35: 1
A36: 43646 | B36: 43646 | C36: 2019Q2 | D36: 1000 | E36: Cash and cash equivalents | F36: 4.1 accruals & expenses | H36: 127000 | I36: -127000 | J36: 1
A37: 43646 | B37: 43646 | C37: 2019Q2 | D37: 1100 | E37: Investments, at cost | F37: 3.1 recording investments | G37: 42000000 | I37: 42000000 | J37: 1
A38: 43646 | B38: 43646 | C38: 2019Q2 | D38: 1000 | E38: Cash and cash equivalents | F38: 3.1 recording investments | H38: 42000000 | I38: -42000000 | J38: 1
A39: 43738 | B39: 43738 | C39: 2019Q3 | D39: 1000 | E39: Cash and cash equivalents | F39: 2.1 capital calls | G39: 700000 | I39: 700000 | J39: 2
A40: 43738 | B40: 43738 | C40: 2019Q3 | D40: 3000 | E40: Partners' capital - contributions | F40: 2.1 capital calls | H40: 700000 | I40: -700000 | J40: 2
A41: 43738 | B41: 43738 | C41: 2019Q3 | D41: 5000 | E41: Management fee | F41: 2.2 management fees | G41: 575000 | I41: 575000 | J41: 2
A42: 43738 | B42: 43738 | C42: 2019Q3 | D42: 2100 | E42: Management fee payable | F42: 2.2 management fees | H42: 575000 | I42: -575000 | J42: 2
A43: 43738 | B43: 43738 | C43: 2019Q3 | D43: 2100 | E43: Management fee payable | F43: 2.2 management fees | G43: 575000 | I43: 575000 | J43: 2
A44: 43738 | B44: 43738 | C44: 2019Q3 | D44: 1000 | E44: Cash and cash equivalents | F44: 2.2 management fees | H44: 575000 | I44: -575000 | J44: 2
A45: 43738 | B45: 43738 | C45: 2019Q3 | D45: 5300 | E45: Fund administration fees | F45: 4.1 accruals & expenses | G45: 45000 | I45: 45000 | J45: 2
A46: 43738 | B46: 43738 | C46: 2019Q3 | D46: 5200 | E46: Professional fees - audit and tax | F46: 4.1 accruals & expenses | G46: 30000 | I46: 30000 | J46: 2
A47: 43738 | B47: 43738 | C47: 2019Q3 | D47: 5210 | E47: Professional fees - legal | F47: 4.1 accruals & expenses | G47: 35000 | I47: 35000 | J47: 2
A48: 43738 | B48: 43738 | C48: 2019Q3 | D48: 5400 | E48: Custody and bank fees | F48: 4.1 accruals & expenses | G48: 5000 | I48: 5000 | J48: 2
A49: 43738 | B49: 43738 | C49: 2019Q3 | D49: 5600 | E49: Other fund expenses | F49: 4.1 accruals & expenses | G49: 12000 | I49: 12000 | J49: 2
A50: 43738 | B50: 43738 | C50: 2019Q3 | D50: 2000 | E50: Accounts payable and accrued expenses | F50: 4.1 accruals & expenses | H50: 127000 | I50: -127000 | J50: 2
A51: 43738 | B51: 43738 | C51: 2019Q3 | D51: 2000 | E51: Accounts payable and accrued expenses | F51: 4.1 accruals & expenses | G51: 127000 | I51: 127000 | J51: 2
A52: 43738 | B52: 43738 | C52: 2019Q3 | D52: 1000 | E52: Cash and cash equivalents | F52: 4.1 accruals & expenses | H52: 127000 | I52: -127000 | J52: 2
A53: 43830 | B53: 43830 | C53: 2019Q4 | D53: 1000 | E53: Cash and cash equivalents | F53: 1.2 closes/equalization | G53: 16141001 | I53: 16141001 | J53: 3
A54: 43830 | B54: 43830 | C54: 2019Q4 | D54: 3000 | E54: Partners' capital - contributions | F54: 1.2 closes/equalization | H54: 16141001 | I54: -16141001 | J54: 3
A55: 43830 | B55: 43830 | C55: 2019Q4 | D55: 3000 | E55: Partners' capital - contributions | F55: 1.2 closes/equalization | G55: 16141001 | I55: 16141001 | J55: 3
A56: 43830 | B56: 43830 | C56: 2019Q4 | D56: 1000 | E56: Cash and cash equivalents | F56: 1.2 closes/equalization | H56: 16141001 | I56: -16141001 | J56: 3
A57: 43830 | B57: 43830 | C57: 2019Q4 | D57: 1000 | E57: Cash and cash equivalents | F57: 2.1 capital calls | G57: 1000000 | I57: 1000000 | J57: 3
A58: 43830 | B58: 43830 | C58: 2019Q4 | D58: 3000 | E58: Partners' capital - contributions | F58: 2.1 capital calls | H58: 1000000 | I58: -1000000 | J58: 3
A59: 43830 | B59: 43830 | C59: 2019Q4 | D59: 5000 | E59: Management fee | F59: 2.2 management fees | G59: 875000 | I59: 875000 | J59: 3
A60: 43830 | B60: 43830 | C60: 2019Q4 | D60: 2100 | E60: Management fee payable | F60: 2.2 management fees | H60: 875000 | I60: -875000 | J60: 3
A61: 43830 | B61: 43830 | C61: 2019Q4 | D61: 2100 | E61: Management fee payable | F61: 2.2 management fees | G61: 875000 | I61: 875000 | J61: 3
A62: 43830 | B62: 43830 | C62: 2019Q4 | D62: 1000 | E62: Cash and cash equivalents | F62: 2.2 management fees | H62: 875000 | I62: -875000 | J62: 3
A63: 43830 | B63: 43830 | C63: 2019Q4 | D63: 5300 | E63: Fund administration fees | F63: 4.1 accruals & expenses | G63: 45000 | I63: 45000 | J63: 3
A64: 43830 | B64: 43830 | C64: 2019Q4 | D64: 5200 | E64: Professional fees - audit and tax | F64: 4.1 accruals & expenses | G64: 30000 | I64: 30000 | J64: 3
A65: 43830 | B65: 43830 | C65: 2019Q4 | D65: 5210 | E65: Professional fees - legal | F65: 4.1 accruals & expenses | G65: 35000 | I65: 35000 | J65: 3
A66: 43830 | B66: 43830 | C66: 2019Q4 | D66: 5400 | E66: Custody and bank fees | F66: 4.1 accruals & expenses | G66: 5000 | I66: 5000 | J66: 3
A67: 43830 | B67: 43830 | C67: 2019Q4 | D67: 5600 | E67: Other fund expenses | F67: 4.1 accruals & expenses | G67: 12000 | I67: 12000 | J67: 3
A68: 43830 | B68: 43830 | C68: 2019Q4 | D68: 2000 | E68: Accounts payable and accrued expenses | F68: 4.1 accruals & expenses | H68: 127000 | I68: -127000 | J68: 3
A69: 43830 | B69: 43830 | C69: 2019Q4 | D69: 2000 | E69: Accounts payable and accrued expenses | F69: 4.1 accruals & expenses | G69: 127000 | I69: 127000 | J69: 3
A70: 43830 | B70: 43830 | C70: 2019Q4 | D70: 1000 | E70: Cash and cash equivalents | F70: 4.1 accruals & expenses | H70: 127000 | I70: -127000 | J70: 3
A71: 43830 | B71: 43830 | C71: 2019Q4 | D71: 1110 | E71: Unrealized appreciation/(depreciation) on investments | F71: 3.3 fair value marks | G71: 1500000 | I71: 1500000 | J71: 3
A72: 43830 | B72: 43830 | C72: 2019Q4 | D72: 6100 | E72: Net change in unrealized appreciation/(depreciation) | F72: 3.3 fair value marks | H72: 1500000 | I72: -1500000 | J72: 3
A73: 43921 | B73: 43921 | C73: 2020Q1 | D73: 1000 | E73: Cash and cash equivalents | F73: 2.1 capital calls | G73: 31000000 | I73: 31000000 | J73: 4
A74: 43921 | B74: 43921 | C74: 2020Q1 | D74: 3000 | E74: Partners' capital - contributions | F74: 2.1 capital calls | H74: 31000000 | I74: -31000000 | J74: 4
A75: 43921 | B75: 43921 | C75: 2020Q1 | D75: 5000 | E75: Management fee | F75: 2.2 management fees | G75: 875000 | I75: 875000 | J75: 4
A76: 43921 | B76: 43921 | C76: 2020Q1 | D76: 2100 | E76: Management fee payable | F76: 2.2 management fees | H76: 875000 | I76: -875000 | J76: 4
A77: 43921 | B77: 43921 | C77: 2020Q1 | D77: 2100 | E77: Management fee payable | F77: 2.2 management fees | G77: 875000 | I77: 875000 | J77: 4
A78: 43921 | B78: 43921 | C78: 2020Q1 | D78: 1000 | E78: Cash and cash equivalents | F78: 2.2 management fees | H78: 875000 | I78: -875000 | J78: 4
A79: 43921 | B79: 43921 | C79: 2020Q1 | D79: 5300 | E79: Fund administration fees | F79: 4.1 accruals & expenses | G79: 62500 | I79: 62500 | J79: 4
A80: 43921 | B80: 43921 | C80: 2020Q1 | D80: 5200 | E80: Professional fees - audit and tax | F80: 4.1 accruals & expenses | G80: 45000 | I80: 45000 | J80: 4
A81: 43921 | B81: 43921 | C81: 2020Q1 | D81: 5210 | E81: Professional fees - legal | F81: 4.1 accruals & expenses | G81: 18000 | I81: 18000 | J81: 4
A82: 43921 | B82: 43921 | C82: 2020Q1 | D82: 5400 | E82: Custody and bank fees | F82: 4.1 accruals & expenses | G82: 7500 | I82: 7500 | J82: 4
A83: 43921 | B83: 43921 | C83: 2020Q1 | D83: 5600 | E83: Other fund expenses | F83: 4.1 accruals & expenses | G83: 9000 | I83: 9000 | J83: 4
A84: 43921 | B84: 43921 | C84: 2020Q1 | D84: 2000 | E84: Accounts payable and accrued expenses | F84: 4.1 accruals & expenses | H84: 142000 | I84: -142000 | J84: 4
A85: 43921 | B85: 43921 | C85: 2020Q1 | D85: 2000 | E85: Accounts payable and accrued expenses | F85: 4.1 accruals & expenses | G85: 142000 | I85: 142000 | J85: 4
A86: 43921 | B86: 43921 | C86: 2020Q1 | D86: 1000 | E86: Cash and cash equivalents | F86: 4.1 accruals & expenses | H86: 142000 | I86: -142000 | J86: 4
A87: 43921 | B87: 43921 | C87: 2020Q1 | D87: 1100 | E87: Investments, at cost | F87: 3.1 recording investments | G87: 30000000 | I87: 30000000 | J87: 4
A88: 43921 | B88: 43921 | C88: 2020Q1 | D88: 1000 | E88: Cash and cash equivalents | F88: 3.1 recording investments | H88: 30000000 | I88: -30000000 | J88: 4
A89: 44012 | B89: 44012 | C89: 2020Q2 | D89: 1000 | E89: Cash and cash equivalents | F89: 1.2 closes/equalization | G89: 23222108 | I89: 23222108 | J89: 5
A90: 44012 | B90: 44012 | C90: 2020Q2 | D90: 3000 | E90: Partners' capital - contributions | F90: 1.2 closes/equalization | H90: 23222108 | I90: -23222108 | J90: 5
A91: 44012 | B91: 44012 | C91: 2020Q2 | D91: 3000 | E91: Partners' capital - contributions | F91: 1.2 closes/equalization | G91: 23222108 | I91: 23222108 | J91: 5
A92: 44012 | B92: 44012 | C92: 2020Q2 | D92: 1000 | E92: Cash and cash equivalents | F92: 1.2 closes/equalization | H92: 23222108 | I92: -23222108 | J92: 5
A93: 44012 | B93: 44012 | C93: 2020Q2 | D93: 1000 | E93: Cash and cash equivalents | F93: 2.1 capital calls | G93: 1400000 | I93: 1400000 | J93: 5
A94: 44012 | B94: 44012 | C94: 2020Q2 | D94: 3000 | E94: Partners' capital - contributions | F94: 2.1 capital calls | H94: 1400000 | I94: -1400000 | J94: 5
A95: 44012 | B95: 44012 | C95: 2020Q2 | D95: 5000 | E95: Management fee | F95: 2.2 management fees | G95: 1225000 | I95: 1225000 | J95: 5
A96: 44012 | B96: 44012 | C96: 2020Q2 | D96: 2100 | E96: Management fee payable | F96: 2.2 management fees | H96: 1225000 | I96: -1225000 | J96: 5
A97: 44012 | B97: 44012 | C97: 2020Q2 | D97: 2100 | E97: Management fee payable | F97: 2.2 management fees | G97: 1225000 | I97: 1225000 | J97: 5
A98: 44012 | B98: 44012 | C98: 2020Q2 | D98: 1000 | E98: Cash and cash equivalents | F98: 2.2 management fees | H98: 1225000 | I98: -1225000 | J98: 5
A99: 44012 | B99: 44012 | C99: 2020Q2 | D99: 5300 | E99: Fund administration fees | F99: 4.1 accruals & expenses | G99: 62500 | I99: 62500 | J99: 5
A100: 44012 | B100: 44012 | C100: 2020Q2 | D100: 5200 | E100: Professional fees - audit and tax | F100: 4.1 accruals & expenses | G100: 45000 | I100: 45000 | J100: 5
A101: 44012 | B101: 44012 | C101: 2020Q2 | D101: 5210 | E101: Professional fees - legal | F101: 4.1 accruals & expenses | G101: 18000 | I101: 18000 | J101: 5
...

Sheet Trial Balance
A1: Trial Balance
A2: Cumulative net balance by account at each year end. SUMIFS over Journal Entries.
A4: Account no. | B4: Account name | C4: Normal | D4: FY2019 | E4: FY2020 | F4: FY2021 | G4: FY2022 | H4: FY2023 | I4: FY2024 | J4: FY2025 | K4: FY2026 | L4: FY2027 | M4: FY2028 | N4: FY2029 | O4: FY2030
A5: 1000 | B5: Cash and cash equivalents | C5: Dr | D5: =SUMIFS('Journal Entries'!$I$5:$I$785,'Journal Entries'!$D$5:$D$785,"1000",'Journal Entries'!$J$5:$J$785,"<=3") -> 292000 | E5: =SUMIFS('Journal Entries'!$I$5:$I$785,'Journal Entries'!$D$5:$D$785,"1000",'Journal Entries'!$J$5:$J$785,"<=7") -> 274000 | F5: =SUMIFS('Journal Entries'!$I$5:$I$785,'Journal Entries'!$D$5:$D$785,"1000",'Journal Entries'!$J$5:$J$785,"<=11") -> 2056000 | G5: =SUMIFS('Journal Entries'!$I$5:$I$785,'Journal Entries'!$D$5:$D$785,"1000",'Journal Entries'!$J$5:$J$785,"<=15") -> 1788000 | H5: =SUMIFS('Journal Entries'!$I$5:$I$785,'Journal Entries'!$D$5:$D$785,"1000",'Journal Entries'!$J$5:$J$785,"<=19") -> 1320000 | I5: =SUMIFS('Journal Entries'!$I$5:$I$785,'Journal Entries'!$D$5:$D$785,"1000",'Journal Entries'!$J$5:$J$785,"<=23") -> 1702000 | J5: =SUMIFS('Journal Entries'!$I$5:$I$785,'Journal Entries'!$D$5:$D$785,"1000",'Journal Entries'!$J$5:$J$785,"<=27") -> 1758000 | K5: =SUMIFS('Journal Entries'!$I$5:$I$785,'Journal Entries'!$D$5:$D$785,"1000",'Journal Entries'!$J$5:$J$785,"<=31") -> 304000 | L5: =SUMIFS('Journal Entries'!$I$5:$I$785,'Journal Entries'!$D$5:$D$785,"1000",'Journal Entries'!$J$5:$J$785,"<=35") -> 2075000 | M5: =SUMIFS('Journal Entries'!$I$5:$I$785,'Journal Entries'!$D$5:$D$785,"1000",'Journal Entries'!$J$5:$J$785,"<=39") -> 3058277.7 | N5: =SUMIFS('Journal Entries'!$I$5:$I$785,'Journal Entries'!$D$5:$D$785,"1000",'Journal Entries'!$J$5:$J$785,"<=43") -> 2734277.7 | O5: =SUMIFS('Journal Entries'!$I$5:$I$785,'Journal Entries'!$D$5:$D$785,"1000",'Journal Entries'!$J$5:$J$785,"<=45") -> 2.7939677e-09
A6: 1050 | B6: Subscriptions receivable | C6: Dr | D6: =SUMIFS('Journal Entries'!$I$5:$I$785,'Journal Entries'!$D$5:$D$785,"1050",'Journal Entries'!$J$5:$J$785,"<=3") -> 0 | E6: =SUMIFS('Journal Entries'!$I$5:$I$785,'Journal Entries'!$D$5:$D$785,"1050",'Journal Entries'!$J$5:$J$785,"<=7") -> 0 | F6: =SUMIFS('Journal Entries'!$I$5:$I$785,'Journal Entries'!$D$5:$D$785,"1050",'Journal Entries'!$J$5:$J$785,"<=11") -> 0 | G6: =SUMIFS('Journal Entries'!$I$5:$I$785,'Journal Entries'!$D$5:$D$785,"1050",'Journal Entries'!$J$5:$J$785,"<=15") -> 0 | H6: =SUMIFS('Journal Entries'!$I$5:$I$785,'Journal Entries'!$D$5:$D$785,"1050",'Journal Entries'!$J$5:$J$785,"<=19") -> 0 | I6: =SUMIFS('Journal Entries'!$I$5:$I$785,'Journal Entries'!$D$5:$D$785,"1050",'Journal Entries'!$J$5:$J$785,"<=23") -> 0 | J6: =SUMIFS('Journal Entries'!$I$5:$I$785,'Journal Entries'!$D$5:$D$785,"1050",'Journal Entries'!$J$5:$J$785,"<=27") -> 0 | K6: =SUMIFS('Journal Entries'!$I$5:$I$785,'Journal Entries'!$D$5:$D$785,"1050",'Journal Entries'!$J$5:$J$785,"<=31") -> 0 | L6: =SUMIFS('Journal Entries'!$I$5:$I$785,'Journal Entries'!$D$5:$D$785,"1050",'Journal Entries'!$J$5:$J$785,"<=35") -> 0 | M6: =SUMIFS('Journal Entries'!$I$5:$I$785,'Journal Entries'!$D$5:$D$785,"1050",'Journal Entries'!$J$5:$J$785,"<=39") -> 0 | N6: =SUMIFS('Journal Entries'!$I$5:$I$785,'Journal Entries'!$D$5:$D$785,"1050",'Journal Entries'!$J$5:$J$785,"<=43") -> 0 | O6: =SUMIFS('Journal Entries'!$I$5:$I$785,'Journal Entries'!$D$5:$D$785,"1050",'Journal Entries'!$J$5:$J$785,"<=45") -> 0
A7: 1100 | B7: Investments, at cost | C7: Dr | D7: =SUMIFS('Journal Entries'!$I$5:$I$785,'Journal Entries'!$D$5:$D$785,"1100",'Journal Entries'!$J$5:$J$785,"<=3") -> 42000000 | E7: =SUMIFS('Journal Entries'!$I$5:$I$785,'Journal Entries'!$D$5:$D$785,"1100",'Journal Entries'!$J$5:$J$785,"<=7") -> 95750000 | F7: =SUMIFS('Journal Entries'!$I$5:$I$785,'Journal Entries'!$D$5:$D$785,"1100",'Journal Entries'!$J$5:$J$785,"<=11") -> 145000000 | G7: =SUMIFS('Journal Entries'!$I$5:$I$785,'Journal Entries'!$D$5:$D$785,"1100",'Journal Entries'!$J$5:$J$785,"<=15") -> 172298178 | H7: =SUMIFS('Journal Entries'!$I$5:$I$785,'Journal Entries'!$D$5:$D$785,"1100",'Journal Entries'!$J$5:$J$785,"<=19") -> 1.8321823e+08 | I7: =SUMIFS('Journal Entries'!$I$5:$I$785,'Journal Entries'!$D$5:$D$785,"1100",'Journal Entries'!$J$5:$J$785,"<=23") -> 1.3537927e+08 | J7: =SUMIFS('Journal Entries'!$I$5:$I$785,'Journal Entries'!$D$5:$D$785,"1100",'Journal Entries'!$J$5:$J$785,"<=27") -> 1.1381154e+08 | K7: =SUMIFS('Journal Entries'!$I$5:$I$785,'Journal Entries'!$D$5:$D$785,"1100",'Journal Entries'!$J$5:$J$785,"<=31") -> 1.1654908e+08 | L7: =SUMIFS('Journal Entries'!$I$5:$I$785,'Journal Entries'!$D$5:$D$785,"1100",'Journal Entries'!$J$5:$J$785,"<=35") -> 84630211 | M7: =SUMIFS('Journal Entries'!$I$5:$I$785,'Journal Entries'!$D$5:$D$785,"1100",'Journal Entries'!$J$5:$J$785,"<=39") -> 18000000 | N7: =SUMIFS('Journal Entries'!$I$5:$I$785,'Journal Entries'!$D$5:$D$785,"1100",'Journal Entries'!$J$5:$J$785,"<=43") -> 2.6077032e-08 | O7: =SUMIFS('Journal Entries'!$I$5:$I$785,'Journal Entries'!$D$5:$D$785,"1100",'Journal Entries'!$J$5:$J$785,"<=45") -> 2.6077032e-08
A8: 1110 | B8: Unrealized appreciation/(depreciation) on investments | C8: Dr | D8: =SUMIFS('Journal Entries'!$I$5:$I$785,'Journal Entries'!$D$5:$D$785,"1110",'Journal Entries'!$J$5:$J$785,"<=3") -> 1500000 | E8: =SUMIFS('Journal Entries'!$I$5:$I$785,'Journal Entries'!$D$5:$D$785,"1110",'Journal Entries'!$J$5:$J$785,"<=7") -> 9000000 | F8: =SUMIFS('Journal Entries'!$I$5:$I$785,'Journal Entries'!$D$5:$D$785,"1110",'Journal Entries'!$J$5:$J$785,"<=11") -> 39000000 | G8: =SUMIFS('Journal Entries'!$I$5:$I$785,'Journal Entries'!$D$5:$D$785,"1110",'Journal Entries'!$J$5:$J$785,"<=15") -> 35000000 | H8: =SUMIFS('Journal Entries'!$I$5:$I$785,'Journal Entries'!$D$5:$D$785,"1110",'Journal Entries'!$J$5:$J$785,"<=19") -> 66000000 | I8: =SUMIFS('Journal Entries'!$I$5:$I$785,'Journal Entries'!$D$5:$D$785,"1110",'Journal Entries'!$J$5:$J$785,"<=23") -> 51000000 | J8: =SUMIFS('Journal Entries'!$I$5:$I$785,'Journal Entries'!$D$5:$D$785,"1110",'Journal Entries'!$J$5:$J$785,"<=27") -> 62500000 | K8: =SUMIFS('Journal Entries'!$I$5:$I$785,'Journal Entries'!$D$5:$D$785,"1110",'Journal Entries'!$J$5:$J$785,"<=31") -> 78000000 | L8: =SUMIFS('Journal Entries'!$I$5:$I$785,'Journal Entries'!$D$5:$D$785,"1110",'Journal Entries'!$J$5:$J$785,"<=35") -> 64000000 | M8: =SUMIFS('Journal Entries'!$I$5:$I$785,'Journal Entries'!$D$5:$D$785,"1110",'Journal Entries'!$J$5:$J$785,"<=39") -> 28000000 | N8: =SUMIFS('Journal Entries'!$I$5:$I$785,'Journal Entries'!$D$5:$D$785,"1110",'Journal Entries'!$J$5:$J$785,"<=43") -> 0 | O8: =SUMIFS('Journal Entries'!$I$5:$I$785,'Journal Entries'!$D$5:$D$785,"1110",'Journal Entries'!$J$5:$J$785,"<=45") -> 0
A9: 1150 | B9: Investments, at cost - bridge notes | C9: Dr | D9: =SUMIFS('Journal Entries'!$I$5:$I$785,'Journal Entries'!$D$5:$D$785,"1150",'Journal Entries'!$J$5:$J$785,"<=3") -> 0 | E9: =SUMIFS('Journal Entries'!$I$5:$I$785,'Journal Entries'!$D$5:$D$785,"1150",'Journal Entries'!$J$5:$J$785,"<=7") -> 1250000 | F9: =SUMIFS('Journal Entries'!$I$5:$I$785,'Journal Entries'!$D$5:$D$785,"1150",'Journal Entries'!$J$5:$J$785,"<=11") -> 0 | G9: =SUMIFS('Journal Entries'!$I$5:$I$785,'Journal Entries'!$D$5:$D$785,"1150",'Journal Entries'!$J$5:$J$785,"<=15") -> 0 | H9: =SUMIFS('Journal Entries'!$I$5:$I$785,'Journal Entries'!$D$5:$D$785,"1150",'Journal Entries'!$J$5:$J$785,"<=19") -> 0 | I9: =SUMIFS('Journal Entries'!$I$5:$I$785,'Journal Entries'!$D$5:$D$785,"1150",'Journal Entries'!$J$5:$J$785,"<=23") -> 0 | J9: =SUMIFS('Journal Entries'!$I$5:$I$785,'Journal Entries'!$D$5:$D$785,"1150",'Journal Entries'!$J$5:$J$785,"<=27") -> 0 | K9: =SUMIFS('Journal Entries'!$I$5:$I$785,'Journal Entries'!$D$5:$D$785,"1150",'Journal Entries'!$J$5:$J$785,"<=31") -> 0 | L9: =SUMIFS('Journal Entries'!$I$5:$I$785,'Journal Entries'!$D$5:$D$785,"1150",'Journal Entries'!$J$5:$J$785,"<=35") -> 0 | M9: =SUMIFS('Journal Entries'!$I$5:$I$785,'Journal Entries'!$D$5:$D$785,"1150",'Journal Entries'!$J$5:$J$785,"<=39") -> 0 | N9: =SUMIFS('Journal Entries'!$I$5:$I$785,'Journal Entries'!$D$5:$D$785,"1150",'Journal Entries'!$J$5:$J$785,"<=43") -> 0 | O9: =SUMIFS('Journal Entries'!$I$5:$I$785,'Journal Entries'!$D$5:$D$785,"1150",'Journal Entries'!$J$5:$J$785,"<=45") -> 0
A10: 1200 | B10: Interest and PIK receivable | C10: Dr | D10: =SUMIFS('Journal Entries'!$I$5:$I$785,'Journal Entries'!$D$5:$D$785,"1200",'Journal Entries'!$J$5:$J$785,"<=3") -> 0 | E10: =SUMIFS('Journal Entries'!$I$5:$I$785,'Journal Entries'!$D$5:$D$785,"1200",'Journal Entries'!$J$5:$J$785,"<=7") -> 0 | F10: =SUMIFS('Journal Entries'!$I$5:$I$785,'Journal Entries'!$D$5:$D$785,"1200",'Journal Entries'!$J$5:$J$785,"<=11") -> 0 | G10: =SUMIFS('Journal Entries'!$I$5:$I$785,'Journal Entries'!$D$5:$D$785,"1200",'Journal Entries'!$J$5:$J$785,"<=15") -> 0 | H10: =SUMIFS('Journal Entries'!$I$5:$I$785,'Journal Entries'!$D$5:$D$785,"1200",'Journal Entries'!$J$5:$J$785,"<=19") -> 0 | I10: =SUMIFS('Journal Entries'!$I$5:$I$785,'Journal Entries'!$D$5:$D$785,"1200",'Journal Entries'!$J$5:$J$785,"<=23") -> 0 | J10: =SUMIFS('Journal Entries'!$I$5:$I$785,'Journal Entries'!$D$5:$D$785,"1200",'Journal Entries'!$J$5:$J$785,"<=27") -> 0 | K10: =SUMIFS('Journal Entries'!$I$5:$I$785,'Journal Entries'!$D$5:$D$785,"1200",'Journal Entries'!$J$5:$J$785,"<=31") -> 0 | L10: =SUMIFS('Journal Entries'!$I$5:$I$785,'Journal Entries'!$D$5:$D$785,"1200",'Journal Entries'!$J$5:$J$785,"<=35") -> 0 | M10: =SUMIFS('Journal Entries'!$I$5:$I$785,'Journal Entries'!$D$5:$D$785,"1200",'Journal Entries'!$J$5:$J$785,"<=39") -> 0 | N10: =SUMIFS('Journal Entries'!$I$5:$I$785,'Journal Entries'!$D$5:$D$785,"1200",'Journal Entries'!$J$5:$J$785,"<=43") -> 0 | O10: =SUMIFS('Journal Entries'!$I$5:$I$785,'Journal Entries'!$D$5:$D$785,"1200",'Journal Entries'!$J$5:$J$785,"<=45") -> 0
A11: 1250 | B11: Prepaid management fee | C11: Dr | D11: =SUMIFS('Journal Entries'!$I$5:$I$785,'Journal Entries'!$D$5:$D$785,"1250",'Journal Entries'!$J$5:$J$785,"<=3") -> 0 | E11: =SUMIFS('Journal Entries'!$I$5:$I$785,'Journal Entries'!$D$5:$D$785,"1250",'Journal Entries'!$J$5:$J$785,"<=7") -> 0 | F11: =SUMIFS('Journal Entries'!$I$5:$I$785,'Journal Entries'!$D$5:$D$785,"1250",'Journal Entries'!$J$5:$J$785,"<=11") -> 0 | G11: =SUMIFS('Journal Entries'!$I$5:$I$785,'Journal Entries'!$D$5:$D$785,"1250",'Journal Entries'!$J$5:$J$785,"<=15") -> 0 | H11: =SUMIFS('Journal Entries'!$I$5:$I$785,'Journal Entries'!$D$5:$D$785,"1250",'Journal Entries'!$J$5:$J$785,"<=19") -> 0 | I11: =SUMIFS('Journal Entries'!$I$5:$I$785,'Journal Entries'!$D$5:$D$785,"1250",'Journal Entries'!$J$5:$J$785,"<=23") -> 0 | J11: =SUMIFS('Journal Entries'!$I$5:$I$785,'Journal Entries'!$D$5:$D$785,"1250",'Journal Entries'!$J$5:$J$785,"<=27") -> 0 | K11: =SUMIFS('Journal Entries'!$I$5:$I$785,'Journal Entries'!$D$5:$D$785,"1250",'Journal Entries'!$J$5:$J$785,"<=31") -> 0 | L11: =SUMIFS('Journal Entries'!$I$5:$I$785,'Journal Entries'!$D$5:$D$785,"1250",'Journal Entries'!$J$5:$J$785,"<=35") -> 0 | M11: =SUMIFS('Journal Entries'!$I$5:$I$785,'Journal Entries'!$D$5:$D$785,"1250",'Journal Entries'!$J$5:$J$785,"<=39") -> 0 | N11: =SUMIFS('Journal Entries'!$I$5:$I$785,'Journal Entries'!$D$5:$D$785,"1250",'Journal Entries'!$J$5:$J$785,"<=43") -> 0 | O11: =SUMIFS('Journal Entries'!$I$5:$I$785,'Journal Entries'!$D$5:$D$785,"1250",'Journal Entries'!$J$5:$J$785,"<=45") -> 0
A12: 1300 | B12: Deferred offering costs | C12: Dr | D12: =SUMIFS('Journal Entries'!$I$5:$I$785,'Journal Entries'!$D$5:$D$785,"1300",'Journal Entries'!$J$5:$J$785,"<=3") -> 0 | E12: =SUMIFS('Journal Entries'!$I$5:$I$785,'Journal Entries'!$D$5:$D$785,"1300",'Journal Entries'!$J$5:$J$785,"<=7") -> 0 | F12: =SUMIFS('Journal Entries'!$I$5:$I$785,'Journal Entries'!$D$5:$D$785,"1300",'Journal Entries'!$J$5:$J$785,"<=11") -> 0 | G12: =SUMIFS('Journal Entries'!$I$5:$I$785,'Journal Entries'!$D$5:$D$785,"1300",'Journal Entries'!$J$5:$J$785,"<=15") -> 0 | H12: =SUMIFS('Journal Entries'!$I$5:$I$785,'Journal Entries'!$D$5:$D$785,"1300",'Journal Entries'!$J$5:$J$785,"<=19") -> 0 | I12: =SUMIFS('Journal Entries'!$I$5:$I$785,'Journal Entries'!$D$5:$D$785,"1300",'Journal Entries'!$J$5:$J$785,"<=23") -> 0 | J12: =SUMIFS('Journal Entries'!$I$5:$I$785,'Journal Entries'!$D$5:$D$785,"1300",'Journal Entries'!$J$5:$J$785,"<=27") -> 0 | K12: =SUMIFS('Journal Entries'!$I$5:$I$785,'Journal Entries'!$D$5:$D$785,"1300",'Journal Entries'!$J$5:$J$785,"<=31") -> 0 | L12: =SUMIFS('Journal Entries'!$I$5:$I$785,'Journal Entries'!$D$5:$D$785,"1300",'Journal Entries'!$J$5:$J$785,"<=35") -> 0 | M12: =SUMIFS('Journal Entries'!$I$5:$I$785,'Journal Entries'!$D$5:$D$785,"1300",'Journal Entries'!$J$5:$J$785,"<=39") -> 0 | N12: =SUMIFS('Journal Entries'!$I$5:$I$785,'Journal Entries'!$D$5:$D$785,"1300",'Journal Entries'!$J$5:$J$785,"<=43") -> 0 | O12: =SUMIFS('Journal Entries'!$I$5:$I$785,'Journal Entries'!$D$5:$D$785,"1300",'Journal Entries'!$J$5:$J$785,"<=45") -> 0
A13: 2000 | B13: Accounts payable and accrued expenses | C13: Cr | D13: =SUMIFS('Journal Entries'!$I$5:$I$785,'Journal Entries'!$D$5:$D$785,"2000",'Journal Entries'!$J$5:$J$785,"<=3") -> 0 | E13: =SUMIFS('Journal Entries'!$I$5:$I$785,'Journal Entries'!$D$5:$D$785,"2000",'Journal Entries'!$J$5:$J$785,"<=7") -> 0 | F13: =SUMIFS('Journal Entries'!$I$5:$I$785,'Journal Entries'!$D$5:$D$785,"2000",'Journal Entries'!$J$5:$J$785,"<=11") -> 0 | G13: =SUMIFS('Journal Entries'!$I$5:$I$785,'Journal Entries'!$D$5:$D$785,"2000",'Journal Entries'!$J$5:$J$785,"<=15") -> 0 | H13: =SUMIFS('Journal Entries'!$I$5:$I$785,'Journal Entries'!$D$5:$D$785,"2000",'Journal Entries'!$J$5:$J$785,"<=19") -> 0 | I13: =SUMIFS('Journal Entries'!$I$5:$I$785,'Journal Entries'!$D$5:$D$785,"2000",'Journal Entries'!$J$5:$J$785,"<=23") -> 0 | J13: =SUMIFS('Journal Entries'!$I$5:$I$785,'Journal Entries'!$D$5:$D$785,"2000",'Journal Entries'!$J$5:$J$785,"<=27") -> 0 | K13: =SUMIFS('Journal Entries'!$I$5:$I$785,'Journal Entries'!$D$5:$D$785,"2000",'Journal Entries'!$J$5:$J$785,"<=31") -> 0 | L13: =SUMIFS('Journal Entries'!$I$5:$I$785,'Journal Entries'!$D$5:$D$785,"2000",'Journal Entries'!$J$5:$J$785,"<=35") -> 0 | M13: =SUMIFS('Journal Entries'!$I$5:$I$785,'Journal Entries'!$D$5:$D$785,"2000",'Journal Entries'!$J$5:$J$785,"<=39") -> 0 | N13: =SUMIFS('Journal Entries'!$I$5:$I$785,'Journal Entries'!$D$5:$D$785,"2000",'Journal Entries'!$J$5:$J$785,"<=43") -> 0 | O13: =SUMIFS('Journal Entries'!$I$5:$I$785,'Journal Entries'!$D$5:$D$785,"2000",'Journal Entries'!$J$5:$J$785,"<=45") -> 0
A14: 2100 | B14: Management fee payable | C14: Cr | D14: =SUMIFS('Journal Entries'!$I$5:$I$785,'Journal Entries'!$D$5:$D$785,"2100",'Journal Entries'!$J$5:$J$785,"<=3") -> 0 | E14: =SUMIFS('Journal Entries'!$I$5:$I$785,'Journal Entries'!$D$5:$D$785,"2100",'Journal Entries'!$J$5:$J$785,"<=7") -> 0 | F14: =SUMIFS('Journal Entries'!$I$5:$I$785,'Journal Entries'!$D$5:$D$785,"2100",'Journal Entries'!$J$5:$J$785,"<=11") -> 0 | G14: =SUMIFS('Journal Entries'!$I$5:$I$785,'Journal Entries'!$D$5:$D$785,"2100",'Journal Entries'!$J$5:$J$785,"<=15") -> 0 | H14: =SUMIFS('Journal Entries'!$I$5:$I$785,'Journal Entries'!$D$5:$D$785,"2100",'Journal Entries'!$J$5:$J$785,"<=19") -> 0 | I14: =SUMIFS('Journal Entries'!$I$5:$I$785,'Journal Entries'!$D$5:$D$785,"2100",'Journal Entries'!$J$5:$J$785,"<=23") -> 0 | J14: =SUMIFS('Journal Entries'!$I$5:$I$785,'Journal Entries'!$D$5:$D$785,"2100",'Journal Entries'!$J$5:$J$785,"<=27") -> 0 | K14: =SUMIFS('Journal Entries'!$I$5:$I$785,'Journal Entries'!$D$5:$D$785,"2100",'Journal Entries'!$J$5:$J$785,"<=31") -> 0 | L14: =SUMIFS('Journal Entries'!$I$5:$I$785,'Journal Entries'!$D$5:$D$785,"2100",'Journal Entries'!$J$5:$J$785,"<=35") -> 0 | M14: =SUMIFS('Journal Entries'!$I$5:$I$785,'Journal Entries'!$D$5:$D$785,"2100",'Journal Entries'!$J$5:$J$785,"<=39") -> 0 | N14: =SUMIFS('Journal Entries'!$I$5:$I$785,'Journal Entries'!$D$5:$D$785,"2100",'Journal Entries'!$J$5:$J$785,"<=43") -> 0 | O14: =SUMIFS('Journal Entries'!$I$5:$I$785,'Journal Entries'!$D$5:$D$785,"2100",'Journal Entries'!$J$5:$J$785,"<=45") -> 0
A15: 2300 | B15: Subscription line payable | C15: Cr | D15: =SUMIFS('Journal Entries'!$I$5:$I$785,'Journal Entries'!$D$5:$D$785,"2300",'Journal Entries'!$J$5:$J$785,"<=3") -> 0 | E15: =SUMIFS('Journal Entries'!$I$5:$I$785,'Journal Entries'!$D$5:$D$785,"2300",'Journal Entries'!$J$5:$J$785,"<=7") -> 0 | F15: =SUMIFS('Journal Entries'!$I$5:$I$785,'Journal Entries'!$D$5:$D$785,"2300",'Journal Entries'!$J$5:$J$785,"<=11") -> 0 | G15: =SUMIFS('Journal Entries'!$I$5:$I$785,'Journal Entries'!$D$5:$D$785,"2300",'Journal Entries'!$J$5:$J$785,"<=15") -> 0 | H15: =SUMIFS('Journal Entries'!$I$5:$I$785,'Journal Entries'!$D$5:$D$785,"2300",'Journal Entries'!$J$5:$J$785,"<=19") -> 0 | I15: =SUMIFS('Journal Entries'!$I$5:$I$785,'Journal Entries'!$D$5:$D$785,"2300",'Journal Entries'!$J$5:$J$785,"<=23") -> 0 | J15: =SUMIFS('Journal Entries'!$I$5:$I$785,'Journal Entries'!$D$5:$D$785,"2300",'Journal Entries'!$J$5:$J$785,"<=27") -> 0 | K15: =SUMIFS('Journal Entries'!$I$5:$I$785,'Journal Entries'!$D$5:$D$785,"2300",'Journal Entries'!$J$5:$J$785,"<=31") -> 0 | L15: =SUMIFS('Journal Entries'!$I$5:$I$785,'Journal Entries'!$D$5:$D$785,"2300",'Journal Entries'!$J$5:$J$785,"<=35") -> 0 | M15: =SUMIFS('Journal Entries'!$I$5:$I$785,'Journal Entries'!$D$5:$D$785,"2300",'Journal Entries'!$J$5:$J$785,"<=39") -> 0 | N15: =SUMIFS('Journal Entries'!$I$5:$I$785,'Journal Entries'!$D$5:$D$785,"2300",'Journal Entries'!$J$5:$J$785,"<=43") -> 0 | O15: =SUMIFS('Journal Entries'!$I$5:$I$785,'Journal Entries'!$D$5:$D$785,"2300",'Journal Entries'!$J$5:$J$785,"<=45") -> 0
A16: 2400 | B16: Distributions payable | C16: Cr | D16: =SUMIFS('Journal Entries'!$I$5:$I$785,'Journal Entries'!$D$5:$D$785,"2400",'Journal Entries'!$J$5:$J$785,"<=3") -> 0 | E16: =SUMIFS('Journal Entries'!$I$5:$I$785,'Journal Entries'!$D$5:$D$785,"2400",'Journal Entries'!$J$5:$J$785,"<=7") -> 0 | F16: =SUMIFS('Journal Entries'!$I$5:$I$785,'Journal Entries'!$D$5:$D$785,"2400",'Journal Entries'!$J$5:$J$785,"<=11") -> 0 | G16: =SUMIFS('Journal Entries'!$I$5:$I$785,'Journal Entries'!$D$5:$D$785,"2400",'Journal Entries'!$J$5:$J$785,"<=15") -> 0 | H16: =SUMIFS('Journal Entries'!$I$5:$I$785,'Journal Entries'!$D$5:$D$785,"2400",'Journal Entries'!$J$5:$J$785,"<=19") -> 0 | I16: =SUMIFS('Journal Entries'!$I$5:$I$785,'Journal Entries'!$D$5:$D$785,"2400",'Journal Entries'!$J$5:$J$785,"<=23") -> 0 | J16: =SUMIFS('Journal Entries'!$I$5:$I$785,'Journal Entries'!$D$5:$D$785,"2400",'Journal Entries'!$J$5:$J$785,"<=27") -> 0 | K16: =SUMIFS('Journal Entries'!$I$5:$I$785,'Journal Entries'!$D$5:$D$785,"2400",'Journal Entries'!$J$5:$J$785,"<=31") -> 0 | L16: =SUMIFS('Journal Entries'!$I$5:$I$785,'Journal Entries'!$D$5:$D$785,"2400",'Journal Entries'!$J$5:$J$785,"<=35") -> 0 | M16: =SUMIFS('Journal Entries'!$I$5:$I$785,'Journal Entries'!$D$5:$D$785,"2400",'Journal Entries'!$J$5:$J$785,"<=39") -> 0 | N16: =SUMIFS('Journal Entries'!$I$5:$I$785,'Journal Entries'!$D$5:$D$785,"2400",'Journal Entries'!$J$5:$J$785,"<=43") -> 0 | O16: =SUMIFS('Journal Entries'!$I$5:$I$785,'Journal Entries'!$D$5:$D$785,"2400",'Journal Entries'!$J$5:$J$785,"<=45") -> 0
A17: 3000 | B17: Partners' capital - contributions | C17: Cr | D17: =SUMIFS('Journal Entries'!$I$5:$I$785,'Journal Entries'!$D$5:$D$785,"3000",'Journal Entries'!$J$5:$J$785,"<=3") -> -47500000 | E17: =SUMIFS('Journal Entries'!$I$5:$I$785,'Journal Entries'!$D$5:$D$785,"3000",'Journal Entries'!$J$5:$J$785,"<=7") -> -107600000 | F17: =SUMIFS('Journal Entries'!$I$5:$I$785,'Journal Entries'!$D$5:$D$785,"3000",'Journal Entries'!$J$5:$J$785,"<=11") -> -162500000 | G17: =SUMIFS('Journal Entries'!$I$5:$I$785,'Journal Entries'!$D$5:$D$785,"3000",'Journal Entries'!$J$5:$J$785,"<=15") -> -193300000 | H17: =SUMIFS('Journal Entries'!$I$5:$I$785,'Journal Entries'!$D$5:$D$785,"3000",'Journal Entries'!$J$5:$J$785,"<=19") -> -206900000 | I17: =SUMIFS('Journal Entries'!$I$5:$I$785,'Journal Entries'!$D$5:$D$785,"3000",'Journal Entries'!$J$5:$J$785,"<=23") -> -209700000 | J17: =SUMIFS('Journal Entries'!$I$5:$I$785,'Journal Entries'!$D$5:$D$785,"3000",'Journal Entries'!$J$5:$J$785,"<=27") -> -211000000 | K17: =SUMIFS('Journal Entries'!$I$5:$I$785,'Journal Entries'!$D$5:$D$785,"3000",'Journal Entries'!$J$5:$J$785,"<=31") -> -212200000 | L17: =SUMIFS('Journal Entries'!$I$5:$I$785,'Journal Entries'!$D$5:$D$785,"3000",'Journal Entries'!$J$5:$J$785,"<=35") -> -213300000 | M17: =SUMIFS('Journal Entries'!$I$5:$I$785,'Journal Entries'!$D$5:$D$785,"3000",'Journal Entries'!$J$5:$J$785,"<=39") -> -213300000 | N17: =SUMIFS('Journal Entries'!$I$5:$I$785,'Journal Entries'!$D$5:$D$785,"3000",'Journal Entries'!$J$5:$J$785,"<=43") -> -213300000 | O17: =SUMIFS('Journal Entries'!$I$5:$I$785,'Journal Entries'!$D$5:$D$785,"3000",'Journal Entries'!$J$5:$J$785,"<=45") -> -213300000
A18: 3050 | B18: Partners' capital - offering costs charged against capital | C18: Cr | D18: =SUMIFS('Journal Entries'!$I$5:$I$785,'Journal Entries'!$D$5:$D$785,"3050",'Journal Entries'!$J$5:$J$785,"<=3") -> 900000 | E18: =SUMIFS('Journal Entries'!$I$5:$I$785,'Journal Entries'!$D$5:$D$785,"3050",'Journal Entries'!$J$5:$J$785,"<=7") -> 900000 | F18: =SUMIFS('Journal Entries'!$I$5:$I$785,'Journal Entries'!$D$5:$D$785,"3050",'Journal Entries'!$J$5:$J$785,"<=11") -> 900000 | G18: =SUMIFS('Journal Entries'!$I$5:$I$785,'Journal Entries'!$D$5:$D$785,"3050",'Journal Entries'!$J$5:$J$785,"<=15") -> 900000 | H18: =SUMIFS('Journal Entries'!$I$5:$I$785,'Journal Entries'!$D$5:$D$785,"3050",'Journal Entries'!$J$5:$J$785,"<=19") -> 900000 | I18: =SUMIFS('Journal Entries'!$I$5:$I$785,'Journal Entries'!$D$5:$D$785,"3050",'Journal Entries'!$J$5:$J$785,"<=23") -> 900000 | J18: =SUMIFS('Journal Entries'!$I$5:$I$785,'Journal Entries'!$D$5:$D$785,"3050",'Journal Entries'!$J$5:$J$785,"<=27") -> 900000 | K18: =SUMIFS('Journal Entries'!$I$5:$I$785,'Journal Entries'!$D$5:$D$785,"3050",'Journal Entries'!$J$5:$J$785,"<=31") -> 900000 | L18: =SUMIFS('Journal Entries'!$I$5:$I$785,'Journal Entries'!$D$5:$D$785,"3050",'Journal Entries'!$J$5:$J$785,"<=35") -> 900000 | M18: =SUMIFS('Journal Entries'!$I$5:$I$785,'Journal Entries'!$D$5:$D$785,"3050",'Journal Entries'!$J$5:$J$785,"<=39") -> 900000 | N18: =SUMIFS('Journal Entries'!$I$5:$I$785,'Journal Entries'!$D$5:$D$785,"3050",'Journal Entries'!$J$5:$J$785,"<=43") -> 900000 | O18: =SUMIFS('Journal Entries'!$I$5:$I$785,'Journal Entries'!$D$5:$D$785,"3050",'Journal Entries'!$J$5:$J$785,"<=45") -> 900000
A19: 3100 | B19: Partners' capital - distributions | C19: Cr | D19: =SUMIFS('Journal Entries'!$I$5:$I$785,'Journal Entries'!$D$5:$D$785,"3100",'Journal Entries'!$J$5:$J$785,"<=3") -> 0 | E19: =SUMIFS('Journal Entries'!$I$5:$I$785,'Journal Entries'!$D$5:$D$785,"3100",'Journal Entries'!$J$5:$J$785,"<=7") -> 0 | F19: =SUMIFS('Journal Entries'!$I$5:$I$785,'Journal Entries'!$D$5:$D$785,"3100",'Journal Entries'!$J$5:$J$785,"<=11") -> 0 | G19: =SUMIFS('Journal Entries'!$I$5:$I$785,'Journal Entries'!$D$5:$D$785,"3100",'Journal Entries'!$J$5:$J$785,"<=15") -> 0 | H19: =SUMIFS('Journal Entries'!$I$5:$I$785,'Journal Entries'!$D$5:$D$785,"3100",'Journal Entries'!$J$5:$J$785,"<=19") -> 0 | I19: =SUMIFS('Journal Entries'!$I$5:$I$785,'Journal Entries'!$D$5:$D$785,"3100",'Journal Entries'!$J$5:$J$785,"<=23") -> 115200000 | J19: =SUMIFS('Journal Entries'!$I$5:$I$785,'Journal Entries'!$D$5:$D$785,"3100",'Journal Entries'!$J$5:$J$785,"<=27") -> 141200000 | K19: =SUMIFS('Journal Entries'!$I$5:$I$785,'Journal Entries'!$D$5:$D$785,"3100",'Journal Entries'!$J$5:$J$785,"<=31") -> 141200000 | L19: =SUMIFS('Journal Entries'!$I$5:$I$785,'Journal Entries'!$D$5:$D$785,"3100",'Journal Entries'!$J$5:$J$785,"<=35") -> 230400000 | M19: =SUMIFS('Journal Entries'!$I$5:$I$785,'Journal Entries'!$D$5:$D$785,"3100",'Journal Entries'!$J$5:$J$785,"<=39") -> 348200000 | N19: =SUMIFS('Journal Entries'!$I$5:$I$785,'Journal Entries'!$D$5:$D$785,"3100",'Journal Entries'!$J$5:$J$785,"<=43") -> 409900000 | O19: =SUMIFS('Journal Entries'!$I$5:$I$785,'Journal Entries'!$D$5:$D$785,"3100",'Journal Entries'!$J$5:$J$785,"<=45") -> 4.1236728e+08
A20: 3900 | B20: Partners' capital - accumulated results | C20: Cr | D20: =SUMIFS('Journal Entries'!$I$5:$I$785,'Journal Entries'!$D$5:$D$785,"3900",'Journal Entries'!$J$5:$J$785,"<=3") -> 0 | E20: =SUMIFS('Journal Entries'!$I$5:$I$785,'Journal Entries'!$D$5:$D$785,"3900",'Journal Entries'!$J$5:$J$785,"<=7") -> 0 | F20: =SUMIFS('Journal Entries'!$I$5:$I$785,'Journal Entries'!$D$5:$D$785,"3900",'Journal Entries'!$J$5:$J$785,"<=11") -> 0 | G20: =SUMIFS('Journal Entries'!$I$5:$I$785,'Journal Entries'!$D$5:$D$785,"3900",'Journal Entries'!$J$5:$J$785,"<=15") -> 0 | H20: =SUMIFS('Journal Entries'!$I$5:$I$785,'Journal Entries'!$D$5:$D$785,"3900",'Journal Entries'!$J$5:$J$785,"<=19") -> 0 | I20: =SUMIFS('Journal Entries'!$I$5:$I$785,'Journal Entries'!$D$5:$D$785,"3900",'Journal Entries'!$J$5:$J$785,"<=23") -> 0 | J20: =SUMIFS('Journal Entries'!$I$5:$I$785,'Journal Entries'!$D$5:$D$785,"3900",'Journal Entries'!$J$5:$J$785,"<=27") -> 0 | K20: =SUMIFS('Journal Entries'!$I$5:$I$785,'Journal Entries'!$D$5:$D$785,"3900",'Journal Entries'!$J$5:$J$785,"<=31") -> 0 | L20: =SUMIFS('Journal Entries'!$I$5:$I$785,'Journal Entries'!$D$5:$D$785,"3900",'Journal Entries'!$J$5:$J$785,"<=35") -> 0 | M20: =SUMIFS('Journal Entries'!$I$5:$I$785,'Journal Entries'!$D$5:$D$785,"3900",'Journal Entries'!$J$5:$J$785,"<=39") -> 0 | N20: =SUMIFS('Journal Entries'!$I$5:$I$785,'Journal Entries'!$D$5:$D$785,"3900",'Journal Entries'!$J$5:$J$785,"<=43") -> 0 | O20: =SUMIFS('Journal Entries'!$I$5:$I$785,'Journal Entries'!$D$5:$D$785,"3900",'Journal Entries'!$J$5:$J$785,"<=45") -> 0
A21: 4000 | B21: Interest income - PIK | C21: Cr | D21: =SUMIFS('Journal Entries'!$I$5:$I$785,'Journal Entries'!$D$5:$D$785,"4000",'Journal Entries'!$J$5:$J$785,"<=3") -> 0 | E21: =SUMIFS('Journal Entries'!$I$5:$I$785,'Journal Entries'!$D$5:$D$785,"4000",'Journal Entries'!$J$5:$J$785,"<=7") -> 0 | F21: =SUMIFS('Journal Entries'!$I$5:$I$785,'Journal Entries'!$D$5:$D$785,"4000",'Journal Entries'!$J$5:$J$785,"<=11") -> 0 | G21: =SUMIFS('Journal Entries'!$I$5:$I$785,'Journal Entries'!$D$5:$D$785,"4000",'Journal Entries'!$J$5:$J$785,"<=15") -> -1298178 | H21: =SUMIFS('Journal Entries'!$I$5:$I$785,'Journal Entries'!$D$5:$D$785,"4000",'Journal Entries'!$J$5:$J$785,"<=19") -> -3218234.1 | I21: =SUMIFS('Journal Entries'!$I$5:$I$785,'Journal Entries'!$D$5:$D$785,"4000",'Journal Entries'!$J$5:$J$785,"<=23") -> -5379274.2 | J21: =SUMIFS('Journal Entries'!$I$5:$I$785,'Journal Entries'!$D$5:$D$785,"4000",'Journal Entries'!$J$5:$J$785,"<=27") -> -7811543.8 | K21: =SUMIFS('Journal Entries'!$I$5:$I$785,'Journal Entries'!$D$5:$D$785,"4000",'Journal Entries'!$J$5:$J$785,"<=31") -> -10549085 | L21: =SUMIFS('Journal Entries'!$I$5:$I$785,'Journal Entries'!$D$5:$D$785,"4000",'Journal Entries'!$J$5:$J$785,"<=35") -> -13630211 | M21: =SUMIFS('Journal Entries'!$I$5:$I$785,'Journal Entries'!$D$5:$D$785,"4000",'Journal Entries'!$J$5:$J$785,"<=39") -> -16192278 | N21: =SUMIFS('Journal Entries'!$I$5:$I$785,'Journal Entries'!$D$5:$D$785,"4000",'Journal Entries'!$J$5:$J$785,"<=43") -> -16192278 | O21: =SUMIFS('Journal Entries'!$I$5:$I$785,'Journal Entries'!$D$5:$D$785,"4000",'Journal Entries'!$J$5:$J$785,"<=45") -> -16192278
A22: 4010 | B22: Interest income - other | C22: Cr | D22: =SUMIFS('Journal Entries'!$I$5:$I$785,'Journal Entries'!$D$5:$D$785,"4010",'Journal Entries'!$J$5:$J$785,"<=3") -> 0 | E22: =SUMIFS('Journal Entries'!$I$5:$I$785,'Journal Entries'!$D$5:$D$785,"4010",'Journal Entries'!$J$5:$J$785,"<=7") -> 0 | F22: =SUMIFS('Journal Entries'!$I$5:$I$785,'Journal Entries'!$D$5:$D$785,"4010",'Journal Entries'!$J$5:$J$785,"<=11") -> 0 | G22: =SUMIFS('Journal Entries'!$I$5:$I$785,'Journal Entries'!$D$5:$D$785,"4010",'Journal Entries'!$J$5:$J$785,"<=15") -> 0 | H22: =SUMIFS('Journal Entries'!$I$5:$I$785,'Journal Entries'!$D$5:$D$785,"4010",'Journal Entries'!$J$5:$J$785,"<=19") -> 0 | I22: =SUMIFS('Journal Entries'!$I$5:$I$785,'Journal Entries'!$D$5:$D$785,"4010",'Journal Entries'!$J$5:$J$785,"<=23") -> 0 | J22: =SUMIFS('Journal Entries'!$I$5:$I$785,'Journal Entries'!$D$5:$D$785,"4010",'Journal Entries'!$J$5:$J$785,"<=27") -> 0 | K22: =SUMIFS('Journal Entries'!$I$5:$I$785,'Journal Entries'!$D$5:$D$785,"4010",'Journal Entries'!$J$5:$J$785,"<=31") -> 0 | L22: =SUMIFS('Journal Entries'!$I$5:$I$785,'Journal Entries'!$D$5:$D$785,"4010",'Journal Entries'!$J$5:$J$785,"<=35") -> 0 | M22: =SUMIFS('Journal Entries'!$I$5:$I$785,'Journal Entries'!$D$5:$D$785,"4010",'Journal Entries'!$J$5:$J$785,"<=39") -> 0 | N22: =SUMIFS('Journal Entries'!$I$5:$I$785,'Journal Entries'!$D$5:$D$785,"4010",'Journal Entries'!$J$5:$J$785,"<=43") -> 0 | O22: =SUMIFS('Journal Entries'!$I$5:$I$785,'Journal Entries'!$D$5:$D$785,"4010",'Journal Entries'!$J$5:$J$785,"<=45") -> 0
A23: 4030 | B23: Other income - monitoring fees | C23: Cr | D23: =SUMIFS('Journal Entries'!$I$5:$I$785,'Journal Entries'!$D$5:$D$785,"4030",'Journal Entries'!$J$5:$J$785,"<=3") -> 0 | E23: =SUMIFS('Journal Entries'!$I$5:$I$785,'Journal Entries'!$D$5:$D$785,"4030",'Journal Entries'!$J$5:$J$785,"<=7") -> 0 | F23: =SUMIFS('Journal Entries'!$I$5:$I$785,'Journal Entries'!$D$5:$D$785,"4030",'Journal Entries'!$J$5:$J$785,"<=11") -> 0 | G23: =SUMIFS('Journal Entries'!$I$5:$I$785,'Journal Entries'!$D$5:$D$785,"4030",'Journal Entries'!$J$5:$J$785,"<=15") -> 0 | H23: =SUMIFS('Journal Entries'!$I$5:$I$785,'Journal Entries'!$D$5:$D$785,"4030",'Journal Entries'!$J$5:$J$785,"<=19") -> 0 | I23: =SUMIFS('Journal Entries'!$I$5:$I$785,'Journal Entries'!$D$5:$D$785,"4030",'Journal Entries'!$J$5:$J$785,"<=23") -> 0 | J23: =SUMIFS('Journal Entries'!$I$5:$I$785,'Journal Entries'!$D$5:$D$785,"4030",'Journal Entries'!$J$5:$J$785,"<=27") -> 0 | K23: =SUMIFS('Journal Entries'!$I$5:$I$785,'Journal Entries'!$D$5:$D$785,"4030",'Journal Entries'!$J$5:$J$785,"<=31") -> 0 | L23: =SUMIFS('Journal Entries'!$I$5:$I$785,'Journal Entries'!$D$5:$D$785,"4030",'Journal Entries'!$J$5:$J$785,"<=35") -> 0 | M23: =SUMIFS('Journal Entries'!$I$5:$I$785,'Journal Entries'!$D$5:$D$785,"4030",'Journal Entries'!$J$5:$J$785,"<=39") -> 0 | N23: =SUMIFS('Journal Entries'!$I$5:$I$785,'Journal Entries'!$D$5:$D$785,"4030",'Journal Entries'!$J$5:$J$785,"<=43") -> 0 | O23: =SUMIFS('Journal Entries'!$I$5:$I$785,'Journal Entries'!$D$5:$D$785,"4030",'Journal Entries'!$J$5:$J$785,"<=45") -> 0
A24: 5000 | B24: Management fee | C24: Dr | D24: =SUMIFS('Journal Entries'!$I$5:$I$785,'Journal Entries'!$D$5:$D$785,"5000",'Journal Entries'!$J$5:$J$785,"<=3") -> 2600000 | E24: =SUMIFS('Journal Entries'!$I$5:$I$785,'Journal Entries'!$D$5:$D$785,"5000",'Journal Entries'!$J$5:$J$785,"<=7") -> 7150000 | F24: =SUMIFS('Journal Entries'!$I$5:$I$785,'Journal Entries'!$D$5:$D$785,"5000",'Journal Entries'!$J$5:$J$785,"<=11") -> 12050000 | G24: =SUMIFS('Journal Entries'!$I$5:$I$785,'Journal Entries'!$D$5:$D$785,"5000",'Journal Entries'!$J$5:$J$785,"<=15") -> 16950000 | H24: =SUMIFS('Journal Entries'!$I$5:$I$785,'Journal Entries'!$D$5:$D$785,"5000",'Journal Entries'!$J$5:$J$785,"<=19") -> 21850000 | I24: =SUMIFS('Journal Entries'!$I$5:$I$785,'Journal Entries'!$D$5:$D$785,"5000",'Journal Entries'!$J$5:$J$785,"<=23") -> 26750000 | J24: =SUMIFS('Journal Entries'!$I$5:$I$785,'Journal Entries'!$D$5:$D$785,"5000",'Journal Entries'!$J$5:$J$785,"<=27") -> 30260000 | K24: =SUMIFS('Journal Entries'!$I$5:$I$785,'Journal Entries'!$D$5:$D$785,"5000",'Journal Entries'!$J$5:$J$785,"<=31") -> 32380000 | L24: =SUMIFS('Journal Entries'!$I$5:$I$785,'Journal Entries'!$D$5:$D$785,"5000",'Journal Entries'!$J$5:$J$785,"<=35") -> 33975000 | M24: =SUMIFS('Journal Entries'!$I$5:$I$785,'Journal Entries'!$D$5:$D$785,"5000",'Journal Entries'!$J$5:$J$785,"<=39") -> 34850000 | N24: =SUMIFS('Journal Entries'!$I$5:$I$785,'Journal Entries'!$D$5:$D$785,"5000",'Journal Entries'!$J$5:$J$785,"<=43") -> 34940000 | O24: =SUMIFS('Journal Entries'!$I$5:$I$785,'Journal Entries'!$D$5:$D$785,"5000",'Journal Entries'!$J$5:$J$785,"<=45") -> 34940000
A25: 5010 | B25: Management fee offset | C25: Dr | D25: =SUMIFS('Journal Entries'!$I$5:$I$785,'Journal Entries'!$D$5:$D$785,"5010",'Journal Entries'!$J$5:$J$785,"<=3") -> 0 | E25: =SUMIFS('Journal Entries'!$I$5:$I$785,'Journal Entries'!$D$5:$D$785,"5010",'Journal Entries'!$J$5:$J$785,"<=7") -> 0 | F25: =SUMIFS('Journal Entries'!$I$5:$I$785,'Journal Entries'!$D$5:$D$785,"5010",'Journal Entries'!$J$5:$J$785,"<=11") -> -350000 | G25: =SUMIFS('Journal Entries'!$I$5:$I$785,'Journal Entries'!$D$5:$D$785,"5010",'Journal Entries'!$J$5:$J$785,"<=15") -> -750000 | H25: =SUMIFS('Journal Entries'!$I$5:$I$785,'Journal Entries'!$D$5:$D$785,"5010",'Journal Entries'!$J$5:$J$785,"<=19") -> -1150000 | I25: =SUMIFS('Journal Entries'!$I$5:$I$785,'Journal Entries'!$D$5:$D$785,"5010",'Journal Entries'!$J$5:$J$785,"<=23") -> -1400000 | J25: =SUMIFS('Journal Entries'!$I$5:$I$785,'Journal Entries'!$D$5:$D$785,"5010",'Journal Entries'!$J$5:$J$785,"<=27") -> -1400000 | K25: =SUMIFS('Journal Entries'!$I$5:$I$785,'Journal Entries'!$D$5:$D$785,"5010",'Journal Entries'!$J$5:$J$785,"<=31") -> -1400000 | L25: =SUMIFS('Journal Entries'!$I$5:$I$785,'Journal Entries'!$D$5:$D$785,"5010",'Journal Entries'!$J$5:$J$785,"<=35") -> -1400000 | M25: =SUMIFS('Journal Entries'!$I$5:$I$785,'Journal Entries'!$D$5:$D$785,"5010",'Journal Entries'!$J$5:$J$785,"<=39") -> -1400000 | N25: =SUMIFS('Journal Entries'!$I$5:$I$785,'Journal Entries'!$D$5:$D$785,"5010",'Journal Entries'!$J$5:$J$785,"<=43") -> -1400000 | O25: =SUMIFS('Journal Entries'!$I$5:$I$785,'Journal Entries'!$D$5:$D$785,"5010",'Journal Entries'!$J$5:$J$785,"<=45") -> -1400000
A26: 5100 | B26: Organizational costs | C26: Dr | D26: =SUMIFS('Journal Entries'!$I$5:$I$785,'Journal Entries'!$D$5:$D$785,"5100",'Journal Entries'!$J$5:$J$785,"<=3") -> 1200000 | E26: =SUMIFS('Journal Entries'!$I$5:$I$785,'Journal Entries'!$D$5:$D$785,"5100",'Journal Entries'!$J$5:$J$785,"<=7") -> 1200000 | F26: =SUMIFS('Journal Entries'!$I$5:$I$785,'Journal Entries'!$D$5:$D$785,"5100",'Journal Entries'!$J$5:$J$785,"<=11") -> 1200000 | G26: =SUMIFS('Journal Entries'!$I$5:$I$785,'Journal Entries'!$D$5:$D$785,"5100",'Journal Entries'!$J$5:$J$785,"<=15") -> 1200000 | H26: =SUMIFS('Journal Entries'!$I$5:$I$785,'Journal Entries'!$D$5:$D$785,"5100",'Journal Entries'!$J$5:$J$785,"<=19") -> 1200000 | I26: =SUMIFS('Journal Entries'!$I$5:$I$785,'Journal Entries'!$D$5:$D$785,"5100",'Journal Entries'!$J$5:$J$785,"<=23") -> 1200000 | J26: =SUMIFS('Journal Entries'!$I$5:$I$785,'Journal Entries'!$D$5:$D$785,"5100",'Journal Entries'!$J$5:$J$785,"<=27") -> 1200000 | K26: =SUMIFS('Journal Entries'!$I$5:$I$785,'Journal Entries'!$D$5:$D$785,"5100",'Journal Entries'!$J$5:$J$785,"<=31") -> 1200000 | L26: =SUMIFS('Journal Entries'!$I$5:$I$785,'Journal Entries'!$D$5:$D$785,"5100",'Journal Entries'!$J$5:$J$785,"<=35") -> 1200000 | M26: =SUMIFS('Journal Entries'!$I$5:$I$785,'Journal Entries'!$D$5:$D$785,"5100",'Journal Entries'!$J$5:$J$785,"<=39") -> 1200000 | N26: =SUMIFS('Journal Entries'!$I$5:$I$785,'Journal Entries'!$D$5:$D$785,"5100",'Journal Entries'!$J$5:$J$785,"<=43") -> 1200000 | O26: =SUMIFS('Journal Entries'!$I$5:$I$785,'Journal Entries'!$D$5:$D$785,"5100",'Journal Entries'!$J$5:$J$785,"<=45") -> 1200000
A27: 5110 | B27: Amortization of deferred offering costs | C27: Dr | D27: =SUMIFS('Journal Entries'!$I$5:$I$785,'Journal Entries'!$D$5:$D$785,"5110",'Journal Entries'!$J$5:$J$785,"<=3") -> 0 | E27: =SUMIFS('Journal Entries'!$I$5:$I$785,'Journal Entries'!$D$5:$D$785,"5110",'Journal Entries'!$J$5:$J$785,"<=7") -> 0 | F27: =SUMIFS('Journal Entries'!$I$5:$I$785,'Journal Entries'!$D$5:$D$785,"5110",'Journal Entries'!$J$5:$J$785,"<=11") -> 0 | G27: =SUMIFS('Journal Entries'!$I$5:$I$785,'Journal Entries'!$D$5:$D$785,"5110",'Journal Entries'!$J$5:$J$785,"<=15") -> 0 | H27: =SUMIFS('Journal Entries'!$I$5:$I$785,'Journal Entries'!$D$5:$D$785,"5110",'Journal Entries'!$J$5:$J$785,"<=19") -> 0 | I27: =SUMIFS('Journal Entries'!$I$5:$I$785,'Journal Entries'!$D$5:$D$785,"5110",'Journal Entries'!$J$5:$J$785,"<=23") -> 0 | J27: =SUMIFS('Journal Entries'!$I$5:$I$785,'Journal Entries'!$D$5:$D$785,"5110",'Journal Entries'!$J$5:$J$785,"<=27") -> 0 | K27: =SUMIFS('Journal Entries'!$I$5:$I$785,'Journal Entries'!$D$5:$D$785,"5110",'Journal Entries'!$J$5:$J$785,"<=31") -> 0 | L27: =SUMIFS('Journal Entries'!$I$5:$I$785,'Journal Entries'!$D$5:$D$785,"5110",'Journal Entries'!$J$5:$J$785,"<=35") -> 0 | M27: =SUMIFS('Journal Entries'!$I$5:$I$785,'Journal Entries'!$D$5:$D$785,"5110",'Journal Entries'!$J$5:$J$785,"<=39") -> 0 | N27: =SUMIFS('Journal Entries'!$I$5:$I$785,'Journal Entries'!$D$5:$D$785,"5110",'Journal Entries'!$J$5:$J$785,"<=43") -> 0 | O27: =SUMIFS('Journal Entries'!$I$5:$I$785,'Journal Entries'!$D$5:$D$785,"5110",'Journal Entries'!$J$5:$J$785,"<=45") -> 0
A28: 5200 | B28: Professional fees - audit and tax | C28: Dr | D28: =SUMIFS('Journal Entries'!$I$5:$I$785,'Journal Entries'!$D$5:$D$785,"5200",'Journal Entries'!$J$5:$J$785,"<=3") -> 120000 | E28: =SUMIFS('Journal Entries'!$I$5:$I$785,'Journal Entries'!$D$5:$D$785,"5200",'Journal Entries'!$J$5:$J$785,"<=7") -> 300000 | F28: =SUMIFS('Journal Entries'!$I$5:$I$785,'Journal Entries'!$D$5:$D$785,"5200",'Journal Entries'!$J$5:$J$785,"<=11") -> 480000 | G28: =SUMIFS('Journal Entries'!$I$5:$I$785,'Journal Entries'!$D$5:$D$785,"5200",'Journal Entries'!$J$5:$J$785,"<=15") -> 660000 | H28: =SUMIFS('Journal Entries'!$I$5:$I$785,'Journal Entries'!$D$5:$D$785,"5200",'Journal Entries'!$J$5:$J$785,"<=19") -> 840000 | I28: =SUMIFS('Journal Entries'!$I$5:$I$785,'Journal Entries'!$D$5:$D$785,"5200",'Journal Entries'!$J$5:$J$785,"<=23") -> 1020000 | J28: =SUMIFS('Journal Entries'!$I$5:$I$785,'Journal Entries'!$D$5:$D$785,"5200",'Journal Entries'!$J$5:$J$785,"<=27") -> 1212000 | K28: =SUMIFS('Journal Entries'!$I$5:$I$785,'Journal Entries'!$D$5:$D$785,"5200",'Journal Entries'!$J$5:$J$785,"<=31") -> 1404000 | L28: =SUMIFS('Journal Entries'!$I$5:$I$785,'Journal Entries'!$D$5:$D$785,"5200",'Journal Entries'!$J$5:$J$785,"<=35") -> 1596000 | M28: =SUMIFS('Journal Entries'!$I$5:$I$785,'Journal Entries'!$D$5:$D$785,"5200",'Journal Entries'!$J$5:$J$785,"<=39") -> 1788000 | N28: =SUMIFS('Journal Entries'!$I$5:$I$785,'Journal Entries'!$D$5:$D$785,"5200",'Journal Entries'!$J$5:$J$785,"<=43") -> 1980000 | O28: =SUMIFS('Journal Entries'!$I$5:$I$785,'Journal Entries'!$D$5:$D$785,"5200",'Journal Entries'!$J$5:$J$785,"<=45") -> 2076000
A29: 5210 | B29: Professional fees - legal | C29: Dr | D29: =SUMIFS('Journal Entries'!$I$5:$I$785,'Journal Entries'!$D$5:$D$785,"5210",'Journal Entries'!$J$5:$J$785,"<=3") -> 140000 | E29: =SUMIFS('Journal Entries'!$I$5:$I$785,'Journal Entries'!$D$5:$D$785,"5210",'Journal Entries'!$J$5:$J$785,"<=7") -> 212000 | F29: =SUMIFS('Journal Entries'!$I$5:$I$785,'Journal Entries'!$D$5:$D$785,"5210",'Journal Entries'!$J$5:$J$785,"<=11") -> 284000 | G29: =SUMIFS('Journal Entries'!$I$5:$I$785,'Journal Entries'!$D$5:$D$785,"5210",'Journal Entries'!$J$5:$J$785,"<=15") -> 356000 | H29: =SUMIFS('Journal Entries'!$I$5:$I$785,'Journal Entries'!$D$5:$D$785,"5210",'Journal Entries'!$J$5:$J$785,"<=19") -> 428000 | I29: =SUMIFS('Journal Entries'!$I$5:$I$785,'Journal Entries'!$D$5:$D$785,"5210",'Journal Entries'!$J$5:$J$785,"<=23") -> 500000 | J29: =SUMIFS('Journal Entries'!$I$5:$I$785,'Journal Entries'!$D$5:$D$785,"5210",'Journal Entries'!$J$5:$J$785,"<=27") -> 560000 | K29: =SUMIFS('Journal Entries'!$I$5:$I$785,'Journal Entries'!$D$5:$D$785,"5210",'Journal Entries'!$J$5:$J$785,"<=31") -> 620000 | L29: =SUMIFS('Journal Entries'!$I$5:$I$785,'Journal Entries'!$D$5:$D$785,"5210",'Journal Entries'!$J$5:$J$785,"<=35") -> 680000 | M29: =SUMIFS('Journal Entries'!$I$5:$I$785,'Journal Entries'!$D$5:$D$785,"5210",'Journal Entries'!$J$5:$J$785,"<=39") -> 740000 | N29: =SUMIFS('Journal Entries'!$I$5:$I$785,'Journal Entries'!$D$5:$D$785,"5210",'Journal Entries'!$J$5:$J$785,"<=43") -> 800000 | O29: =SUMIFS('Journal Entries'!$I$5:$I$785,'Journal Entries'!$D$5:$D$785,"5210",'Journal Entries'!$J$5:$J$785,"<=45") -> 830000
A30: 5300 | B30: Fund administration fees | C30: Dr | D30: =SUMIFS('Journal Entries'!$I$5:$I$785,'Journal Entries'!$D$5:$D$785,"5300",'Journal Entries'!$J$5:$J$785,"<=3") -> 180000 | E30: =SUMIFS('Journal Entries'!$I$5:$I$785,'Journal Entries'!$D$5:$D$785,"5300",'Journal Entries'!$J$5:$J$785,"<=7") -> 430000 | F30: =SUMIFS('Journal Entries'!$I$5:$I$785,'Journal Entries'!$D$5:$D$785,"5300",'Journal Entries'!$J$5:$J$785,"<=11") -> 680000 | G30: =SUMIFS('Journal Entries'!$I$5:$I$785,'Journal Entries'!$D$5:$D$785,"5300",'Journal Entries'!$J$5:$J$785,"<=15") -> 930000 | H30: =SUMIFS('Journal Entries'!$I$5:$I$785,'Journal Entries'!$D$5:$D$785,"5300",'Journal Entries'!$J$5:$J$785,"<=19") -> 1180000 | I30: =SUMIFS('Journal Entries'!$I$5:$I$785,'Journal Entries'!$D$5:$D$785,"5300",'Journal Entries'!$J$5:$J$785,"<=23") -> 1430000 | J30: =SUMIFS('Journal Entries'!$I$5:$I$785,'Journal Entries'!$D$5:$D$785,"5300",'Journal Entries'!$J$5:$J$785,"<=27") -> 1650000 | K30: =SUMIFS('Journal Entries'!$I$5:$I$785,'Journal Entries'!$D$5:$D$785,"5300",'Journal Entries'!$J$5:$J$785,"<=31") -> 1870000 | L30: =SUMIFS('Journal Entries'!$I$5:$I$785,'Journal Entries'!$D$5:$D$785,"5300",'Journal Entries'!$J$5:$J$785,"<=35") -> 2090000 | M30: =SUMIFS('Journal Entries'!$I$5:$I$785,'Journal Entries'!$D$5:$D$785,"5300",'Journal Entries'!$J$5:$J$785,"<=39") -> 2310000 | N30: =SUMIFS('Journal Entries'!$I$5:$I$785,'Journal Entries'!$D$5:$D$785,"5300",'Journal Entries'!$J$5:$J$785,"<=43") -> 2530000 | O30: =SUMIFS('Journal Entries'!$I$5:$I$785,'Journal Entries'!$D$5:$D$785,"5300",'Journal Entries'!$J$5:$J$785,"<=45") -> 2640000
A31: 5400 | B31: Custody and bank fees | C31: Dr | D31: =SUMIFS('Journal Entries'!$I$5:$I$785,'Journal Entries'!$D$5:$D$785,"5400",'Journal Entries'!$J$5:$J$785,"<=3") -> 20000 | E31: =SUMIFS('Journal Entries'!$I$5:$I$785,'Journal Entries'!$D$5:$D$785,"5400",'Journal Entries'!$J$5:$J$785,"<=7") -> 50000 | F31: =SUMIFS('Journal Entries'!$I$5:$I$785,'Journal Entries'!$D$5:$D$785,"5400",'Journal Entries'!$J$5:$J$785,"<=11") -> 80000 | G31: =SUMIFS('Journal Entries'!$I$5:$I$785,'Journal Entries'!$D$5:$D$785,"5400",'Journal Entries'!$J$5:$J$785,"<=15") -> 110000 | H31: =SUMIFS('Journal Entries'!$I$5:$I$785,'Journal Entries'!$D$5:$D$785,"5400",'Journal Entries'!$J$5:$J$785,"<=19") -> 140000 | I31: =SUMIFS('Journal Entries'!$I$5:$I$785,'Journal Entries'!$D$5:$D$785,"5400",'Journal Entries'!$J$5:$J$785,"<=23") -> 170000 | J31: =SUMIFS('Journal Entries'!$I$5:$I$785,'Journal Entries'!$D$5:$D$785,"5400",'Journal Entries'!$J$5:$J$785,"<=27") -> 200000 | K31: =SUMIFS('Journal Entries'!$I$5:$I$785,'Journal Entries'!$D$5:$D$785,"5400",'Journal Entries'!$J$5:$J$785,"<=31") -> 230000 | L31: =SUMIFS('Journal Entries'!$I$5:$I$785,'Journal Entries'!$D$5:$D$785,"5400",'Journal Entries'!$J$5:$J$785,"<=35") -> 260000 | M31: =SUMIFS('Journal Entries'!$I$5:$I$785,'Journal Entries'!$D$5:$D$785,"5400",'Journal Entries'!$J$5:$J$785,"<=39") -> 290000 | N31: =SUMIFS('Journal Entries'!$I$5:$I$785,'Journal Entries'!$D$5:$D$785,"5400",'Journal Entries'!$J$5:$J$785,"<=43") -> 320000 | O31: =SUMIFS('Journal Entries'!$I$5:$I$785,'Journal Entries'!$D$5:$D$785,"5400",'Journal Entries'!$J$5:$J$785,"<=45") -> 335000
A32: 5500 | B32: Interest expense - subscription line | C32: Dr | D32: =SUMIFS('Journal Entries'!$I$5:$I$785,'Journal Entries'!$D$5:$D$785,"5500",'Journal Entries'!$J$5:$J$785,"<=3") -> 0 | E32: =SUMIFS('Journal Entries'!$I$5:$I$785,'Journal Entries'!$D$5:$D$785,"5500",'Journal Entries'!$J$5:$J$785,"<=7") -> 0 | F32: =SUMIFS('Journal Entries'!$I$5:$I$785,'Journal Entries'!$D$5:$D$785,"5500",'Journal Entries'!$J$5:$J$785,"<=11") -> 0 | G32: =SUMIFS('Journal Entries'!$I$5:$I$785,'Journal Entries'!$D$5:$D$785,"5500",'Journal Entries'!$J$5:$J$785,"<=15") -> 0 | H32: =SUMIFS('Journal Entries'!$I$5:$I$785,'Journal Entries'!$D$5:$D$785,"5500",'Journal Entries'!$J$5:$J$785,"<=19") -> 0 | I32: =SUMIFS('Journal Entries'!$I$5:$I$785,'Journal Entries'!$D$5:$D$785,"5500",'Journal Entries'!$J$5:$J$785,"<=23") -> 0 | J32: =SUMIFS('Journal Entries'!$I$5:$I$785,'Journal Entries'!$D$5:$D$785,"5500",'Journal Entries'!$J$5:$J$785,"<=27") -> 0 | K32: =SUMIFS('Journal Entries'!$I$5:$I$785,'Journal Entries'!$D$5:$D$785,"5500",'Journal Entries'!$J$5:$J$785,"<=31") -> 0 | L32: =SUMIFS('Journal Entries'!$I$5:$I$785,'Journal Entries'!$D$5:$D$785,"5500",'Journal Entries'!$J$5:$J$785,"<=35") -> 0 | M32: =SUMIFS('Journal Entries'!$I$5:$I$785,'Journal Entries'!$D$5:$D$785,"5500",'Journal Entries'!$J$5:$J$785,"<=39") -> 0 | N32: =SUMIFS('Journal Entries'!$I$5:$I$785,'Journal Entries'!$D$5:$D$785,"5500",'Journal Entries'!$J$5:$J$785,"<=43") -> 0 | O32: =SUMIFS('Journal Entries'!$I$5:$I$785,'Journal Entries'!$D$5:$D$785,"5500",'Journal Entries'!$J$5:$J$785,"<=45") -> 0
A33: 5600 | B33: Other fund expenses | C33: Dr | D33: =SUMIFS('Journal Entries'!$I$5:$I$785,'Journal Entries'!$D$5:$D$785,"5600",'Journal Entries'!$J$5:$J$785,"<=3") -> 48000 | E33: =SUMIFS('Journal Entries'!$I$5:$I$785,'Journal Entries'!$D$5:$D$785,"5600",'Journal Entries'!$J$5:$J$785,"<=7") -> 84000 | F33: =SUMIFS('Journal Entries'!$I$5:$I$785,'Journal Entries'!$D$5:$D$785,"5600",'Journal Entries'!$J$5:$J$785,"<=11") -> 120000 | G33: =SUMIFS('Journal Entries'!$I$5:$I$785,'Journal Entries'!$D$5:$D$785,"5600",'Journal Entries'!$J$5:$J$785,"<=15") -> 156000 | H33: =SUMIFS('Journal Entries'!$I$5:$I$785,'Journal Entries'!$D$5:$D$785,"5600",'Journal Entries'!$J$5:$J$785,"<=19") -> 192000 | I33: =SUMIFS('Journal Entries'!$I$5:$I$785,'Journal Entries'!$D$5:$D$785,"5600",'Journal Entries'!$J$5:$J$785,"<=23") -> 228000 | J33: =SUMIFS('Journal Entries'!$I$5:$I$785,'Journal Entries'!$D$5:$D$785,"5600",'Journal Entries'!$J$5:$J$785,"<=27") -> 260000 | K33: =SUMIFS('Journal Entries'!$I$5:$I$785,'Journal Entries'!$D$5:$D$785,"5600",'Journal Entries'!$J$5:$J$785,"<=31") -> 292000 | L33: =SUMIFS('Journal Entries'!$I$5:$I$785,'Journal Entries'!$D$5:$D$785,"5600",'Journal Entries'!$J$5:$J$785,"<=35") -> 324000 | M33: =SUMIFS('Journal Entries'!$I$5:$I$785,'Journal Entries'!$D$5:$D$785,"5600",'Journal Entries'!$J$5:$J$785,"<=39") -> 356000 | N33: =SUMIFS('Journal Entries'!$I$5:$I$785,'Journal Entries'!$D$5:$D$785,"5600",'Journal Entries'!$J$5:$J$785,"<=43") -> 388000 | O33: =SUMIFS('Journal Entries'!$I$5:$I$785,'Journal Entries'!$D$5:$D$785,"5600",'Journal Entries'!$J$5:$J$785,"<=45") -> 404000
A34: 6000 | B34: Net realized gain/(loss) on investments | C34: Cr | D34: =SUMIFS('Journal Entries'!$I$5:$I$785,'Journal Entries'!$D$5:$D$785,"6000",'Journal Entries'!$J$5:$J$785,"<=3") -> 0 | E34: =SUMIFS('Journal Entries'!$I$5:$I$785,'Journal Entries'!$D$5:$D$785,"6000",'Journal Entries'!$J$5:$J$785,"<=7") -> 0 | F34: =SUMIFS('Journal Entries'!$I$5:$I$785,'Journal Entries'!$D$5:$D$785,"6000",'Journal Entries'!$J$5:$J$785,"<=11") -> 0 | G34: =SUMIFS('Journal Entries'!$I$5:$I$785,'Journal Entries'!$D$5:$D$785,"6000",'Journal Entries'!$J$5:$J$785,"<=15") -> 0 | H34: =SUMIFS('Journal Entries'!$I$5:$I$785,'Journal Entries'!$D$5:$D$785,"6000",'Journal Entries'!$J$5:$J$785,"<=19") -> 0 | I34: =SUMIFS('Journal Entries'!$I$5:$I$785,'Journal Entries'!$D$5:$D$785,"6000",'Journal Entries'!$J$5:$J$785,"<=23") -> -68000000 | J34: =SUMIFS('Journal Entries'!$I$5:$I$785,'Journal Entries'!$D$5:$D$785,"6000",'Journal Entries'!$J$5:$J$785,"<=27") -> -72800000 | K34: =SUMIFS('Journal Entries'!$I$5:$I$785,'Journal Entries'!$D$5:$D$785,"6000",'Journal Entries'!$J$5:$J$785,"<=31") -> -72800000 | L34: =SUMIFS('Journal Entries'!$I$5:$I$785,'Journal Entries'!$D$5:$D$785,"6000",'Journal Entries'!$J$5:$J$785,"<=35") -> -129800000 | M34: =SUMIFS('Journal Entries'!$I$5:$I$785,'Journal Entries'!$D$5:$D$785,"6000",'Journal Entries'!$J$5:$J$785,"<=39") -> -180800000 | N34: =SUMIFS('Journal Entries'!$I$5:$I$785,'Journal Entries'!$D$5:$D$785,"6000",'Journal Entries'!$J$5:$J$785,"<=43") -> -224800000 | O34: =SUMIFS('Journal Entries'!$I$5:$I$785,'Journal Entries'!$D$5:$D$785,"6000",'Journal Entries'!$J$5:$J$785,"<=45") -> -224800000
A35: 6100 | B35: Net change in unrealized appreciation/(depreciation) | C35: Cr | D35: =SUMIFS('Journal Entries'!$I$5:$I$785,'Journal Entries'!$D$5:$D$785,"6100",'Journal Entries'!$J$5:$J$785,"<=3") -> -1500000 | E35: =SUMIFS('Journal Entries'!$I$5:$I$785,'Journal Entries'!$D$5:$D$785,"6100",'Journal Entries'!$J$5:$J$785,"<=7") -> -9000000 | F35: =SUMIFS('Journal Entries'!$I$5:$I$785,'Journal Entries'!$D$5:$D$785,"6100",'Journal Entries'!$J$5:$J$785,"<=11") -> -39000000 | G35: =SUMIFS('Journal Entries'!$I$5:$I$785,'Journal Entries'!$D$5:$D$785,"6100",'Journal Entries'!$J$5:$J$785,"<=15") -> -35000000 | H35: =SUMIFS('Journal Entries'!$I$5:$I$785,'Journal Entries'!$D$5:$D$785,"6100",'Journal Entries'!$J$5:$J$785,"<=19") -> -66000000 | I35: =SUMIFS('Journal Entries'!$I$5:$I$785,'Journal Entries'!$D$5:$D$785,"6100",'Journal Entries'!$J$5:$J$785,"<=23") -> -51000000 | J35: =SUMIFS('Journal Entries'!$I$5:$I$785,'Journal Entries'!$D$5:$D$785,"6100",'Journal Entries'!$J$5:$J$785,"<=27") -> -62500000 | K35: =SUMIFS('Journal Entries'!$I$5:$I$785,'Journal Entries'!$D$5:$D$785,"6100",'Journal Entries'!$J$5:$J$785,"<=31") -> -78000000 | L35: =SUMIFS('Journal Entries'!$I$5:$I$785,'Journal Entries'!$D$5:$D$785,"6100",'Journal Entries'!$J$5:$J$785,"<=35") -> -64000000 | M35: =SUMIFS('Journal Entries'!$I$5:$I$785,'Journal Entries'!$D$5:$D$785,"6100",'Journal Entries'!$J$5:$J$785,"<=39") -> -28000000 | N35: =SUMIFS('Journal Entries'!$I$5:$I$785,'Journal Entries'!$D$5:$D$785,"6100",'Journal Entries'!$J$5:$J$785,"<=43") -> 0 | O35: =SUMIFS('Journal Entries'!$I$5:$I$785,'Journal Entries'!$D$5:$D$785,"6100",'Journal Entries'!$J$5:$J$785,"<=45") -> 0
B36: Total — must be zero | D36: =SUM(D5:D35) -> 0 | E36: =SUM(E5:E35) -> 0 | F36: =SUM(F5:F35) -> 0 | G36: =SUM(G5:G35) -> 0 | H36: =SUM(H5:H35) -> 0 | I36: =SUM(I5:I35) -> 0 | J36: =SUM(J5:J35) -> 0 | K36: =SUM(K5:K35) -> 0 | ... O36: =SUM(O5:O35) -> 2.9802322e-08

Sheet Balance Sheet
A1: Statement of Assets and Liabilities
A2: ASC 946 presentation. Columns are cumulative at each year end. Every trial balance account reaches a line on this statement, so nothing can go missing.
A4: (US dollars) | B4: FY2019 | C4: FY2020 | D4: FY2021 | E4: FY2022 | F4: FY2023 | G4: FY2024 | H4: FY2025 | I4: FY2026 | J4: FY2027 | K4: FY2028 | L4: FY2029 | M4: FY2030
A5: ASSETS
A6: Investments, at fair value | B6: ='Trial Balance'!D$7+'Trial Balance'!D$8+'Trial Balance'!D$9 -> 43500000 | C6: ='Trial Balance'!E$7+'Trial Balance'!E$8+'Trial Balance'!E$9 -> 106000000 | D6: ='Trial Balance'!F$7+'Trial Balance'!F$8+'Trial Balance'!F$9 -> 184000000 | E6: ='Trial Balance'!G$7+'Trial Balance'!G$8+'Trial Balance'!G$9 -> 207298178 | F6: ='Trial Balance'!H$7+'Trial Balance'!H$8+'Trial Balance'!H$9 -> 2.4921823e+08 | G6: ='Trial Balance'!I$7+'Trial Balance'!I$8+'Trial Balance'!I$9 -> 1.8637927e+08 | H6: ='Trial Balance'!J$7+'Trial Balance'!J$8+'Trial Balance'!J$9 -> 1.7631154e+08 | I6: ='Trial Balance'!K$7+'Trial Balance'!K$8+'Trial Balance'!K$9 -> 1.9454908e+08 | ... M6: ='Trial Balance'!O$7+'Trial Balance'!O$8+'Trial Balance'!O$9 -> 2.6077032e-08
A7: Cash and cash equivalents | B7: ='Trial Balance'!D$5 -> 292000 | C7: ='Trial Balance'!E$5 -> 274000 | D7: ='Trial Balance'!F$5 -> 2056000 | E7: ='Trial Balance'!G$5 -> 1788000 | F7: ='Trial Balance'!H$5 -> 1320000 | G7: ='Trial Balance'!I$5 -> 1702000 | H7: ='Trial Balance'!J$5 -> 1758000 | I7: ='Trial Balance'!K$5 -> 304000 | ... M7: ='Trial Balance'!O$5 -> 2.7939677e-09
A8: Interest and PIK receivable | B8: ='Trial Balance'!D$10 -> 0 | C8: ='Trial Balance'!E$10 -> 0 | D8: ='Trial Balance'!F$10 -> 0 | E8: ='Trial Balance'!G$10 -> 0 | F8: ='Trial Balance'!H$10 -> 0 | G8: ='Trial Balance'!I$10 -> 0 | H8: ='Trial Balance'!J$10 -> 0 | I8: ='Trial Balance'!K$10 -> 0 | ... M8: ='Trial Balance'!O$10 -> 0
A9: Subscriptions receivable | B9: ='Trial Balance'!D$6 -> 0 | C9: ='Trial Balance'!E$6 -> 0 | D9: ='Trial Balance'!F$6 -> 0 | E9: ='Trial Balance'!G$6 -> 0 | F9: ='Trial Balance'!H$6 -> 0 | G9: ='Trial Balance'!I$6 -> 0 | H9: ='Trial Balance'!J$6 -> 0 | I9: ='Trial Balance'!K$6 -> 0 | ... M9: ='Trial Balance'!O$6 -> 0
A10: Prepaid management fee | B10: ='Trial Balance'!D$11 -> 0 | C10: ='Trial Balance'!E$11 -> 0 | D10: ='Trial Balance'!F$11 -> 0 | E10: ='Trial Balance'!G$11 -> 0 | F10: ='Trial Balance'!H$11 -> 0 | G10: ='Trial Balance'!I$11 -> 0 | H10: ='Trial Balance'!J$11 -> 0 | I10: ='Trial Balance'!K$11 -> 0 | ... M10: ='Trial Balance'!O$11 -> 0
A11: Deferred offering costs | B11: ='Trial Balance'!D$12 -> 0 | C11: ='Trial Balance'!E$12 -> 0 | D11: ='Trial Balance'!F$12 -> 0 | E11: ='Trial Balance'!G$12 -> 0 | F11: ='Trial Balance'!H$12 -> 0 | G11: ='Trial Balance'!I$12 -> 0 | H11: ='Trial Balance'!J$12 -> 0 | I11: ='Trial Balance'!K$12 -> 0 | ... M11: ='Trial Balance'!O$12 -> 0
A12: Total assets | B12: ='Trial Balance'!D$5+'Trial Balance'!D$6+'Trial Balance'!D$7+'Trial Balance'!D$8+'Trial Balance'!D$9+'Trial Balance'!D$10+'Trial Balance'!D$11+'Trial Balance'!D$12 -> 43792000 | C12: ='Trial Balance'!E$5+'Trial Balance'!E$6+'Trial Balance'!E$7+'Trial Balance'!E$8+'Trial Balance'!E$9+'Trial Balance'!E$10+'Trial Balance'!E$11+'Trial Balance'!E$12 -> 106274000 | D12: ='Trial Balance'!F$5+'Trial Balance'!F$6+'Trial Balance'!F$7+'Trial Balance'!F$8+'Trial Balance'!F$9+'Trial Balance'!F$10+'Trial Balance'!F$11+'Trial Balance'!F$12 -> 186056000 | E12: ='Trial Balance'!G$5+'Trial Balance'!G$6+'Trial Balance'!G$7+'Trial Balance'!G$8+'Trial Balance'!G$9+'Trial Balance'!G$10+'Trial Balance'!G$11+'Trial Balance'!G$12 -> 209086178 | F12: ='Trial Balance'!H$5+'Trial Balance'!H$6+'Trial Balance'!H$7+'Trial Balance'!H$8+'Trial Balance'!H$9+'Trial Balance'!H$10+'Trial Balance'!H$11+'Trial Balance'!H$12 -> 2.5053823e+08 | G12: ='Trial Balance'!I$5+'Trial Balance'!I$6+'Trial Balance'!I$7+'Trial Balance'!I$8+'Trial Balance'!I$9+'Trial Balance'!I$10+'Trial Balance'!I$11+'Trial Balance'!I$12 -> 1.8808127e+08 | H12: ='Trial Balance'!J$5+'Trial Balance'!J$6+'Trial Balance'!J$7+'Trial Balance'!J$8+'Trial Balance'!J$9+'Trial Balance'!J$10+'Trial Balance'!J$11+'Trial Balance'!J$12 -> 1.7806954e+08 | I12: ='Trial Balance'!K$5+'Trial Balance'!K$6+'Trial Balance'!K$7+'Trial Balance'!K$8+'Trial Balance'!K$9+'Trial Balance'!K$10+'Trial Balance'!K$11+'Trial Balance'!K$12 -> 1.9485308e+08 | ... M12: ='Trial Balance'!O$5+'Trial Balance'!O$6+'Trial Balance'!O$7+'Trial Balance'!O$8+'Trial Balance'!O$9+'Trial Balance'!O$10+'Trial Balance'!O$11+'Trial Balance'!O$12 -> 2.8871e-08
A14: LIABILITIES
A15: Accounts payable and accrued expenses | B15: =-('Trial Balance'!D$13) -> 0 | C15: =-('Trial Balance'!E$13) -> 0 | D15: =-('Trial Balance'!F$13) -> 0 | E15: =-('Trial Balance'!G$13) -> 0 | F15: =-('Trial Balance'!H$13) -> 0 | G15: =-('Trial Balance'!I$13) -> 0 | H15: =-('Trial Balance'!J$13) -> 0 | I15: =-('Trial Balance'!K$13) -> 0 | ... M15: =-('Trial Balance'!O$13) -> 0
A16: Management fee payable | B16: =-('Trial Balance'!D$14) -> 0 | C16: =-('Trial Balance'!E$14) -> 0 | D16: =-('Trial Balance'!F$14) -> 0 | E16: =-('Trial Balance'!G$14) -> 0 | F16: =-('Trial Balance'!H$14) -> 0 | G16: =-('Trial Balance'!I$14) -> 0 | H16: =-('Trial Balance'!J$14) -> 0 | I16: =-('Trial Balance'!K$14) -> 0 | ... M16: =-('Trial Balance'!O$14) -> 0
A17: Distributions payable | B17: =-('Trial Balance'!D$16) -> 0 | C17: =-('Trial Balance'!E$16) -> 0 | D17: =-('Trial Balance'!F$16) -> 0 | E17: =-('Trial Balance'!G$16) -> 0 | F17: =-('Trial Balance'!H$16) -> 0 | G17: =-('Trial Balance'!I$16) -> 0 | H17: =-('Trial Balance'!J$16) -> 0 | I17: =-('Trial Balance'!K$16) -> 0 | ... M17: =-('Trial Balance'!O$16) -> 0
A18: Subscription line payable | B18: =-('Trial Balance'!D$15) -> 0 | C18: =-('Trial Balance'!E$15) -> 0 | D18: =-('Trial Balance'!F$15) -> 0 | E18: =-('Trial Balance'!G$15) -> 0 | F18: =-('Trial Balance'!H$15) -> 0 | G18: =-('Trial Balance'!I$15) -> 0 | H18: =-('Trial Balance'!J$15) -> 0 | I18: =-('Trial Balance'!K$15) -> 0 | ... M18: =-('Trial Balance'!O$15) -> 0
A19: Total liabilities | B19: =-('Trial Balance'!D$13+'Trial Balance'!D$14+'Trial Balance'!D$15+'Trial Balance'!D$16) -> 0 | C19: =-('Trial Balance'!E$13+'Trial Balance'!E$14+'Trial Balance'!E$15+'Trial Balance'!E$16) -> 0 | D19: =-('Trial Balance'!F$13+'Trial Balance'!F$14+'Trial Balance'!F$15+'Trial Balance'!F$16) -> 0 | E19: =-('Trial Balance'!G$13+'Trial Balance'!G$14+'Trial Balance'!G$15+'Trial Balance'!G$16) -> 0 | F19: =-('Trial Balance'!H$13+'Trial Balance'!H$14+'Trial Balance'!H$15+'Trial Balance'!H$16) -> 0 | G19: =-('Trial Balance'!I$13+'Trial Balance'!I$14+'Trial Balance'!I$15+'Trial Balance'!I$16) -> 0 | H19: =-('Trial Balance'!J$13+'Trial Balance'!J$14+'Trial Balance'!J$15+'Trial Balance'!J$16) -> 0 | I19: =-('Trial Balance'!K$13+'Trial Balance'!K$14+'Trial Balance'!K$15+'Trial Balance'!K$16) -> 0 | ... M19: =-('Trial Balance'!O$13+'Trial Balance'!O$14+'Trial Balance'!O$15+'Trial Balance'!O$16) -> 0
A21: NET ASSETS | B21: =B12-B19 -> 43792000 | C21: =C12-C19 -> 106274000 | D21: =D12-D19 -> 186056000 | E21: =E12-E19 -> 209086178 | F21: =F12-F19 -> 2.5053823e+08 | G21: =G12-G19 -> 1.8808127e+08 | H21: =H12-H19 -> 1.7806954e+08 | I21: =I12-I19 -> 1.9485308e+08 | ... M21: =M12-M19 -> 2.8871e-08

Sheet Income Statement
A1: Statement of Operations
A2: Movement in each fiscal year, plus inception to date.
A4: (US dollars) | B4: FY2019 | C4: FY2020 | D4: FY2021 | E4: FY2022 | F4: FY2023 | G4: FY2024 | H4: FY2025 | I4: FY2026 | J4: FY2027 | K4: FY2028 | L4: FY2029 | M4: FY2030 | N4: Inception to date
A5: INVESTMENT INCOME
A6: Interest income — PIK | B6: =-('Trial Balance'!D$21) -> 0 | C6: =-(('Trial Balance'!E$21-'Trial Balance'!D$21)) -> 0 | D6: =-(('Trial Balance'!F$21-'Trial Balance'!E$21)) -> 0 | E6: =-(('Trial Balance'!G$21-'Trial Balance'!F$21)) -> 1298178 | F6: =-(('Trial Balance'!H$21-'Trial Balance'!G$21)) -> 1920056.1 | G6: =-(('Trial Balance'!I$21-'Trial Balance'!H$21)) -> 2161040.1 | H6: =-(('Trial Balance'!J$21-'Trial Balance'!I$21)) -> 2432269.6 | I6: =-(('Trial Balance'!K$21-'Trial Balance'!J$21)) -> 2737540.9 | J6: =-(('Trial Balance'!L$21-'Trial Balance'!K$21)) -> 3081126.4 | ... M6: =-(('Trial Balance'!O$21-'Trial Balance'!N$21)) -> 0 | N6: =SUM(B6:M6) -> 16192278
A7: Interest income — other | B7: =-('Trial Balance'!D$22) -> 0 | C7: =-(('Trial Balance'!E$22-'Trial Balance'!D$22)) -> 0 | D7: =-(('Trial Balance'!F$22-'Trial Balance'!E$22)) -> 0 | E7: =-(('Trial Balance'!G$22-'Trial Balance'!F$22)) -> 0 | F7: =-(('Trial Balance'!H$22-'Trial Balance'!G$22)) -> 0 | G7: =-(('Trial Balance'!I$22-'Trial Balance'!H$22)) -> 0 | H7: =-(('Trial Balance'!J$22-'Trial Balance'!I$22)) -> 0 | I7: =-(('Trial Balance'!K$22-'Trial Balance'!J$22)) -> 0 | J7: =-(('Trial Balance'!L$22-'Trial Balance'!K$22)) -> 0 | ... M7: =-(('Trial Balance'!O$22-'Trial Balance'!N$22)) -> 0 | N7: =SUM(B7:M7) -> 0
A8: Other income — monitoring fees | B8: =-('Trial Balance'!D$23) -> 0 | C8: =-(('Trial Balance'!E$23-'Trial Balance'!D$23)) -> 0 | D8: =-(('Trial Balance'!F$23-'Trial Balance'!E$23)) -> 0 | E8: =-(('Trial Balance'!G$23-'Trial Balance'!F$23)) -> 0 | F8: =-(('Trial Balance'!H$23-'Trial Balance'!G$23)) -> 0 | G8: =-(('Trial Balance'!I$23-'Trial Balance'!H$23)) -> 0 | H8: =-(('Trial Balance'!J$23-'Trial Balance'!I$23)) -> 0 | I8: =-(('Trial Balance'!K$23-'Trial Balance'!J$23)) -> 0 | J8: =-(('Trial Balance'!L$23-'Trial Balance'!K$23)) -> 0 | ... M8: =-(('Trial Balance'!O$23-'Trial Balance'!N$23)) -> 0 | N8: =SUM(B8:M8) -> 0
A9: Total investment income | B9: =-('Trial Balance'!D$21+'Trial Balance'!D$22+'Trial Balance'!D$23) -> 0 | C9: =-(('Trial Balance'!E$21-'Trial Balance'!D$21)+('Trial Balance'!E$22-'Trial Balance'!D$22)+('Trial Balance'!E$23-'Trial Balance'!D$23)) -> 0 | D9: =-(('Trial Balance'!F$21-'Trial Balance'!E$21)+('Trial Balance'!F$22-'Trial Balance'!E$22)+('Trial Balance'!F$23-'Trial Balance'!E$23)) -> 0 | E9: =-(('Trial Balance'!G$21-'Trial Balance'!F$21)+('Trial Balance'!G$22-'Trial Balance'!F$22)+('Trial Balance'!G$23-'Trial Balance'!F$23)) -> 1298178 | F9: =-(('Trial Balance'!H$21-'Trial Balance'!G$21)+('Trial Balance'!H$22-'Trial Balance'!G$22)+('Trial Balance'!H$23-'Trial Balance'!G$23)) -> 1920056.1 | G9: =-(('Trial Balance'!I$21-'Trial Balance'!H$21)+('Trial Balance'!I$22-'Trial Balance'!H$22)+('Trial Balance'!I$23-'Trial Balance'!H$23)) -> 2161040.1 | H9: =-(('Trial Balance'!J$21-'Trial Balance'!I$21)+('Trial Balance'!J$22-'Trial Balance'!I$22)+('Trial Balance'!J$23-'Trial Balance'!I$23)) -> 2432269.6 | I9: =-(('Trial Balance'!K$21-'Trial Balance'!J$21)+('Trial Balance'!K$22-'Trial Balance'!J$22)+('Trial Balance'!K$23-'Trial Balance'!J$23)) -> 2737540.9 | J9: =-(('Trial Balance'!L$21-'Trial Balance'!K$21)+('Trial Balance'!L$22-'Trial Balance'!K$22)+('Trial Balance'!L$23-'Trial Balance'!K$23)) -> 3081126.4 | ... M9: =-(('Trial Balance'!O$21-'Trial Balance'!N$21)+('Trial Balance'!O$22-'Trial Balance'!N$22)+('Trial Balance'!O$23-'Trial Balance'!N$23)) -> 0 | N9: =SUM(B9:M9) -> 16192278
A11: EXPENSES
A12: Management fee | B12: ='Trial Balance'!D$24 -> 2600000 | C12: =('Trial Balance'!E$24-'Trial Balance'!D$24) -> 4550000 | D12: =('Trial Balance'!F$24-'Trial Balance'!E$24) -> 4900000 | E12: =('Trial Balance'!G$24-'Trial Balance'!F$24) -> 4900000 | F12: =('Trial Balance'!H$24-'Trial Balance'!G$24) -> 4900000 | G12: =('Trial Balance'!I$24-'Trial Balance'!H$24) -> 4900000 | H12: =('Trial Balance'!J$24-'Trial Balance'!I$24) -> 3510000 | I12: =('Trial Balance'!K$24-'Trial Balance'!J$24) -> 2120000 | J12: =('Trial Balance'!L$24-'Trial Balance'!K$24) -> 1595000 | ... M12: =('Trial Balance'!O$24-'Trial Balance'!N$24) -> 0 | N12: =SUM(B12:M12) -> 34940000
A13: Less: management fee offset | B13: ='Trial Balance'!D$25 -> 0 | C13: =('Trial Balance'!E$25-'Trial Balance'!D$25) -> 0 | D13: =('Trial Balance'!F$25-'Trial Balance'!E$25) -> -350000 | E13: =('Trial Balance'!G$25-'Trial Balance'!F$25) -> -400000 | F13: =('Trial Balance'!H$25-'Trial Balance'!G$25) -> -400000 | G13: =('Trial Balance'!I$25-'Trial Balance'!H$25) -> -250000 | H13: =('Trial Balance'!J$25-'Trial Balance'!I$25) -> 0 | I13: =('Trial Balance'!K$25-'Trial Balance'!J$25) -> 0 | J13: =('Trial Balance'!L$25-'Trial Balance'!K$25) -> 0 | ... M13: =('Trial Balance'!O$25-'Trial Balance'!N$25) -> 0 | N13: =SUM(B13:M13) -> -1400000
A14: Organizational costs | B14: ='Trial Balance'!D$26 -> 1200000 | C14: =('Trial Balance'!E$26-'Trial Balance'!D$26) -> 0 | D14: =('Trial Balance'!F$26-'Trial Balance'!E$26) -> 0 | E14: =('Trial Balance'!G$26-'Trial Balance'!F$26) -> 0 | F14: =('Trial Balance'!H$26-'Trial Balance'!G$26) -> 0 | G14: =('Trial Balance'!I$26-'Trial Balance'!H$26) -> 0 | H14: =('Trial Balance'!J$26-'Trial Balance'!I$26) -> 0 | I14: =('Trial Balance'!K$26-'Trial Balance'!J$26) -> 0 | J14: =('Trial Balance'!L$26-'Trial Balance'!K$26) -> 0 | ... M14: =('Trial Balance'!O$26-'Trial Balance'!N$26) -> 0 | N14: =SUM(B14:M14) -> 1200000
A15: Amortization of deferred offering costs | B15: ='Trial Balance'!D$27 -> 0 | C15: =('Trial Balance'!E$27-'Trial Balance'!D$27) -> 0 | D15: =('Trial Balance'!F$27-'Trial Balance'!E$27) -> 0 | E15: =('Trial Balance'!G$27-'Trial Balance'!F$27) -> 0 | F15: =('Trial Balance'!H$27-'Trial Balance'!G$27) -> 0 | G15: =('Trial Balance'!I$27-'Trial Balance'!H$27) -> 0 | H15: =('Trial Balance'!J$27-'Trial Balance'!I$27) -> 0 | I15: =('Trial Balance'!K$27-'Trial Balance'!J$27) -> 0 | J15: =('Trial Balance'!L$27-'Trial Balance'!K$27) -> 0 | ... M15: =('Trial Balance'!O$27-'Trial Balance'!N$27) -> 0 | N15: =SUM(B15:M15) -> 0
A16: Professional fees — audit and tax | B16: ='Trial Balance'!D$28 -> 120000 | C16: =('Trial Balance'!E$28-'Trial Balance'!D$28) -> 180000 | D16: =('Trial Balance'!F$28-'Trial Balance'!E$28) -> 180000 | E16: =('Trial Balance'!G$28-'Trial Balance'!F$28) -> 180000 | F16: =('Trial Balance'!H$28-'Trial Balance'!G$28) -> 180000 | G16: =('Trial Balance'!I$28-'Trial Balance'!H$28) -> 180000 | H16: =('Trial Balance'!J$28-'Trial Balance'!I$28) -> 192000 | I16: =('Trial Balance'!K$28-'Trial Balance'!J$28) -> 192000 | J16: =('Trial Balance'!L$28-'Trial Balance'!K$28) -> 192000 | ... M16: =('Trial Balance'!O$28-'Trial Balance'!N$28) -> 96000 | N16: =SUM(B16:M16) -> 2076000
A17: Professional fees — legal | B17: ='Trial Balance'!D$29 -> 140000 | C17: =('Trial Balance'!E$29-'Trial Balance'!D$29) -> 72000 | D17: =('Trial Balance'!F$29-'Trial Balance'!E$29) -> 72000 | E17: =('Trial Balance'!G$29-'Trial Balance'!F$29) -> 72000 | F17: =('Trial Balance'!H$29-'Trial Balance'!G$29) -> 72000 | G17: =('Trial Balance'!I$29-'Trial Balance'!H$29) -> 72000 | H17: =('Trial Balance'!J$29-'Trial Balance'!I$29) -> 60000 | I17: =('Trial Balance'!K$29-'Trial Balance'!J$29) -> 60000 | J17: =('Trial Balance'!L$29-'Trial Balance'!K$29) -> 60000 | ... M17: =('Trial Balance'!O$29-'Trial Balance'!N$29) -> 30000 | N17: =SUM(B17:M17) -> 830000
A18: Fund administration fees | B18: ='Trial Balance'!D$30 -> 180000 | C18: =('Trial Balance'!E$30-'Trial Balance'!D$30) -> 250000 | D18: =('Trial Balance'!F$30-'Trial Balance'!E$30) -> 250000 | E18: =('Trial Balance'!G$30-'Trial Balance'!F$30) -> 250000 | F18: =('Trial Balance'!H$30-'Trial Balance'!G$30) -> 250000 | G18: =('Trial Balance'!I$30-'Trial Balance'!H$30) -> 250000 | H18: =('Trial Balance'!J$30-'Trial Balance'!I$30) -> 220000 | I18: =('Trial Balance'!K$30-'Trial Balance'!J$30) -> 220000 | J18: =('Trial Balance'!L$30-'Trial Balance'!K$30) -> 220000 | ... M18: =('Trial Balance'!O$30-'Trial Balance'!N$30) -> 110000 | N18: =SUM(B18:M18) -> 2640000
A19: Custody and bank fees | B19: ='Trial Balance'!D$31 -> 20000 | C19: =('Trial Balance'!E$31-'Trial Balance'!D$31) -> 30000 | D19: =('Trial Balance'!F$31-'Trial Balance'!E$31) -> 30000 | E19: =('Trial Balance'!G$31-'Trial Balance'!F$31) -> 30000 | F19: =('Trial Balance'!H$31-'Trial Balance'!G$31) -> 30000 | G19: =('Trial Balance'!I$31-'Trial Balance'!H$31) -> 30000 | H19: =('Trial Balance'!J$31-'Trial Balance'!I$31) -> 30000 | I19: =('Trial Balance'!K$31-'Trial Balance'!J$31) -> 30000 | J19: =('Trial Balance'!L$31-'Trial Balance'!K$31) -> 30000 | ... M19: =('Trial Balance'!O$31-'Trial Balance'!N$31) -> 15000 | N19: =SUM(B19:M19) -> 335000
A20: Interest expense — subscription line | B20: ='Trial Balance'!D$32 -> 0 | C20: =('Trial Balance'!E$32-'Trial Balance'!D$32) -> 0 | D20: =('Trial Balance'!F$32-'Trial Balance'!E$32) -> 0 | E20: =('Trial Balance'!G$32-'Trial Balance'!F$32) -> 0 | F20: =('Trial Balance'!H$32-'Trial Balance'!G$32) -> 0 | G20: =('Trial Balance'!I$32-'Trial Balance'!H$32) -> 0 | H20: =('Trial Balance'!J$32-'Trial Balance'!I$32) -> 0 | I20: =('Trial Balance'!K$32-'Trial Balance'!J$32) -> 0 | J20: =('Trial Balance'!L$32-'Trial Balance'!K$32) -> 0 | ... M20: =('Trial Balance'!O$32-'Trial Balance'!N$32) -> 0 | N20: =SUM(B20:M20) -> 0
A21: Other fund expenses | B21: ='Trial Balance'!D$33 -> 48000 | C21: =('Trial Balance'!E$33-'Trial Balance'!D$33) -> 36000 | D21: =('Trial Balance'!F$33-'Trial Balance'!E$33) -> 36000 | E21: =('Trial Balance'!G$33-'Trial Balance'!F$33) -> 36000 | F21: =('Trial Balance'!H$33-'Trial Balance'!G$33) -> 36000 | G21: =('Trial Balance'!I$33-'Trial Balance'!H$33) -> 36000 | H21: =('Trial Balance'!J$33-'Trial Balance'!I$33) -> 32000 | I21: =('Trial Balance'!K$33-'Trial Balance'!J$33) -> 32000 | J21: =('Trial Balance'!L$33-'Trial Balance'!K$33) -> 32000 | ... M21: =('Trial Balance'!O$33-'Trial Balance'!N$33) -> 16000 | N21: =SUM(B21:M21) -> 404000
A22: Total expenses | B22: ='Trial Balance'!D$24+'Trial Balance'!D$25+'Trial Balance'!D$26+'Trial Balance'!D$27+'Trial Balance'!D$28+'Trial Balance'!D$29+'Trial Balance'!D$30+'Trial Balance'!D$31+'Trial Balance'!D$32+'Trial Balance'!D$33 -> 4308000 | C22: =('Trial Balance'!E$24-'Trial Balance'!D$24)+('Trial Balance'!E$25-'Trial Balance'!D$25)+('Trial Balance'!E$26-'Trial Balance'!D$26)+('Trial Balance'!E$27-'Trial Balance'!D$27)+('Trial Balance'!E$28-'Trial Balance'!D$28)+('Trial Balance'!E$29-'Trial Balance'!D$29)+('Trial Balance'!E$30-'Trial Balance'!D$30)+('Trial Balance'!E$31-'Trial Balance'!D$31)+('Trial Balance'!E$32-'Trial Balance'!D$32)+('Trial Balance'!E$33-'Trial Balance'!D$33) -> 5118000 | D22: =('Trial Balance'!F$24-'Trial Balance'!E$24)+('Trial Balance'!F$25-'Trial Balance'!E$25)+('Trial Balance'!F$26-'Trial Balance'!E$26)+('Trial Balance'!F$27-'Trial Balance'!E$27)+('Trial Balance'!F$28-'Trial Balance'!E$28)+('Trial Balance'!F$29-'Trial Balance'!E$29)+('Trial Balance'!F$30-'Trial Balance'!E$30)+('Trial Balance'!F$31-'Trial Balance'!E$31)+('Trial Balance'!F$32-'Trial Balance'!E$32)+('Trial Balance'!F$33-'Trial Balance'!E$33) -> 5118000 | E22: =('Trial Balance'!G$24-'Trial Balance'!F$24)+('Trial Balance'!G$25-'Trial Balance'!F$25)+('Trial Balance'!G$26-'Trial Balance'!F$26)+('Trial Balance'!G$27-'Trial Balance'!F$27)+('Trial Balance'!G$28-'Trial Balance'!F$28)+('Trial Balance'!G$29-'Trial Balance'!F$29)+('Trial Balance'!G$30-'Trial Balance'!F$30)+('Trial Balance'!G$31-'Trial Balance'!F$31)+('Trial Balance'!G$32-'Trial Balance'!F$32)+('Trial Balance'!G$33-'Trial Balance'!F$33) -> 5068000 | F22: =('Trial Balance'!H$24-'Trial Balance'!G$24)+('Trial Balance'!H$25-'Trial Balance'!G$25)+('Trial Balance'!H$26-'Trial Balance'!G$26)+('Trial Balance'!H$27-'Trial Balance'!G$27)+('Trial Balance'!H$28-'Trial Balance'!G$28)+('Trial Balance'!H$29-'Trial Balance'!G$29)+('Trial Balance'!H$30-'Trial Balance'!G$30)+('Trial Balance'!H$31-'Trial Balance'!G$31)+('Trial Balance'!H$32-'Trial Balance'!G$32)+('Trial Balance'!H$33-'Trial Balance'!G$33) -> 5068000 | G22: =('Trial Balance'!I$24-'Trial Balance'!H$24)+('Trial Balance'!I$25-'Trial Balance'!H$25)+('Trial Balance'!I$26-'Trial Balance'!H$26)+('Trial Balance'!I$27-'Trial Balance'!H$27)+('Trial Balance'!I$28-'Trial Balance'!H$28)+('Trial Balance'!I$29-'Trial Balance'!H$29)+('Trial Balance'!I$30-'Trial Balance'!H$30)+('Trial Balance'!I$31-'Trial Balance'!H$31)+('Trial Balance'!I$32-'Trial Balance'!H$32)+('Trial Balance'!I$33-'Trial Balance'!H$33) -> 5218000 | H22: =('Trial Balance'!J$24-'Trial Balance'!I$24)+('Trial Balance'!J$25-'Trial Balance'!I$25)+('Trial Balance'!J$26-'Trial Balance'!I$26)+('Trial Balance'!J$27-'Trial Balance'!I$27)+('Trial Balance'!J$28-'Trial Balance'!I$28)+('Trial Balance'!J$29-'Trial Balance'!I$29)+('Trial Balance'!J$30-'Trial Balance'!I$30)+('Trial Balance'!J$31-'Trial Balance'!I$31)+('Trial Balance'!J$32-'Trial Balance'!I$32)+('Trial Balance'!J$33-'Trial Balance'!I$33) -> 4044000 | I22: =('Trial Balance'!K$24-'Trial Balance'!J$24)+('Trial Balance'!K$25-'Trial Balance'!J$25)+('Trial Balance'!K$26-'Trial Balance'!J$26)+('Trial Balance'!K$27-'Trial Balance'!J$27)+('Trial Balance'!K$28-'Trial Balance'!J$28)+('Trial Balance'!K$29-'Trial Balance'!J$29)+('Trial Balance'!K$30-'Trial Balance'!J$30)+('Trial Balance'!K$31-'Trial Balance'!J$31)+('Trial Balance'!K$32-'Trial Balance'!J$32)+('Trial Balance'!K$33-'Trial Balance'!J$33) -> 2654000 | J22: =('Trial Balance'!L$24-'Trial Balance'!K$24)+('Trial Balance'!L$25-'Trial Balance'!K$25)+('Trial Balance'!L$26-'Trial Balance'!K$26)+('Trial Balance'!L$27-'Trial Balance'!K$27)+('Trial Balance'!L$28-'Trial Balance'!K$28)+('Trial Balance'!L$29-'Trial Balance'!K$29)+('Trial Balance'!L$30-'Trial Balance'!K$30)+('Trial Balance'!L$31-'Trial Balance'!K$31)+('Trial Balance'!L$32-'Trial Balance'!K$32)+('Trial Balance'!L$33-'Trial Balance'!K$33) -> 2129000 | ... M22: =('Trial Balance'!O$24-'Trial Balance'!N$24)+('Trial Balance'!O$25-'Trial Balance'!N$25)+('Trial Balance'!O$26-'Trial Balance'!N$26)+('Trial Balance'!O$27-'Trial Balance'!N$27)+('Trial Balance'!O$28-'Trial Balance'!N$28)+('Trial Balance'!O$29-'Trial Balance'!N$29)+('Trial Balance'!O$30-'Trial Balance'!N$30)+('Trial Balance'!O$31-'Trial Balance'!N$31)+('Trial Balance'!O$32-'Trial Balance'!N$32)+('Trial Balance'!O$33-'Trial Balance'!N$33) -> 267000 | N22: =SUM(B22:M22) -> 41025000
A23: NET INVESTMENT INCOME / (LOSS) | B23: =B9-B22 -> -4308000 | C23: =C9-C22 -> -5118000 | D23: =D9-D22 -> -5118000 | E23: =E9-E22 -> -3769822 | F23: =F9-F22 -> -3147943.9 | G23: =G9-G22 -> -3056959.9 | H23: =H9-H22 -> -1611730.4 | I23: =I9-I22 -> 83540.89 | ... N23: =N9-N22 -> -24832722
A25: REALIZED AND UNREALIZED
A26: Net realized gain / (loss) on investments | B26: =-('Trial Balance'!D$34) -> 0 | C26: =-(('Trial Balance'!E$34-'Trial Balance'!D$34)) -> 0 | D26: =-(('Trial Balance'!F$34-'Trial Balance'!E$34)) -> 0 | E26: =-(('Trial Balance'!G$34-'Trial Balance'!F$34)) -> 0 | F26: =-(('Trial Balance'!H$34-'Trial Balance'!G$34)) -> 0 | G26: =-(('Trial Balance'!I$34-'Trial Balance'!H$34)) -> 68000000 | H26: =-(('Trial Balance'!J$34-'Trial Balance'!I$34)) -> 4800000 | I26: =-(('Trial Balance'!K$34-'Trial Balance'!J$34)) -> 0 | J26: =-(('Trial Balance'!L$34-'Trial Balance'!K$34)) -> 57000000 | ... M26: =-(('Trial Balance'!O$34-'Trial Balance'!N$34)) -> 0 | N26: =SUM(B26:M26) -> 224800000
A27: Net change in unrealized appreciation / (depreciation) | B27: =-('Trial Balance'!D$35) -> 1500000 | C27: =-(('Trial Balance'!E$35-'Trial Balance'!D$35)) -> 7500000 | D27: =-(('Trial Balance'!F$35-'Trial Balance'!E$35)) -> 30000000 | E27: =-(('Trial Balance'!G$35-'Trial Balance'!F$35)) -> -4000000 | F27: =-(('Trial Balance'!H$35-'Trial Balance'!G$35)) -> 31000000 | G27: =-(('Trial Balance'!I$35-'Trial Balance'!H$35)) -> -15000000 | H27: =-(('Trial Balance'!J$35-'Trial Balance'!I$35)) -> 11500000 | I27: =-(('Trial Balance'!K$35-'Trial Balance'!J$35)) -> 15500000 | J27: =-(('Trial Balance'!L$35-'Trial Balance'!K$35)) -> -14000000 | ... M27: =-(('Trial Balance'!O$35-'Trial Balance'!N$35)) -> 0 | N27: =SUM(B27:M27) -> 0
A28: NET INCREASE / (DECREASE) IN NET ASSETS FROM OPERATIONS | B28: =B23+B26+B27 -> -2808000 | C28: =C23+C26+C27 -> 2382000 | D28: =D23+D26+D27 -> 24882000 | E28: =E23+E26+E27 -> -7769822 | F28: =F23+F26+F27 -> 27852056 | G28: =G23+G26+G27 -> 49943040 | H28: =H23+H26+H27 -> 14688270 | I28: =I23+I26+I27 -> 15583541 | ... N28: =N23+N26+N27 -> 1.9996728e+08

Sheet Changes in Partners Capital
A1: Statement of Changes in Partners' Capital
A4: (US dollars) | B4: FY2019 | C4: FY2020 | D4: FY2021 | E4: FY2022 | F4: FY2023 | G4: FY2024 | H4: FY2025 | I4: FY2026 | J4: FY2027 | K4: FY2028 | L4: FY2029 | M4: FY2030 | N4: Inception to date
A5: Partners' capital, beginning of year | B5: 0 | C5: ='Balance Sheet'!B21 -> 43792000 | D5: ='Balance Sheet'!C21 -> 106274000 | E5: ='Balance Sheet'!D21 -> 186056000 | F5: ='Balance Sheet'!E21 -> 209086178 | G5: ='Balance Sheet'!F21 -> 2.5053823e+08 | H5: ='Balance Sheet'!G21 -> 1.8808127e+08 | I5: ='Balance Sheet'!H21 -> 1.7806954e+08 | J5: ='Balance Sheet'!I21 -> 1.9485308e+08 | ... M5: ='Balance Sheet'!L21 -> 2734277.7 | N5: 0
A6: Capital contributions | B6: =-('Trial Balance'!D$17) -> 47500000 | C6: =-(('Trial Balance'!E$17-'Trial Balance'!D$17)) -> 60100000 | D6: =-(('Trial Balance'!F$17-'Trial Balance'!E$17)) -> 54900000 | E6: =-(('Trial Balance'!G$17-'Trial Balance'!F$17)) -> 30800000 | F6: =-(('Trial Balance'!H$17-'Trial Balance'!G$17)) -> 13600000 | G6: =-(('Trial Balance'!I$17-'Trial Balance'!H$17)) -> 2800000 | H6: =-(('Trial Balance'!J$17-'Trial Balance'!I$17)) -> 1300000 | I6: =-(('Trial Balance'!K$17-'Trial Balance'!J$17)) -> 1200000 | J6: =-(('Trial Balance'!L$17-'Trial Balance'!K$17)) -> 1100000 | ... M6: =-(('Trial Balance'!O$17-'Trial Balance'!N$17)) -> 0 | N6: =SUM(B6:M6) -> 213300000
A7: Offering costs charged against capital | B7: =-('Trial Balance'!D$18) -> -900000 | C7: =-(('Trial Balance'!E$18-'Trial Balance'!D$18)) -> 0 | D7: =-(('Trial Balance'!F$18-'Trial Balance'!E$18)) -> 0 | E7: =-(('Trial Balance'!G$18-'Trial Balance'!F$18)) -> 0 | F7: =-(('Trial Balance'!H$18-'Trial Balance'!G$18)) -> 0 | G7: =-(('Trial Balance'!I$18-'Trial Balance'!H$18)) -> 0 | H7: =-(('Trial Balance'!J$18-'Trial Balance'!I$18)) -> 0 | I7: =-(('Trial Balance'!K$18-'Trial Balance'!J$18)) -> 0 | J7: =-(('Trial Balance'!L$18-'Trial Balance'!K$18)) -> 0 | ... M7: =-(('Trial Balance'!O$18-'Trial Balance'!N$18)) -> 0 | N7: =SUM(B7:M7) -> -900000
A8: Capital distributions | B8: =-('Trial Balance'!D$19) -> 0 | C8: =-(('Trial Balance'!E$19-'Trial Balance'!D$19)) -> 0 | D8: =-(('Trial Balance'!F$19-'Trial Balance'!E$19)) -> 0 | E8: =-(('Trial Balance'!G$19-'Trial Balance'!F$19)) -> 0 | F8: =-(('Trial Balance'!H$19-'Trial Balance'!G$19)) -> 0 | G8: =-(('Trial Balance'!I$19-'Trial Balance'!H$19)) -> -115200000 | H8: =-(('Trial Balance'!J$19-'Trial Balance'!I$19)) -> -26000000 | I8: =-(('Trial Balance'!K$19-'Trial Balance'!J$19)) -> 0 | J8: =-(('Trial Balance'!L$19-'Trial Balance'!K$19)) -> -89200000 | ... M8: =-(('Trial Balance'!O$19-'Trial Balance'!N$19)) -> -2467277.7 | N8: =SUM(B8:M8) -> -4.1236728e+08
A9: Net increase / (decrease) from operations | B9: ='Income Statement'!B28 -> -2808000 | C9: ='Income Statement'!C28 -> 2382000 | D9: ='Income Statement'!D28 -> 24882000 | E9: ='Income Statement'!E28 -> -7769822 | F9: ='Income Statement'!F28 -> 27852056 | G9: ='Income Statement'!G28 -> 49943040 | H9: ='Income Statement'!H28 -> 14688270 | I9: ='Income Statement'!I28 -> 15583541 | ... N9: ='Income Statement'!N28 -> 1.9996728e+08
A10: Partners' capital, end of year | B10: =B5+B6+B7+B8+B9 -> 43792000 | C10: =C5+C6+C7+C8+C9 -> 106274000 | D10: =D5+D6+D7+D8+D9 -> 186056000 | E10: =E5+E6+E7+E8+E9 -> 209086178 | F10: =F5+F6+F7+F8+F9 -> 2.5053823e+08 | G10: =G5+G6+G7+G8+G9 -> 1.8808127e+08 | H10: =H5+H6+H7+H8+H9 -> 1.7806954e+08 | I10: =I5+I6+I7+I8+I9 -> 1.9485308e+08 | ... M10: =M5+M6+M7+M8+M9 -> 4.0978193e-08
A12: Reconciliation — Balance Sheet net assets | B12: ='Balance Sheet'!B21 -> 43792000 | C12: ='Balance Sheet'!C21 -> 106274000 | D12: ='Balance Sheet'!D21 -> 186056000 | E12: ='Balance Sheet'!E21 -> 209086178 | F12: ='Balance Sheet'!F21 -> 2.5053823e+08 | G12: ='Balance Sheet'!G21 -> 1.8808127e+08 | H12: ='Balance Sheet'!H21 -> 1.7806954e+08 | I12: ='Balance Sheet'!I21 -> 1.9485308e+08 | ... M12: ='Balance Sheet'!M21 -> 2.8871e-08
A13: Difference — must be zero | B13: =B10-B12 -> 0 | C13: =C10-C12 -> 0 | D13: =D10-D12 -> 0 | E13: =E10-E12 -> 0 | F13: =F10-F12 -> 0 | G13: =G10-G12 -> 0 | H13: =H10-H12 -> 0 | I13: =I10-I12 -> 0 | ... M13: =M10-M12 -> 1.2107193e-08

Sheet Cash Flow Statement
A1: Statement of Cash Flows
A2: Indirect method. Under ASC 946 purchases and sales of investments are operating activities and are presented gross. Non-cash items are removed above, so the statement ties to cash in every year.
A4: (US dollars) | B4: FY2019 | C4: FY2020 | D4: FY2021 | E4: FY2022 | F4: FY2023 | G4: FY2024 | H4: FY2025 | I4: FY2026 | J4: FY2027 | K4: FY2028 | L4: FY2029 | M4: FY2030
A5: CASH FLOWS FROM OPERATING ACTIVITIES
A6: Net increase / (decrease) in net assets from operations | B6: ='Income Statement'!B28 -> -2808000 | C6: ='Income Statement'!C28 -> 2382000 | D6: ='Income Statement'!D28 -> 24882000 | E6: ='Income Statement'!E28 -> -7769822 | F6: ='Income Statement'!F28 -> 27852056 | G6: ='Income Statement'!G28 -> 49943040 | H6: ='Income Statement'!H28 -> 14688270 | I6: ='Income Statement'!I28 -> 15583541 | ... M6: ='Income Statement'!M28 -> -267000
A7: Adjustments to reconcile to net cash provided by / (used in) operating activities:
A8: Net realized (gain) / loss on investments | B8: =-'Income Statement'!B26 -> 0 | C8: =-'Income Statement'!C26 -> 0 | D8: =-'Income Statement'!D26 -> 0 | E8: =-'Income Statement'!E26 -> 0 | F8: =-'Income Statement'!F26 -> 0 | G8: =-'Income Statement'!G26 -> -68000000 | H8: =-'Income Statement'!H26 -> -4800000 | I8: =-'Income Statement'!I26 -> 0 | ... M8: =-'Income Statement'!M26 -> 0
A9: Net change in unrealized (appreciation) / depreciation | B9: =-'Income Statement'!B27 -> -1500000 | C9: =-'Income Statement'!C27 -> -7500000 | D9: =-'Income Statement'!D27 -> -30000000 | E9: =-'Income Statement'!E27 -> 4000000 | F9: =-'Income Statement'!F27 -> -31000000 | G9: =-'Income Statement'!G27 -> 15000000 | H9: =-'Income Statement'!H27 -> -11500000 | I9: =-'Income Statement'!I27 -> -15500000 | ... M9: =-'Income Statement'!M27 -> 0
A10: PIK interest income capitalised into the note principal (non-cash) | B10: =-'Income Statement'!B6 -> 0 | C10: =-'Income Statement'!C6 -> 0 | D10: =-'Income Statement'!D6 -> 0 | E10: =-'Income Statement'!E6 -> -1298178 | F10: =-'Income Statement'!F6 -> -1920056.1 | G10: =-'Income Statement'!G6 -> -2161040.1 | H10: =-'Income Statement'!H6 -> -2432269.6 | I10: =-'Income Statement'!I6 -> -2737540.9 | ... M10: =-'Income Statement'!M6 -> 0
A11: Purchases of investments, at cost | B11: =-(SUMIFS('Journal Entries'!$G$5:$G$785,'Journal Entries'!$D$5:$D$785,"1100",'Journal Entries'!$C$5:$C$785,"2019*",'Journal Entries'!$F$5:$F$785,"<>3.1 bridge conversion",'Journal Entries'!$F$5:$F$785,"<>3.1 PIK capitalisation")+SUMIFS('Journal Entries'!$G$5:$G$785,'Journal Entries'!$D$5:$D$785,"1150",'Journal Entries'!$C$5:$C$785,"2019*")) -> -42000000 | C11: =-(SUMIFS('Journal Entries'!$G$5:$G$785,'Journal Entries'!$D$5:$D$785,"1100",'Journal Entries'!$C$5:$C$785,"2020*",'Journal Entries'!$F$5:$F$785,"<>3.1 bridge conversion",'Journal Entries'!$F$5:$F$785,"<>3.1 PIK capitalisation")+SUMIFS('Journal Entries'!$G$5:$G$785,'Journal Entries'!$D$5:$D$785,"1150",'Journal Entries'!$C$5:$C$785,"2020*")) -> -55000000 | D11: =-(SUMIFS('Journal Entries'!$G$5:$G$785,'Journal Entries'!$D$5:$D$785,"1100",'Journal Entries'!$C$5:$C$785,"2021*",'Journal Entries'!$F$5:$F$785,"<>3.1 bridge conversion",'Journal Entries'!$F$5:$F$785,"<>3.1 PIK capitalisation")+SUMIFS('Journal Entries'!$G$5:$G$785,'Journal Entries'!$D$5:$D$785,"1150",'Journal Entries'!$C$5:$C$785,"2021*")) -> -48000000 | E11: =-(SUMIFS('Journal Entries'!$G$5:$G$785,'Journal Entries'!$D$5:$D$785,"1100",'Journal Entries'!$C$5:$C$785,"2022*",'Journal Entries'!$F$5:$F$785,"<>3.1 bridge conversion",'Journal Entries'!$F$5:$F$785,"<>3.1 PIK capitalisation")+SUMIFS('Journal Entries'!$G$5:$G$785,'Journal Entries'!$D$5:$D$785,"1150",'Journal Entries'!$C$5:$C$785,"2022*")) -> -26000000 | F11: =-(SUMIFS('Journal Entries'!$G$5:$G$785,'Journal Entries'!$D$5:$D$785,"1100",'Journal Entries'!$C$5:$C$785,"2023*",'Journal Entries'!$F$5:$F$785,"<>3.1 bridge conversion",'Journal Entries'!$F$5:$F$785,"<>3.1 PIK capitalisation")+SUMIFS('Journal Entries'!$G$5:$G$785,'Journal Entries'!$D$5:$D$785,"1150",'Journal Entries'!$C$5:$C$785,"2023*")) -> -9000000 | G11: =-(SUMIFS('Journal Entries'!$G$5:$G$785,'Journal Entries'!$D$5:$D$785,"1100",'Journal Entries'!$C$5:$C$785,"2024*",'Journal Entries'!$F$5:$F$785,"<>3.1 bridge conversion",'Journal Entries'!$F$5:$F$785,"<>3.1 PIK capitalisation")+SUMIFS('Journal Entries'!$G$5:$G$785,'Journal Entries'!$D$5:$D$785,"1150",'Journal Entries'!$C$5:$C$785,"2024*")) -> 0 | H11: =-(SUMIFS('Journal Entries'!$G$5:$G$785,'Journal Entries'!$D$5:$D$785,"1100",'Journal Entries'!$C$5:$C$785,"2025*",'Journal Entries'!$F$5:$F$785,"<>3.1 bridge conversion",'Journal Entries'!$F$5:$F$785,"<>3.1 PIK capitalisation")+SUMIFS('Journal Entries'!$G$5:$G$785,'Journal Entries'!$D$5:$D$785,"1150",'Journal Entries'!$C$5:$C$785,"2025*")) -> 0 | I11: =-(SUMIFS('Journal Entries'!$G$5:$G$785,'Journal Entries'!$D$5:$D$785,"1100",'Journal Entries'!$C$5:$C$785,"2026*",'Journal Entries'!$F$5:$F$785,"<>3.1 bridge conversion",'Journal Entries'!$F$5:$F$785,"<>3.1 PIK capitalisation")+SUMIFS('Journal Entries'!$G$5:$G$785,'Journal Entries'!$D$5:$D$785,"1150",'Journal Entries'!$C$5:$C$785,"2026*")) -> 0 | J11: =-(SUMIFS('Journal Entries'!$G$5:$G$785,'Journal Entries'!$D$5:$D$785,"1100",'Journal Entries'!$C$5:$C$785,"2027*",'Journal Entries'!$F$5:$F$785,"<>3.1 bridge conversion",'Journal Entries'!$F$5:$F$785,"<>3.1 PIK capitalisation")+SUMIFS('Journal Entries'!$G$5:$G$785,'Journal Entries'!$D$5:$D$785,"1150",'Journal Entries'!$C$5:$C$785,"2027*")) -> 0 | K11: =-(SUMIFS('Journal Entries'!$G$5:$G$785,'Journal Entries'!$D$5:$D$785,"1100",'Journal Entries'!$C$5:$C$785,"2028*",'Journal Entries'!$F$5:$F$785,"<>3.1 bridge conversion",'Journal Entries'!$F$5:$F$785,"<>3.1 PIK capitalisation")+SUMIFS('Journal Entries'!$G$5:$G$785,'Journal Entries'!$D$5:$D$785,"1150",'Journal Entries'!$C$5:$C$785,"2028*")) -> 0 | L11: =-(SUMIFS('Journal Entries'!$G$5:$G$785,'Journal Entries'!$D$5:$D$785,"1100",'Journal Entries'!$C$5:$C$785,"2029*",'Journal Entries'!$F$5:$F$785,"<>3.1 bridge conversion",'Journal Entries'!$F$5:$F$785,"<>3.1 PIK capitalisation")+SUMIFS('Journal Entries'!$G$5:$G$785,'Journal Entries'!$D$5:$D$785,"1150",'Journal Entries'!$C$5:$C$785,"2029*")) -> 0 | M11: =-(SUMIFS('Journal Entries'!$G$5:$G$785,'Journal Entries'!$D$5:$D$785,"1100",'Journal Entries'!$C$5:$C$785,"2030*",'Journal Entries'!$F$5:$F$785,"<>3.1 bridge conversion",'Journal Entries'!$F$5:$F$785,"<>3.1 PIK capitalisation")+SUMIFS('Journal Entries'!$G$5:$G$785,'Journal Entries'!$D$5:$D$785,"1150",'Journal Entries'!$C$5:$C$785,"2030*")) -> 0
A12: Proceeds from disposition of investments | B12: =SUMIFS('Journal Entries'!$H$5:$H$785,'Journal Entries'!$D$5:$D$785,"1100",'Journal Entries'!$C$5:$C$785,"2019*",'Journal Entries'!$F$5:$F$785,"<>3.1 bridge conversion",'Journal Entries'!$F$5:$F$785,"<>3.1 PIK capitalisation")+'Income Statement'!B26 -> 0 | C12: =SUMIFS('Journal Entries'!$H$5:$H$785,'Journal Entries'!$D$5:$D$785,"1100",'Journal Entries'!$C$5:$C$785,"2020*",'Journal Entries'!$F$5:$F$785,"<>3.1 bridge conversion",'Journal Entries'!$F$5:$F$785,"<>3.1 PIK capitalisation")+'Income Statement'!C26 -> 0 | D12: =SUMIFS('Journal Entries'!$H$5:$H$785,'Journal Entries'!$D$5:$D$785,"1100",'Journal Entries'!$C$5:$C$785,"2021*",'Journal Entries'!$F$5:$F$785,"<>3.1 bridge conversion",'Journal Entries'!$F$5:$F$785,"<>3.1 PIK capitalisation")+'Income Statement'!D26 -> 0 | E12: =SUMIFS('Journal Entries'!$H$5:$H$785,'Journal Entries'!$D$5:$D$785,"1100",'Journal Entries'!$C$5:$C$785,"2022*",'Journal Entries'!$F$5:$F$785,"<>3.1 bridge conversion",'Journal Entries'!$F$5:$F$785,"<>3.1 PIK capitalisation")+'Income Statement'!E26 -> 0 | F12: =SUMIFS('Journal Entries'!$H$5:$H$785,'Journal Entries'!$D$5:$D$785,"1100",'Journal Entries'!$C$5:$C$785,"2023*",'Journal Entries'!$F$5:$F$785,"<>3.1 bridge conversion",'Journal Entries'!$F$5:$F$785,"<>3.1 PIK capitalisation")+'Income Statement'!F26 -> 0 | G12: =SUMIFS('Journal Entries'!$H$5:$H$785,'Journal Entries'!$D$5:$D$785,"1100",'Journal Entries'!$C$5:$C$785,"2024*",'Journal Entries'!$F$5:$F$785,"<>3.1 bridge conversion",'Journal Entries'!$F$5:$F$785,"<>3.1 PIK capitalisation")+'Income Statement'!G26 -> 118000000 | H12: =SUMIFS('Journal Entries'!$H$5:$H$785,'Journal Entries'!$D$5:$D$785,"1100",'Journal Entries'!$C$5:$C$785,"2025*",'Journal Entries'!$F$5:$F$785,"<>3.1 bridge conversion",'Journal Entries'!$F$5:$F$785,"<>3.1 PIK capitalisation")+'Income Statement'!H26 -> 28800000 | I12: =SUMIFS('Journal Entries'!$H$5:$H$785,'Journal Entries'!$D$5:$D$785,"1100",'Journal Entries'!$C$5:$C$785,"2026*",'Journal Entries'!$F$5:$F$785,"<>3.1 bridge conversion",'Journal Entries'!$F$5:$F$785,"<>3.1 PIK capitalisation")+'Income Statement'!I26 -> 0 | J12: =SUMIFS('Journal Entries'!$H$5:$H$785,'Journal Entries'!$D$5:$D$785,"1100",'Journal Entries'!$C$5:$C$785,"2027*",'Journal Entries'!$F$5:$F$785,"<>3.1 bridge conversion",'Journal Entries'!$F$5:$F$785,"<>3.1 PIK capitalisation")+'Income Statement'!J26 -> 92000000 | K12: =SUMIFS('Journal Entries'!$H$5:$H$785,'Journal Entries'!$D$5:$D$785,"1100",'Journal Entries'!$C$5:$C$785,"2028*",'Journal Entries'!$F$5:$F$785,"<>3.1 bridge conversion",'Journal Entries'!$F$5:$F$785,"<>3.1 PIK capitalisation")+'Income Statement'!K26 -> 1.2019228e+08 | L12: =SUMIFS('Journal Entries'!$H$5:$H$785,'Journal Entries'!$D$5:$D$785,"1100",'Journal Entries'!$C$5:$C$785,"2029*",'Journal Entries'!$F$5:$F$785,"<>3.1 bridge conversion",'Journal Entries'!$F$5:$F$785,"<>3.1 PIK capitalisation")+'Income Statement'!L26 -> 62000000 | M12: =SUMIFS('Journal Entries'!$H$5:$H$785,'Journal Entries'!$D$5:$D$785,"1100",'Journal Entries'!$C$5:$C$785,"2030*",'Journal Entries'!$F$5:$F$785,"<>3.1 bridge conversion",'Journal Entries'!$F$5:$F$785,"<>3.1 PIK capitalisation")+'Income Statement'!M26 -> 0
A13: (Increase) / decrease in interest receivable | B13: =-('Trial Balance'!D$10) -> 0 | C13: =-(('Trial Balance'!E$10-'Trial Balance'!D$10)) -> 0 | D13: =-(('Trial Balance'!F$10-'Trial Balance'!E$10)) -> 0 | E13: =-(('Trial Balance'!G$10-'Trial Balance'!F$10)) -> 0 | F13: =-(('Trial Balance'!H$10-'Trial Balance'!G$10)) -> 0 | G13: =-(('Trial Balance'!I$10-'Trial Balance'!H$10)) -> 0 | H13: =-(('Trial Balance'!J$10-'Trial Balance'!I$10)) -> 0 | I13: =-(('Trial Balance'!K$10-'Trial Balance'!J$10)) -> 0 | J13: =-(('Trial Balance'!L$10-'Trial Balance'!K$10)) -> 0 | ... M13: =-(('Trial Balance'!O$10-'Trial Balance'!N$10)) -> 0
A14: (Increase) / decrease in subscriptions receivable and prepaid expenses | B14: =-('Trial Balance'!D$6+'Trial Balance'!D$11) -> 0 | C14: =-(('Trial Balance'!E$6-'Trial Balance'!D$6)+('Trial Balance'!E$11-'Trial Balance'!D$11)) -> 0 | D14: =-(('Trial Balance'!F$6-'Trial Balance'!E$6)+('Trial Balance'!F$11-'Trial Balance'!E$11)) -> 0 | E14: =-(('Trial Balance'!G$6-'Trial Balance'!F$6)+('Trial Balance'!G$11-'Trial Balance'!F$11)) -> 0 | F14: =-(('Trial Balance'!H$6-'Trial Balance'!G$6)+('Trial Balance'!H$11-'Trial Balance'!G$11)) -> 0 | G14: =-(('Trial Balance'!I$6-'Trial Balance'!H$6)+('Trial Balance'!I$11-'Trial Balance'!H$11)) -> 0 | H14: =-(('Trial Balance'!J$6-'Trial Balance'!I$6)+('Trial Balance'!J$11-'Trial Balance'!I$11)) -> 0 | I14: =-(('Trial Balance'!K$6-'Trial Balance'!J$6)+('Trial Balance'!K$11-'Trial Balance'!J$11)) -> 0 | J14: =-(('Trial Balance'!L$6-'Trial Balance'!K$6)+('Trial Balance'!L$11-'Trial Balance'!K$11)) -> 0 | ... M14: =-(('Trial Balance'!O$6-'Trial Balance'!N$6)+('Trial Balance'!O$11-'Trial Balance'!N$11)) -> 0
A15: (Increase) / decrease in deferred offering costs | B15: =-('Trial Balance'!D$12) -> 0 | C15: =-(('Trial Balance'!E$12-'Trial Balance'!D$12)) -> 0 | D15: =-(('Trial Balance'!F$12-'Trial Balance'!E$12)) -> 0 | E15: =-(('Trial Balance'!G$12-'Trial Balance'!F$12)) -> 0 | F15: =-(('Trial Balance'!H$12-'Trial Balance'!G$12)) -> 0 | G15: =-(('Trial Balance'!I$12-'Trial Balance'!H$12)) -> 0 | H15: =-(('Trial Balance'!J$12-'Trial Balance'!I$12)) -> 0 | I15: =-(('Trial Balance'!K$12-'Trial Balance'!J$12)) -> 0 | J15: =-(('Trial Balance'!L$12-'Trial Balance'!K$12)) -> 0 | ... M15: =-(('Trial Balance'!O$12-'Trial Balance'!N$12)) -> 0
A16: Increase / (decrease) in payables and accrued liabilities | B16: =-('Trial Balance'!D$13+'Trial Balance'!D$14+'Trial Balance'!D$15+'Trial Balance'!D$16) -> 0 | C16: =-(('Trial Balance'!E$13-'Trial Balance'!D$13)+('Trial Balance'!E$14-'Trial Balance'!D$14)+('Trial Balance'!E$15-'Trial Balance'!D$15)+('Trial Balance'!E$16-'Trial Balance'!D$16)) -> 0 | D16: =-(('Trial Balance'!F$13-'Trial Balance'!E$13)+('Trial Balance'!F$14-'Trial Balance'!E$14)+('Trial Balance'!F$15-'Trial Balance'!E$15)+('Trial Balance'!F$16-'Trial Balance'!E$16)) -> 0 | E16: =-(('Trial Balance'!G$13-'Trial Balance'!F$13)+('Trial Balance'!G$14-'Trial Balance'!F$14)+('Trial Balance'!G$15-'Trial Balance'!F$15)+('Trial Balance'!G$16-'Trial Balance'!F$16)) -> 0 | F16: =-(('Trial Balance'!H$13-'Trial Balance'!G$13)+('Trial Balance'!H$14-'Trial Balance'!G$14)+('Trial Balance'!H$15-'Trial Balance'!G$15)+('Trial Balance'!H$16-'Trial Balance'!G$16)) -> 0 | G16: =-(('Trial Balance'!I$13-'Trial Balance'!H$13)+('Trial Balance'!I$14-'Trial Balance'!H$14)+('Trial Balance'!I$15-'Trial Balance'!H$15)+('Trial Balance'!I$16-'Trial Balance'!H$16)) -> 0 | H16: =-(('Trial Balance'!J$13-'Trial Balance'!I$13)+('Trial Balance'!J$14-'Trial Balance'!I$14)+('Trial Balance'!J$15-'Trial Balance'!I$15)+('Trial Balance'!J$16-'Trial Balance'!I$16)) -> 0 | I16: =-(('Trial Balance'!K$13-'Trial Balance'!J$13)+('Trial Balance'!K$14-'Trial Balance'!J$14)+('Trial Balance'!K$15-'Trial Balance'!J$15)+('Trial Balance'!K$16-'Trial Balance'!J$16)) -> 0 | J16: =-(('Trial Balance'!L$13-'Trial Balance'!K$13)+('Trial Balance'!L$14-'Trial Balance'!K$14)+('Trial Balance'!L$15-'Trial Balance'!K$15)+('Trial Balance'!L$16-'Trial Balance'!K$16)) -> 0 | ... M16: =-(('Trial Balance'!O$13-'Trial Balance'!N$13)+('Trial Balance'!O$14-'Trial Balance'!N$14)+('Trial Balance'!O$15-'Trial Balance'!N$15)+('Trial Balance'!O$16-'Trial Balance'!N$16)) -> 0
A17: Net cash provided by / (used in) operating activities | B17: =SUM(B6:B16) -> -46308000 | C17: =SUM(C6:C16) -> -60118000 | D17: =SUM(D6:D16) -> -53118000 | E17: =SUM(E6:E16) -> -31068000 | F17: =SUM(F6:F16) -> -14068000 | G17: =SUM(G6:G16) -> 112782000 | H17: =SUM(H6:H16) -> 24756000 | I17: =SUM(I6:I16) -> -2654000 | ... M17: =SUM(M6:M16) -> -267000
A19: CASH FLOWS FROM FINANCING ACTIVITIES
A20: Capital contributions | B20: =-('Trial Balance'!D$17) -> 47500000 | C20: =-(('Trial Balance'!E$17-'Trial Balance'!D$17)) -> 60100000 | D20: =-(('Trial Balance'!F$17-'Trial Balance'!E$17)) -> 54900000 | E20: =-(('Trial Balance'!G$17-'Trial Balance'!F$17)) -> 30800000 | F20: =-(('Trial Balance'!H$17-'Trial Balance'!G$17)) -> 13600000 | G20: =-(('Trial Balance'!I$17-'Trial Balance'!H$17)) -> 2800000 | H20: =-(('Trial Balance'!J$17-'Trial Balance'!I$17)) -> 1300000 | I20: =-(('Trial Balance'!K$17-'Trial Balance'!J$17)) -> 1200000 | J20: =-(('Trial Balance'!L$17-'Trial Balance'!K$17)) -> 1100000 | ... M20: =-(('Trial Balance'!O$17-'Trial Balance'!N$17)) -> 0
A21: Offering costs paid from capital | B21: =-('Trial Balance'!D$18) -> -900000 | C21: =-(('Trial Balance'!E$18-'Trial Balance'!D$18)) -> 0 | D21: =-(('Trial Balance'!F$18-'Trial Balance'!E$18)) -> 0 | E21: =-(('Trial Balance'!G$18-'Trial Balance'!F$18)) -> 0 | F21: =-(('Trial Balance'!H$18-'Trial Balance'!G$18)) -> 0 | G21: =-(('Trial Balance'!I$18-'Trial Balance'!H$18)) -> 0 | H21: =-(('Trial Balance'!J$18-'Trial Balance'!I$18)) -> 0 | I21: =-(('Trial Balance'!K$18-'Trial Balance'!J$18)) -> 0 | J21: =-(('Trial Balance'!L$18-'Trial Balance'!K$18)) -> 0 | ... M21: =-(('Trial Balance'!O$18-'Trial Balance'!N$18)) -> 0
A22: Capital distributions | B22: =-('Trial Balance'!D$19) -> 0 | C22: =-(('Trial Balance'!E$19-'Trial Balance'!D$19)) -> 0 | D22: =-(('Trial Balance'!F$19-'Trial Balance'!E$19)) -> 0 | E22: =-(('Trial Balance'!G$19-'Trial Balance'!F$19)) -> 0 | F22: =-(('Trial Balance'!H$19-'Trial Balance'!G$19)) -> 0 | G22: =-(('Trial Balance'!I$19-'Trial Balance'!H$19)) -> -115200000 | H22: =-(('Trial Balance'!J$19-'Trial Balance'!I$19)) -> -26000000 | I22: =-(('Trial Balance'!K$19-'Trial Balance'!J$19)) -> 0 | J22: =-(('Trial Balance'!L$19-'Trial Balance'!K$19)) -> -89200000 | ... M22: =-(('Trial Balance'!O$19-'Trial Balance'!N$19)) -> -2467277.7
A23: Net cash provided by / (used in) financing activities | B23: =B20+B21+B22 -> 46600000 | C23: =C20+C21+C22 -> 60100000 | D23: =D20+D21+D22 -> 54900000 | E23: =E20+E21+E22 -> 30800000 | F23: =F20+F21+F22 -> 13600000 | G23: =G20+G21+G22 -> -112400000 | H23: =H20+H21+H22 -> -24700000 | I23: =I20+I21+I22 -> 1200000 | ... M23: =M20+M21+M22 -> -2467277.7
A25: Net increase / (decrease) in cash | B25: =B17+B23 -> 292000 | C25: =C17+C23 -> -18000 | D25: =D17+D23 -> 1782000 | E25: =E17+E23 -> -268000 | F25: =F17+F23 -> -468000 | G25: =G17+G23 -> 382000 | H25: =H17+H23 -> 56000 | I25: =I17+I23 -> -1454000 | ... M25: =M17+M23 -> -2734277.7
A26: Cash, beginning of year | B26: 0 | C26: ='Trial Balance'!D$5 -> 292000 | D26: ='Trial Balance'!E$5 -> 274000 | E26: ='Trial Balance'!F$5 -> 2056000 | F26: ='Trial Balance'!G$5 -> 1788000 | G26: ='Trial Balance'!H$5 -> 1320000 | H26: ='Trial Balance'!I$5 -> 1702000 | I26: ='Trial Balance'!J$5 -> 1758000 | J26: ='Trial Balance'!K$5 -> 304000 | ... M26: ='Trial Balance'!N$5 -> 2734277.7
A27: Cash, end of year | B27: =B25+B26 -> 292000 | C27: =C25+C26 -> 274000 | D27: =D25+D26 -> 2056000 | E27: =E25+E26 -> 1788000 | F27: =F25+F26 -> 1320000 | G27: =G25+G26 -> 1702000 | H27: =H25+H26 -> 1758000 | I27: =I25+I26 -> 304000 | ... M27: =M25+M26 -> 1.4901161e-08
A28: Cash per Trial Balance - difference must be zero | B28: =B27-'Trial Balance'!D$5 -> 0 | C28: =C27-'Trial Balance'!E$5 -> 0 | D28: =D27-'Trial Balance'!F$5 -> 0 | E28: =E27-'Trial Balance'!G$5 -> 0 | F28: =F27-'Trial Balance'!H$5 -> 0 | G28: =G27-'Trial Balance'!I$5 -> 0 | H28: =H27-'Trial Balance'!J$5 -> 0 | I28: =I27-'Trial Balance'!K$5 -> 0 | ... M28: =M27-'Trial Balance'!O$5 -> 1.2107193e-08
A30: SUPPLEMENTAL DISCLOSURE OF NON-CASH INVESTING ACTIVITY
A31: Bridge note converted to equity - reclassification only, no cash, no gain or loss | B31: =SUMIFS('Journal Entries'!$G$5:$G$785,'Journal Entries'!$D$5:$D$785,"1100",'Journal Entries'!$C$5:$C$785,"2019*",'Journal Entries'!$F$5:$F$785,"3.1 bridge conversion") -> 0 | C31: =SUMIFS('Journal Entries'!$G$5:$G$785,'Journal Entries'!$D$5:$D$785,"1100",'Journal Entries'!$C$5:$C$785,"2020*",'Journal Entries'!$F$5:$F$785,"3.1 bridge conversion") -> 0 | D31: =SUMIFS('Journal Entries'!$G$5:$G$785,'Journal Entries'!$D$5:$D$785,"1100",'Journal Entries'!$C$5:$C$785,"2021*",'Journal Entries'!$F$5:$F$785,"3.1 bridge conversion") -> 1250000 | E31: =SUMIFS('Journal Entries'!$G$5:$G$785,'Journal Entries'!$D$5:$D$785,"1100",'Journal Entries'!$C$5:$C$785,"2022*",'Journal Entries'!$F$5:$F$785,"3.1 bridge conversion") -> 0 | F31: =SUMIFS('Journal Entries'!$G$5:$G$785,'Journal Entries'!$D$5:$D$785,"1100",'Journal Entries'!$C$5:$C$785,"2023*",'Journal Entries'!$F$5:$F$785,"3.1 bridge conversion") -> 0 | G31: =SUMIFS('Journal Entries'!$G$5:$G$785,'Journal Entries'!$D$5:$D$785,"1100",'Journal Entries'!$C$5:$C$785,"2024*",'Journal Entries'!$F$5:$F$785,"3.1 bridge conversion") -> 0 | H31: =SUMIFS('Journal Entries'!$G$5:$G$785,'Journal Entries'!$D$5:$D$785,"1100",'Journal Entries'!$C$5:$C$785,"2025*",'Journal Entries'!$F$5:$F$785,"3.1 bridge conversion") -> 0 | I31: =SUMIFS('Journal Entries'!$G$5:$G$785,'Journal Entries'!$D$5:$D$785,"1100",'Journal Entries'!$C$5:$C$785,"2026*",'Journal Entries'!$F$5:$F$785,"3.1 bridge conversion") -> 0 | J31: =SUMIFS('Journal Entries'!$G$5:$G$785,'Journal Entries'!$D$5:$D$785,"1100",'Journal Entries'!$C$5:$C$785,"2027*",'Journal Entries'!$F$5:$F$785,"3.1 bridge conversion") -> 0 | K31: =SUMIFS('Journal Entries'!$G$5:$G$785,'Journal Entries'!$D$5:$D$785,"1100",'Journal Entries'!$C$5:$C$785,"2028*",'Journal Entries'!$F$5:$F$785,"3.1 bridge conversion") -> 0 | L31: =SUMIFS('Journal Entries'!$G$5:$G$785,'Journal Entries'!$D$5:$D$785,"1100",'Journal Entries'!$C$5:$C$785,"2029*",'Journal Entries'!$F$5:$F$785,"3.1 bridge conversion") -> 0 | M31: =SUMIFS('Journal Entries'!$G$5:$G$785,'Journal Entries'!$D$5:$D$785,"1100",'Journal Entries'!$C$5:$C$785,"2030*",'Journal Entries'!$F$5:$F$785,"3.1 bridge conversion") -> 0

Sheet Financial Highlights
A1: Financial Highlights
A2: Required supplementary information under ASC 946-205-50, presented for the limited partner class. Ratios are to average LP net assets. The general partner and the carried interest vehicle are excluded: they are not a class of limited partner interest and their inclusion distorts every ratio.
A4: (US dollars / ratios) | B4: FY2019 | C4: FY2020 | D4: FY2021 | E4: FY2022 | F4: FY2023 | G4: FY2024 | H4: FY2025 | I4: FY2026 | J4: FY2027 | K4: FY2028 | L4: FY2029 | M4: FY2030
A5: LP net assets, beginning of year | B5: 0 | C5: =B6 -> 42537792 | D5: =C6 -> 1.040497e+08 | E5: =D6 -> 1.7756841e+08 | F5: =E6 -> 2.0462463e+08 | G5: =F6 -> 2.4515765e+08 | H5: =G6 -> 1.6579202e+08 | I5: =H6 -> 1.5309e+08 | J5: =I6 -> 1.6644963e+08 | ... M5: =L6 -> 2144258.3
A6: LP net assets, end of year | B6: =(SUMIFS(Allocations!$E$5:$E$1700,Allocations!$B$5:$B$1700,"<="&3,Allocations!$F$5:$F$1700,"LP")-2*SUMIFS(Allocations!$E$5:$E$1700,Allocations!$B$5:$B$1700,"<="&3,Allocations!$F$5:$F$1700,"LP",Allocations!$D$5:$D$1700,"Distributions")) -> 42537792 | C6: =(SUMIFS(Allocations!$E$5:$E$1700,Allocations!$B$5:$B$1700,"<="&7,Allocations!$F$5:$F$1700,"LP")-2*SUMIFS(Allocations!$E$5:$E$1700,Allocations!$B$5:$B$1700,"<="&7,Allocations!$F$5:$F$1700,"LP",Allocations!$D$5:$D$1700,"Distributions")) -> 1.040497e+08 | D6: =(SUMIFS(Allocations!$E$5:$E$1700,Allocations!$B$5:$B$1700,"<="&11,Allocations!$F$5:$F$1700,"LP")-2*SUMIFS(Allocations!$E$5:$E$1700,Allocations!$B$5:$B$1700,"<="&11,Allocations!$F$5:$F$1700,"LP",Allocations!$D$5:$D$1700,"Distributions")) -> 1.7756841e+08 | E6: =(SUMIFS(Allocations!$E$5:$E$1700,Allocations!$B$5:$B$1700,"<="&15,Allocations!$F$5:$F$1700,"LP")-2*SUMIFS(Allocations!$E$5:$E$1700,Allocations!$B$5:$B$1700,"<="&15,Allocations!$F$5:$F$1700,"LP",Allocations!$D$5:$D$1700,"Distributions")) -> 2.0462463e+08 | F6: =(SUMIFS(Allocations!$E$5:$E$1700,Allocations!$B$5:$B$1700,"<="&19,Allocations!$F$5:$F$1700,"LP")-2*SUMIFS(Allocations!$E$5:$E$1700,Allocations!$B$5:$B$1700,"<="&19,Allocations!$F$5:$F$1700,"LP",Allocations!$D$5:$D$1700,"Distributions")) -> 2.4515765e+08 | G6: =(SUMIFS(Allocations!$E$5:$E$1700,Allocations!$B$5:$B$1700,"<="&23,Allocations!$F$5:$F$1700,"LP")-2*SUMIFS(Allocations!$E$5:$E$1700,Allocations!$B$5:$B$1700,"<="&23,Allocations!$F$5:$F$1700,"LP",Allocations!$D$5:$D$1700,"Distributions")) -> 1.6579202e+08 | H6: =(SUMIFS(Allocations!$E$5:$E$1700,Allocations!$B$5:$B$1700,"<="&27,Allocations!$F$5:$F$1700,"LP")-2*SUMIFS(Allocations!$E$5:$E$1700,Allocations!$B$5:$B$1700,"<="&27,Allocations!$F$5:$F$1700,"LP",Allocations!$D$5:$D$1700,"Distributions")) -> 1.5309e+08 | I6: =(SUMIFS(Allocations!$E$5:$E$1700,Allocations!$B$5:$B$1700,"<="&31,Allocations!$F$5:$F$1700,"LP")-2*SUMIFS(Allocations!$E$5:$E$1700,Allocations!$B$5:$B$1700,"<="&31,Allocations!$F$5:$F$1700,"LP",Allocations!$D$5:$D$1700,"Distributions")) -> 1.6644963e+08 | J6: =(SUMIFS(Allocations!$E$5:$E$1700,Allocations!$B$5:$B$1700,"<="&35,Allocations!$F$5:$F$1700,"LP")-2*SUMIFS(Allocations!$E$5:$E$1700,Allocations!$B$5:$B$1700,"<="&35,Allocations!$F$5:$F$1700,"LP",Allocations!$D$5:$D$1700,"Distributions")) -> 1.1468449e+08 | K6: =(SUMIFS(Allocations!$E$5:$E$1700,Allocations!$B$5:$B$1700,"<="&39,Allocations!$F$5:$F$1700,"LP")-2*SUMIFS(Allocations!$E$5:$E$1700,Allocations!$B$5:$B$1700,"<="&39,Allocations!$F$5:$F$1700,"LP",Allocations!$D$5:$D$1700,"Distributions")) -> 38445539 | L6: =(SUMIFS(Allocations!$E$5:$E$1700,Allocations!$B$5:$B$1700,"<="&43,Allocations!$F$5:$F$1700,"LP")-2*SUMIFS(Allocations!$E$5:$E$1700,Allocations!$B$5:$B$1700,"<="&43,Allocations!$F$5:$F$1700,"LP",Allocations!$D$5:$D$1700,"Distributions")) -> 2144258.3 | M6: =(SUMIFS(Allocations!$E$5:$E$1700,Allocations!$B$5:$B$1700,"<="&45,Allocations!$F$5:$F$1700,"LP")-2*SUMIFS(Allocations!$E$5:$E$1700,Allocations!$B$5:$B$1700,"<="&45,Allocations!$F$5:$F$1700,"LP",Allocations!$D$5:$D$1700,"Distributions")) -> 8.3446503e-07
A7: Average LP net assets | B7: =(B5+B6)/2 -> 21268896 | C7: =(C5+C6)/2 -> 73293746 | D7: =(D5+D6)/2 -> 1.4080905e+08 | E7: =(E5+E6)/2 -> 1.9109652e+08 | F7: =(F5+F6)/2 -> 2.2489114e+08 | G7: =(G5+G6)/2 -> 2.0547484e+08 | H7: =(H5+H6)/2 -> 1.5944101e+08 | I7: =(I5+I6)/2 -> 1.5976981e+08 | ... M7: =(M5+M6)/2 -> 1072129.2
A9: RATIOS TO AVERAGE LP NET ASSETS
A10: Total expenses, excluding carried interest | B10: =IF(B7=0,0,-(SUMIFS(Allocations!$E$5:$E$1700,Allocations!$B$5:$B$1700,">-1",Allocations!$B$5:$B$1700,"<=3",Allocations!$F$5:$F$1700,"LP",Allocations!$D$5:$D$1700,"Management fee")+SUMIFS(Allocations!$E$5:$E$1700,Allocations!$B$5:$B$1700,">-1",Allocations!$B$5:$B$1700,"<=3",Allocations!$F$5:$F$1700,"LP",Allocations!$D$5:$D$1700,"Other fund expenses"))/B7) -> 0.19928619 | C10: =IF(C7=0,0,-(SUMIFS(Allocations!$E$5:$E$1700,Allocations!$B$5:$B$1700,">3",Allocations!$B$5:$B$1700,"<=7",Allocations!$F$5:$F$1700,"LP",Allocations!$D$5:$D$1700,"Management fee")+SUMIFS(Allocations!$E$5:$E$1700,Allocations!$B$5:$B$1700,">3",Allocations!$B$5:$B$1700,"<=7",Allocations!$F$5:$F$1700,"LP",Allocations!$D$5:$D$1700,"Other fund expenses"))/C7) -> 0.069658543 | D10: =IF(D7=0,0,-(SUMIFS(Allocations!$E$5:$E$1700,Allocations!$B$5:$B$1700,">7",Allocations!$B$5:$B$1700,"<=11",Allocations!$F$5:$F$1700,"LP",Allocations!$D$5:$D$1700,"Management fee")+SUMIFS(Allocations!$E$5:$E$1700,Allocations!$B$5:$B$1700,">7",Allocations!$B$5:$B$1700,"<=11",Allocations!$F$5:$F$1700,"LP",Allocations!$D$5:$D$1700,"Other fund expenses"))/D7) -> 0.036266418 | E10: =IF(E7=0,0,-(SUMIFS(Allocations!$E$5:$E$1700,Allocations!$B$5:$B$1700,">11",Allocations!$B$5:$B$1700,"<=15",Allocations!$F$5:$F$1700,"LP",Allocations!$D$5:$D$1700,"Management fee")+SUMIFS(Allocations!$E$5:$E$1700,Allocations!$B$5:$B$1700,">11",Allocations!$B$5:$B$1700,"<=15",Allocations!$F$5:$F$1700,"LP",Allocations!$D$5:$D$1700,"Other fund expenses"))/E7) -> 0.026461183 | F10: =IF(F7=0,0,-(SUMIFS(Allocations!$E$5:$E$1700,Allocations!$B$5:$B$1700,">15",Allocations!$B$5:$B$1700,"<=19",Allocations!$F$5:$F$1700,"LP",Allocations!$D$5:$D$1700,"Management fee")+SUMIFS(Allocations!$E$5:$E$1700,Allocations!$B$5:$B$1700,">15",Allocations!$B$5:$B$1700,"<=19",Allocations!$F$5:$F$1700,"LP",Allocations!$D$5:$D$1700,"Other fund expenses"))/F7) -> 0.022484834 | G10: =IF(G7=0,0,-(SUMIFS(Allocations!$E$5:$E$1700,Allocations!$B$5:$B$1700,">19",Allocations!$B$5:$B$1700,"<=23",Allocations!$F$5:$F$1700,"LP",Allocations!$D$5:$D$1700,"Management fee")+SUMIFS(Allocations!$E$5:$E$1700,Allocations!$B$5:$B$1700,">19",Allocations!$B$5:$B$1700,"<=23",Allocations!$F$5:$F$1700,"LP",Allocations!$D$5:$D$1700,"Other fund expenses"))/G7) -> 0.02533955 | H10: =IF(H7=0,0,-(SUMIFS(Allocations!$E$5:$E$1700,Allocations!$B$5:$B$1700,">23",Allocations!$B$5:$B$1700,"<=27",Allocations!$F$5:$F$1700,"LP",Allocations!$D$5:$D$1700,"Management fee")+SUMIFS(Allocations!$E$5:$E$1700,Allocations!$B$5:$B$1700,">23",Allocations!$B$5:$B$1700,"<=27",Allocations!$F$5:$F$1700,"LP",Allocations!$D$5:$D$1700,"Other fund expenses"))/H7) -> 0.025296628 | I10: =IF(I7=0,0,-(SUMIFS(Allocations!$E$5:$E$1700,Allocations!$B$5:$B$1700,">27",Allocations!$B$5:$B$1700,"<=31",Allocations!$F$5:$F$1700,"LP",Allocations!$D$5:$D$1700,"Management fee")+SUMIFS(Allocations!$E$5:$E$1700,Allocations!$B$5:$B$1700,">27",Allocations!$B$5:$B$1700,"<=31",Allocations!$F$5:$F$1700,"LP",Allocations!$D$5:$D$1700,"Other fund expenses"))/I7) -> 0.016544552 | J10: =IF(J7=0,0,-(SUMIFS(Allocations!$E$5:$E$1700,Allocations!$B$5:$B$1700,">31",Allocations!$B$5:$B$1700,"<=35",Allocations!$F$5:$F$1700,"LP",Allocations!$D$5:$D$1700,"Management fee")+SUMIFS(Allocations!$E$5:$E$1700,Allocations!$B$5:$B$1700,">31",Allocations!$B$5:$B$1700,"<=35",Allocations!$F$5:$F$1700,"LP",Allocations!$D$5:$D$1700,"Other fund expenses"))/J7) -> 0.015069818 | K10: =IF(K7=0,0,-(SUMIFS(Allocations!$E$5:$E$1700,Allocations!$B$5:$B$1700,">35",Allocations!$B$5:$B$1700,"<=39",Allocations!$F$5:$F$1700,"LP",Allocations!$D$5:$D$1700,"Management fee")+SUMIFS(Allocations!$E$5:$E$1700,Allocations!$B$5:$B$1700,">35",Allocations!$B$5:$B$1700,"<=39",Allocations!$F$5:$F$1700,"LP",Allocations!$D$5:$D$1700,"Other fund expenses"))/K7) -> 0.018263171 | L10: =IF(L7=0,0,-(SUMIFS(Allocations!$E$5:$E$1700,Allocations!$B$5:$B$1700,">39",Allocations!$B$5:$B$1700,"<=43",Allocations!$F$5:$F$1700,"LP",Allocations!$D$5:$D$1700,"Management fee")+SUMIFS(Allocations!$E$5:$E$1700,Allocations!$B$5:$B$1700,">39",Allocations!$B$5:$B$1700,"<=43",Allocations!$F$5:$F$1700,"LP",Allocations!$D$5:$D$1700,"Other fund expenses"))/L7) -> 0.030220402 | M10: =IF(M7=0,0,-(SUMIFS(Allocations!$E$5:$E$1700,Allocations!$B$5:$B$1700,">43",Allocations!$B$5:$B$1700,"<=45",Allocations!$F$5:$F$1700,"LP",Allocations!$D$5:$D$1700,"Management fee")+SUMIFS(Allocations!$E$5:$E$1700,Allocations!$B$5:$B$1700,">43",Allocations!$B$5:$B$1700,"<=45",Allocations!$F$5:$F$1700,"LP",Allocations!$D$5:$D$1700,"Other fund expenses"))/M7) -> 0.24405641
A11: Carried interest (assumed-liquidation accrual) | B11: =IF(B7=0,0,-(SUMIFS(Allocations!$E$5:$E$1700,Allocations!$B$5:$B$1700,">-1",Allocations!$B$5:$B$1700,"<=3",Allocations!$F$5:$F$1700,"LP",Allocations!$D$5:$D$1700,"Carried interest"))/B7) -> 0 | C11: =IF(C7=0,0,-(SUMIFS(Allocations!$E$5:$E$1700,Allocations!$B$5:$B$1700,">3",Allocations!$B$5:$B$1700,"<=7",Allocations!$F$5:$F$1700,"LP",Allocations!$D$5:$D$1700,"Carried interest"))/C7) -> 0 | D11: =IF(D7=0,0,-(SUMIFS(Allocations!$E$5:$E$1700,Allocations!$B$5:$B$1700,">7",Allocations!$B$5:$B$1700,"<=11",Allocations!$F$5:$F$1700,"LP",Allocations!$D$5:$D$1700,"Carried interest"))/D7) -> 0.032502546 | E11: =IF(E7=0,0,-(SUMIFS(Allocations!$E$5:$E$1700,Allocations!$B$5:$B$1700,">11",Allocations!$B$5:$B$1700,"<=15",Allocations!$F$5:$F$1700,"LP",Allocations!$D$5:$D$1700,"Carried interest"))/E7) -> -0.02394943 | F11: =IF(F7=0,0,-(SUMIFS(Allocations!$E$5:$E$1700,Allocations!$B$5:$B$1700,">15",Allocations!$B$5:$B$1700,"<=19",Allocations!$F$5:$F$1700,"LP",Allocations!$D$5:$D$1700,"Carried interest"))/F7) -> 0 | G11: =IF(G7=0,0,-(SUMIFS(Allocations!$E$5:$E$1700,Allocations!$B$5:$B$1700,">19",Allocations!$B$5:$B$1700,"<=23",Allocations!$F$5:$F$1700,"LP",Allocations!$D$5:$D$1700,"Carried interest"))/G7) -> 0.088801067 | H11: =IF(H7=0,0,-(SUMIFS(Allocations!$E$5:$E$1700,Allocations!$B$5:$B$1700,">23",Allocations!$B$5:$B$1700,"<=27",Allocations!$F$5:$F$1700,"LP",Allocations!$D$5:$D$1700,"Carried interest"))/H7) -> 0.017968106 | I11: =IF(I7=0,0,-(SUMIFS(Allocations!$E$5:$E$1700,Allocations!$B$5:$B$1700,">27",Allocations!$B$5:$B$1700,"<=31",Allocations!$F$5:$F$1700,"LP",Allocations!$D$5:$D$1700,"Carried interest"))/I7) -> 0.019063935 | J11: =IF(J7=0,0,-(SUMIFS(Allocations!$E$5:$E$1700,Allocations!$B$5:$B$1700,">31",Allocations!$B$5:$B$1700,"<=35",Allocations!$F$5:$F$1700,"LP",Allocations!$D$5:$D$1700,"Carried interest"))/J7) -> 0.061238011 | K11: =IF(K7=0,0,-(SUMIFS(Allocations!$E$5:$E$1700,Allocations!$B$5:$B$1700,">35",Allocations!$B$5:$B$1700,"<=39",Allocations!$F$5:$F$1700,"LP",Allocations!$D$5:$D$1700,"Carried interest"))/K7) -> 0.041344622 | L11: =IF(L7=0,0,-(SUMIFS(Allocations!$E$5:$E$1700,Allocations!$B$5:$B$1700,">39",Allocations!$B$5:$B$1700,"<=43",Allocations!$F$5:$F$1700,"LP",Allocations!$D$5:$D$1700,"Carried interest"))/L7) -> 0.14853817 | M11: =IF(M7=0,0,-(SUMIFS(Allocations!$E$5:$E$1700,Allocations!$B$5:$B$1700,">43",Allocations!$B$5:$B$1700,"<=45",Allocations!$F$5:$F$1700,"LP",Allocations!$D$5:$D$1700,"Carried interest"))/M7) -> -0.048910795
A12: Total expenses, including carried interest | B12: =IF(B7=0,0,(-(SUMIFS(Allocations!$E$5:$E$1700,Allocations!$B$5:$B$1700,">-1",Allocations!$B$5:$B$1700,"<=3",Allocations!$F$5:$F$1700,"LP",Allocations!$D$5:$D$1700,"Management fee")+SUMIFS(Allocations!$E$5:$E$1700,Allocations!$B$5:$B$1700,">-1",Allocations!$B$5:$B$1700,"<=3",Allocations!$F$5:$F$1700,"LP",Allocations!$D$5:$D$1700,"Other fund expenses"))+-(SUMIFS(Allocations!$E$5:$E$1700,Allocations!$B$5:$B$1700,">-1",Allocations!$B$5:$B$1700,"<=3",Allocations!$F$5:$F$1700,"LP",Allocations!$D$5:$D$1700,"Carried interest")))/B7) -> 0.19928619 | C12: =IF(C7=0,0,(-(SUMIFS(Allocations!$E$5:$E$1700,Allocations!$B$5:$B$1700,">3",Allocations!$B$5:$B$1700,"<=7",Allocations!$F$5:$F$1700,"LP",Allocations!$D$5:$D$1700,"Management fee")+SUMIFS(Allocations!$E$5:$E$1700,Allocations!$B$5:$B$1700,">3",Allocations!$B$5:$B$1700,"<=7",Allocations!$F$5:$F$1700,"LP",Allocations!$D$5:$D$1700,"Other fund expenses"))+-(SUMIFS(Allocations!$E$5:$E$1700,Allocations!$B$5:$B$1700,">3",Allocations!$B$5:$B$1700,"<=7",Allocations!$F$5:$F$1700,"LP",Allocations!$D$5:$D$1700,"Carried interest")))/C7) -> 0.069658543 | D12: =IF(D7=0,0,(-(SUMIFS(Allocations!$E$5:$E$1700,Allocations!$B$5:$B$1700,">7",Allocations!$B$5:$B$1700,"<=11",Allocations!$F$5:$F$1700,"LP",Allocations!$D$5:$D$1700,"Management fee")+SUMIFS(Allocations!$E$5:$E$1700,Allocations!$B$5:$B$1700,">7",Allocations!$B$5:$B$1700,"<=11",Allocations!$F$5:$F$1700,"LP",Allocations!$D$5:$D$1700,"Other fund expenses"))+-(SUMIFS(Allocations!$E$5:$E$1700,Allocations!$B$5:$B$1700,">7",Allocations!$B$5:$B$1700,"<=11",Allocations!$F$5:$F$1700,"LP",Allocations!$D$5:$D$1700,"Carried interest")))/D7) -> 0.068768964 | E12: =IF(E7=0,0,(-(SUMIFS(Allocations!$E$5:$E$1700,Allocations!$B$5:$B$1700,">11",Allocations!$B$5:$B$1700,"<=15",Allocations!$F$5:$F$1700,"LP",Allocations!$D$5:$D$1700,"Management fee")+SUMIFS(Allocations!$E$5:$E$1700,Allocations!$B$5:$B$1700,">11",Allocations!$B$5:$B$1700,"<=15",Allocations!$F$5:$F$1700,"LP",Allocations!$D$5:$D$1700,"Other fund expenses"))+-(SUMIFS(Allocations!$E$5:$E$1700,Allocations!$B$5:$B$1700,">11",Allocations!$B$5:$B$1700,"<=15",Allocations!$F$5:$F$1700,"LP",Allocations!$D$5:$D$1700,"Carried interest")))/E7) -> 0.002511753 | F12: =IF(F7=0,0,(-(SUMIFS(Allocations!$E$5:$E$1700,Allocations!$B$5:$B$1700,">15",Allocations!$B$5:$B$1700,"<=19",Allocations!$F$5:$F$1700,"LP",Allocations!$D$5:$D$1700,"Management fee")+SUMIFS(Allocations!$E$5:$E$1700,Allocations!$B$5:$B$1700,">15",Allocations!$B$5:$B$1700,"<=19",Allocations!$F$5:$F$1700,"LP",Allocations!$D$5:$D$1700,"Other fund expenses"))+-(SUMIFS(Allocations!$E$5:$E$1700,Allocations!$B$5:$B$1700,">15",Allocations!$B$5:$B$1700,"<=19",Allocations!$F$5:$F$1700,"LP",Allocations!$D$5:$D$1700,"Carried interest")))/F7) -> 0.022484834 | G12: =IF(G7=0,0,(-(SUMIFS(Allocations!$E$5:$E$1700,Allocations!$B$5:$B$1700,">19",Allocations!$B$5:$B$1700,"<=23",Allocations!$F$5:$F$1700,"LP",Allocations!$D$5:$D$1700,"Management fee")+SUMIFS(Allocations!$E$5:$E$1700,Allocations!$B$5:$B$1700,">19",Allocations!$B$5:$B$1700,"<=23",Allocations!$F$5:$F$1700,"LP",Allocations!$D$5:$D$1700,"Other fund expenses"))+-(SUMIFS(Allocations!$E$5:$E$1700,Allocations!$B$5:$B$1700,">19",Allocations!$B$5:$B$1700,"<=23",Allocations!$F$5:$F$1700,"LP",Allocations!$D$5:$D$1700,"Carried interest")))/G7) -> 0.11414062 | H12: =IF(H7=0,0,(-(SUMIFS(Allocations!$E$5:$E$1700,Allocations!$B$5:$B$1700,">23",Allocations!$B$5:$B$1700,"<=27",Allocations!$F$5:$F$1700,"LP",Allocations!$D$5:$D$1700,"Management fee")+SUMIFS(Allocations!$E$5:$E$1700,Allocations!$B$5:$B$1700,">23",Allocations!$B$5:$B$1700,"<=27",Allocations!$F$5:$F$1700,"LP",Allocations!$D$5:$D$1700,"Other fund expenses"))+-(SUMIFS(Allocations!$E$5:$E$1700,Allocations!$B$5:$B$1700,">23",Allocations!$B$5:$B$1700,"<=27",Allocations!$F$5:$F$1700,"LP",Allocations!$D$5:$D$1700,"Carried interest")))/H7) -> 0.043264734 | I12: =IF(I7=0,0,(-(SUMIFS(Allocations!$E$5:$E$1700,Allocations!$B$5:$B$1700,">27",Allocations!$B$5:$B$1700,"<=31",Allocations!$F$5:$F$1700,"LP",Allocations!$D$5:$D$1700,"Management fee")+SUMIFS(Allocations!$E$5:$E$1700,Allocations!$B$5:$B$1700,">27",Allocations!$B$5:$B$1700,"<=31",Allocations!$F$5:$F$1700,"LP",Allocations!$D$5:$D$1700,"Other fund expenses"))+-(SUMIFS(Allocations!$E$5:$E$1700,Allocations!$B$5:$B$1700,">27",Allocations!$B$5:$B$1700,"<=31",Allocations!$F$5:$F$1700,"LP",Allocations!$D$5:$D$1700,"Carried interest")))/I7) -> 0.035608487 | J12: =IF(J7=0,0,(-(SUMIFS(Allocations!$E$5:$E$1700,Allocations!$B$5:$B$1700,">31",Allocations!$B$5:$B$1700,"<=35",Allocations!$F$5:$F$1700,"LP",Allocations!$D$5:$D$1700,"Management fee")+SUMIFS(Allocations!$E$5:$E$1700,Allocations!$B$5:$B$1700,">31",Allocations!$B$5:$B$1700,"<=35",Allocations!$F$5:$F$1700,"LP",Allocations!$D$5:$D$1700,"Other fund expenses"))+-(SUMIFS(Allocations!$E$5:$E$1700,Allocations!$B$5:$B$1700,">31",Allocations!$B$5:$B$1700,"<=35",Allocations!$F$5:$F$1700,"LP",Allocations!$D$5:$D$1700,"Carried interest")))/J7) -> 0.076307829 | K12: =IF(K7=0,0,(-(SUMIFS(Allocations!$E$5:$E$1700,Allocations!$B$5:$B$1700,">35",Allocations!$B$5:$B$1700,"<=39",Allocations!$F$5:$F$1700,"LP",Allocations!$D$5:$D$1700,"Management fee")+SUMIFS(Allocations!$E$5:$E$1700,Allocations!$B$5:$B$1700,">35",Allocations!$B$5:$B$1700,"<=39",Allocations!$F$5:$F$1700,"LP",Allocations!$D$5:$D$1700,"Other fund expenses"))+-(SUMIFS(Allocations!$E$5:$E$1700,Allocations!$B$5:$B$1700,">35",Allocations!$B$5:$B$1700,"<=39",Allocations!$F$5:$F$1700,"LP",Allocations!$D$5:$D$1700,"Carried interest")))/K7) -> 0.059607793 | L12: =IF(L7=0,0,(-(SUMIFS(Allocations!$E$5:$E$1700,Allocations!$B$5:$B$1700,">39",Allocations!$B$5:$B$1700,"<=43",Allocations!$F$5:$F$1700,"LP",Allocations!$D$5:$D$1700,"Management fee")+SUMIFS(Allocations!$E$5:$E$1700,Allocations!$B$5:$B$1700,">39",Allocations!$B$5:$B$1700,"<=43",Allocations!$F$5:$F$1700,"LP",Allocations!$D$5:$D$1700,"Other fund expenses"))+-(SUMIFS(Allocations!$E$5:$E$1700,Allocations!$B$5:$B$1700,">39",Allocations!$B$5:$B$1700,"<=43",Allocations!$F$5:$F$1700,"LP",Allocations!$D$5:$D$1700,"Carried interest")))/L7) -> 0.17875857 | M12: =IF(M7=0,0,(-(SUMIFS(Allocations!$E$5:$E$1700,Allocations!$B$5:$B$1700,">43",Allocations!$B$5:$B$1700,"<=45",Allocations!$F$5:$F$1700,"LP",Allocations!$D$5:$D$1700,"Management fee")+SUMIFS(Allocations!$E$5:$E$1700,Allocations!$B$5:$B$1700,">43",Allocations!$B$5:$B$1700,"<=45",Allocations!$F$5:$F$1700,"LP",Allocations!$D$5:$D$1700,"Other fund expenses"))+-(SUMIFS(Allocations!$E$5:$E$1700,Allocations!$B$5:$B$1700,">43",Allocations!$B$5:$B$1700,"<=45",Allocations!$F$5:$F$1700,"LP",Allocations!$D$5:$D$1700,"Carried interest")))/M7) -> 0.19514562
A13: Net investment income / (loss) | B13: =IF(B7=0,0,(SUMIFS(Allocations!$E$5:$E$1700,Allocations!$B$5:$B$1700,">-1",Allocations!$B$5:$B$1700,"<=3",Allocations!$F$5:$F$1700,"LP",Allocations!$D$5:$D$1700,"Investment income")-(-(SUMIFS(Allocations!$E$5:$E$1700,Allocations!$B$5:$B$1700,">-1",Allocations!$B$5:$B$1700,"<=3",Allocations!$F$5:$F$1700,"LP",Allocations!$D$5:$D$1700,"Management fee")+SUMIFS(Allocations!$E$5:$E$1700,Allocations!$B$5:$B$1700,">-1",Allocations!$B$5:$B$1700,"<=3",Allocations!$F$5:$F$1700,"LP",Allocations!$D$5:$D$1700,"Other fund expenses"))))/B7) -> -0.19928619 | C13: =IF(C7=0,0,(SUMIFS(Allocations!$E$5:$E$1700,Allocations!$B$5:$B$1700,">3",Allocations!$B$5:$B$1700,"<=7",Allocations!$F$5:$F$1700,"LP",Allocations!$D$5:$D$1700,"Investment income")-(-(SUMIFS(Allocations!$E$5:$E$1700,Allocations!$B$5:$B$1700,">3",Allocations!$B$5:$B$1700,"<=7",Allocations!$F$5:$F$1700,"LP",Allocations!$D$5:$D$1700,"Management fee")+SUMIFS(Allocations!$E$5:$E$1700,Allocations!$B$5:$B$1700,">3",Allocations!$B$5:$B$1700,"<=7",Allocations!$F$5:$F$1700,"LP",Allocations!$D$5:$D$1700,"Other fund expenses"))))/C7) -> -0.069658543 | D13: =IF(D7=0,0,(SUMIFS(Allocations!$E$5:$E$1700,Allocations!$B$5:$B$1700,">7",Allocations!$B$5:$B$1700,"<=11",Allocations!$F$5:$F$1700,"LP",Allocations!$D$5:$D$1700,"Investment income")-(-(SUMIFS(Allocations!$E$5:$E$1700,Allocations!$B$5:$B$1700,">7",Allocations!$B$5:$B$1700,"<=11",Allocations!$F$5:$F$1700,"LP",Allocations!$D$5:$D$1700,"Management fee")+SUMIFS(Allocations!$E$5:$E$1700,Allocations!$B$5:$B$1700,">7",Allocations!$B$5:$B$1700,"<=11",Allocations!$F$5:$F$1700,"LP",Allocations!$D$5:$D$1700,"Other fund expenses"))))/D7) -> -0.036266418 | E13: =IF(E7=0,0,(SUMIFS(Allocations!$E$5:$E$1700,Allocations!$B$5:$B$1700,">11",Allocations!$B$5:$B$1700,"<=15",Allocations!$F$5:$F$1700,"LP",Allocations!$D$5:$D$1700,"Investment income")-(-(SUMIFS(Allocations!$E$5:$E$1700,Allocations!$B$5:$B$1700,">11",Allocations!$B$5:$B$1700,"<=15",Allocations!$F$5:$F$1700,"LP",Allocations!$D$5:$D$1700,"Management fee")+SUMIFS(Allocations!$E$5:$E$1700,Allocations!$B$5:$B$1700,">11",Allocations!$B$5:$B$1700,"<=15",Allocations!$F$5:$F$1700,"LP",Allocations!$D$5:$D$1700,"Other fund expenses"))))/E7) -> -0.019803739 | F13: =IF(F7=0,0,(SUMIFS(Allocations!$E$5:$E$1700,Allocations!$B$5:$B$1700,">15",Allocations!$B$5:$B$1700,"<=19",Allocations!$F$5:$F$1700,"LP",Allocations!$D$5:$D$1700,"Investment income")-(-(SUMIFS(Allocations!$E$5:$E$1700,Allocations!$B$5:$B$1700,">15",Allocations!$B$5:$B$1700,"<=19",Allocations!$F$5:$F$1700,"LP",Allocations!$D$5:$D$1700,"Management fee")+SUMIFS(Allocations!$E$5:$E$1700,Allocations!$B$5:$B$1700,">15",Allocations!$B$5:$B$1700,"<=19",Allocations!$F$5:$F$1700,"LP",Allocations!$D$5:$D$1700,"Other fund expenses"))))/F7) -> -0.014117875 | G13: =IF(G7=0,0,(SUMIFS(Allocations!$E$5:$E$1700,Allocations!$B$5:$B$1700,">19",Allocations!$B$5:$B$1700,"<=23",Allocations!$F$5:$F$1700,"LP",Allocations!$D$5:$D$1700,"Investment income")-(-(SUMIFS(Allocations!$E$5:$E$1700,Allocations!$B$5:$B$1700,">19",Allocations!$B$5:$B$1700,"<=23",Allocations!$F$5:$F$1700,"LP",Allocations!$D$5:$D$1700,"Management fee")+SUMIFS(Allocations!$E$5:$E$1700,Allocations!$B$5:$B$1700,">19",Allocations!$B$5:$B$1700,"<=23",Allocations!$F$5:$F$1700,"LP",Allocations!$D$5:$D$1700,"Other fund expenses"))))/G7) -> -0.015032599 | H13: =IF(H7=0,0,(SUMIFS(Allocations!$E$5:$E$1700,Allocations!$B$5:$B$1700,">23",Allocations!$B$5:$B$1700,"<=27",Allocations!$F$5:$F$1700,"LP",Allocations!$D$5:$D$1700,"Investment income")-(-(SUMIFS(Allocations!$E$5:$E$1700,Allocations!$B$5:$B$1700,">23",Allocations!$B$5:$B$1700,"<=27",Allocations!$F$5:$F$1700,"LP",Allocations!$D$5:$D$1700,"Management fee")+SUMIFS(Allocations!$E$5:$E$1700,Allocations!$B$5:$B$1700,">23",Allocations!$B$5:$B$1700,"<=27",Allocations!$F$5:$F$1700,"LP",Allocations!$D$5:$D$1700,"Other fund expenses"))))/H7) -> -0.010346747 | I13: =IF(I7=0,0,(SUMIFS(Allocations!$E$5:$E$1700,Allocations!$B$5:$B$1700,">27",Allocations!$B$5:$B$1700,"<=31",Allocations!$F$5:$F$1700,"LP",Allocations!$D$5:$D$1700,"Investment income")-(-(SUMIFS(Allocations!$E$5:$E$1700,Allocations!$B$5:$B$1700,">27",Allocations!$B$5:$B$1700,"<=31",Allocations!$F$5:$F$1700,"LP",Allocations!$D$5:$D$1700,"Management fee")+SUMIFS(Allocations!$E$5:$E$1700,Allocations!$B$5:$B$1700,">27",Allocations!$B$5:$B$1700,"<=31",Allocations!$F$5:$F$1700,"LP",Allocations!$D$5:$D$1700,"Other fund expenses"))))/I7) -> 0.00024704335 | J13: =IF(J7=0,0,(SUMIFS(Allocations!$E$5:$E$1700,Allocations!$B$5:$B$1700,">31",Allocations!$B$5:$B$1700,"<=35",Allocations!$F$5:$F$1700,"LP",Allocations!$D$5:$D$1700,"Investment income")-(-(SUMIFS(Allocations!$E$5:$E$1700,Allocations!$B$5:$B$1700,">31",Allocations!$B$5:$B$1700,"<=35",Allocations!$F$5:$F$1700,"LP",Allocations!$D$5:$D$1700,"Management fee")+SUMIFS(Allocations!$E$5:$E$1700,Allocations!$B$5:$B$1700,">31",Allocations!$B$5:$B$1700,"<=35",Allocations!$F$5:$F$1700,"LP",Allocations!$D$5:$D$1700,"Other fund expenses"))))/J7) -> 0.0064110602 | K13: =IF(K7=0,0,(SUMIFS(Allocations!$E$5:$E$1700,Allocations!$B$5:$B$1700,">35",Allocations!$B$5:$B$1700,"<=39",Allocations!$F$5:$F$1700,"LP",Allocations!$D$5:$D$1700,"Investment income")-(-(SUMIFS(Allocations!$E$5:$E$1700,Allocations!$B$5:$B$1700,">35",Allocations!$B$5:$B$1700,"<=39",Allocations!$F$5:$F$1700,"LP",Allocations!$D$5:$D$1700,"Management fee")+SUMIFS(Allocations!$E$5:$E$1700,Allocations!$B$5:$B$1700,">35",Allocations!$B$5:$B$1700,"<=39",Allocations!$F$5:$F$1700,"LP",Allocations!$D$5:$D$1700,"Other fund expenses"))))/K7) -> 0.014530203 | L13: =IF(L7=0,0,(SUMIFS(Allocations!$E$5:$E$1700,Allocations!$B$5:$B$1700,">39",Allocations!$B$5:$B$1700,"<=43",Allocations!$F$5:$F$1700,"LP",Allocations!$D$5:$D$1700,"Investment income")-(-(SUMIFS(Allocations!$E$5:$E$1700,Allocations!$B$5:$B$1700,">39",Allocations!$B$5:$B$1700,"<=43",Allocations!$F$5:$F$1700,"LP",Allocations!$D$5:$D$1700,"Management fee")+SUMIFS(Allocations!$E$5:$E$1700,Allocations!$B$5:$B$1700,">39",Allocations!$B$5:$B$1700,"<=43",Allocations!$F$5:$F$1700,"LP",Allocations!$D$5:$D$1700,"Other fund expenses"))))/L7) -> -0.030220402 | M13: =IF(M7=0,0,(SUMIFS(Allocations!$E$5:$E$1700,Allocations!$B$5:$B$1700,">43",Allocations!$B$5:$B$1700,"<=45",Allocations!$F$5:$F$1700,"LP",Allocations!$D$5:$D$1700,"Investment income")-(-(SUMIFS(Allocations!$E$5:$E$1700,Allocations!$B$5:$B$1700,">43",Allocations!$B$5:$B$1700,"<=45",Allocations!$F$5:$F$1700,"LP",Allocations!$D$5:$D$1700,"Management fee")+SUMIFS(Allocations!$E$5:$E$1700,Allocations!$B$5:$B$1700,">43",Allocations!$B$5:$B$1700,"<=45",Allocations!$F$5:$F$1700,"LP",Allocations!$D$5:$D$1700,"Other fund expenses"))))/M7) -> -0.24405641
A15: TOTAL RETURN
A16: Total return before carried interest | B16: =IF(B7=0,0,(SUMIFS(Allocations!$E$5:$E$1700,Allocations!$B$5:$B$1700,">-1",Allocations!$B$5:$B$1700,"<=3",Allocations!$F$5:$F$1700,"LP",Allocations!$D$5:$D$1700,"Investment income")-(-(SUMIFS(Allocations!$E$5:$E$1700,Allocations!$B$5:$B$1700,">-1",Allocations!$B$5:$B$1700,"<=3",Allocations!$F$5:$F$1700,"LP",Allocations!$D$5:$D$1700,"Management fee")+SUMIFS(Allocations!$E$5:$E$1700,Allocations!$B$5:$B$1700,">-1",Allocations!$B$5:$B$1700,"<=3",Allocations!$F$5:$F$1700,"LP",Allocations!$D$5:$D$1700,"Other fund expenses")))+SUMIFS(Allocations!$E$5:$E$1700,Allocations!$B$5:$B$1700,">-1",Allocations!$B$5:$B$1700,"<=3",Allocations!$F$5:$F$1700,"LP",Allocations!$D$5:$D$1700,"Realized gain/(loss)")+SUMIFS(Allocations!$E$5:$E$1700,Allocations!$B$5:$B$1700,">-1",Allocations!$B$5:$B$1700,"<=3",Allocations!$F$5:$F$1700,"LP",Allocations!$D$5:$D$1700,"Change in unrealized"))/B7) -> -0.13071971 | C16: =IF(C7=0,0,(SUMIFS(Allocations!$E$5:$E$1700,Allocations!$B$5:$B$1700,">3",Allocations!$B$5:$B$1700,"<=7",Allocations!$F$5:$F$1700,"LP",Allocations!$D$5:$D$1700,"Investment income")-(-(SUMIFS(Allocations!$E$5:$E$1700,Allocations!$B$5:$B$1700,">3",Allocations!$B$5:$B$1700,"<=7",Allocations!$F$5:$F$1700,"LP",Allocations!$D$5:$D$1700,"Management fee")+SUMIFS(Allocations!$E$5:$E$1700,Allocations!$B$5:$B$1700,">3",Allocations!$B$5:$B$1700,"<=7",Allocations!$F$5:$F$1700,"LP",Allocations!$D$5:$D$1700,"Other fund expenses")))+SUMIFS(Allocations!$E$5:$E$1700,Allocations!$B$5:$B$1700,">3",Allocations!$B$5:$B$1700,"<=7",Allocations!$F$5:$F$1700,"LP",Allocations!$D$5:$D$1700,"Realized gain/(loss)")+SUMIFS(Allocations!$E$5:$E$1700,Allocations!$B$5:$B$1700,">3",Allocations!$B$5:$B$1700,"<=7",Allocations!$F$5:$F$1700,"LP",Allocations!$D$5:$D$1700,"Change in unrealized"))/C7) -> 0.030622864 | D16: =IF(D7=0,0,(SUMIFS(Allocations!$E$5:$E$1700,Allocations!$B$5:$B$1700,">7",Allocations!$B$5:$B$1700,"<=11",Allocations!$F$5:$F$1700,"LP",Allocations!$D$5:$D$1700,"Investment income")-(-(SUMIFS(Allocations!$E$5:$E$1700,Allocations!$B$5:$B$1700,">7",Allocations!$B$5:$B$1700,"<=11",Allocations!$F$5:$F$1700,"LP",Allocations!$D$5:$D$1700,"Management fee")+SUMIFS(Allocations!$E$5:$E$1700,Allocations!$B$5:$B$1700,">7",Allocations!$B$5:$B$1700,"<=11",Allocations!$F$5:$F$1700,"LP",Allocations!$D$5:$D$1700,"Other fund expenses")))+SUMIFS(Allocations!$E$5:$E$1700,Allocations!$B$5:$B$1700,">7",Allocations!$B$5:$B$1700,"<=11",Allocations!$F$5:$F$1700,"LP",Allocations!$D$5:$D$1700,"Realized gain/(loss)")+SUMIFS(Allocations!$E$5:$E$1700,Allocations!$B$5:$B$1700,">7",Allocations!$B$5:$B$1700,"<=11",Allocations!$F$5:$F$1700,"LP",Allocations!$D$5:$D$1700,"Change in unrealized"))/D7) -> 0.17252697 | E16: =IF(E7=0,0,(SUMIFS(Allocations!$E$5:$E$1700,Allocations!$B$5:$B$1700,">11",Allocations!$B$5:$B$1700,"<=15",Allocations!$F$5:$F$1700,"LP",Allocations!$D$5:$D$1700,"Investment income")-(-(SUMIFS(Allocations!$E$5:$E$1700,Allocations!$B$5:$B$1700,">11",Allocations!$B$5:$B$1700,"<=15",Allocations!$F$5:$F$1700,"LP",Allocations!$D$5:$D$1700,"Management fee")+SUMIFS(Allocations!$E$5:$E$1700,Allocations!$B$5:$B$1700,">11",Allocations!$B$5:$B$1700,"<=15",Allocations!$F$5:$F$1700,"LP",Allocations!$D$5:$D$1700,"Other fund expenses")))+SUMIFS(Allocations!$E$5:$E$1700,Allocations!$B$5:$B$1700,">11",Allocations!$B$5:$B$1700,"<=15",Allocations!$F$5:$F$1700,"LP",Allocations!$D$5:$D$1700,"Realized gain/(loss)")+SUMIFS(Allocations!$E$5:$E$1700,Allocations!$B$5:$B$1700,">11",Allocations!$B$5:$B$1700,"<=15",Allocations!$F$5:$F$1700,"LP",Allocations!$D$5:$D$1700,"Change in unrealized"))/E7) -> -0.040316933 | F16: =IF(F7=0,0,(SUMIFS(Allocations!$E$5:$E$1700,Allocations!$B$5:$B$1700,">15",Allocations!$B$5:$B$1700,"<=19",Allocations!$F$5:$F$1700,"LP",Allocations!$D$5:$D$1700,"Investment income")-(-(SUMIFS(Allocations!$E$5:$E$1700,Allocations!$B$5:$B$1700,">15",Allocations!$B$5:$B$1700,"<=19",Allocations!$F$5:$F$1700,"LP",Allocations!$D$5:$D$1700,"Management fee")+SUMIFS(Allocations!$E$5:$E$1700,Allocations!$B$5:$B$1700,">15",Allocations!$B$5:$B$1700,"<=19",Allocations!$F$5:$F$1700,"LP",Allocations!$D$5:$D$1700,"Other fund expenses")))+SUMIFS(Allocations!$E$5:$E$1700,Allocations!$B$5:$B$1700,">15",Allocations!$B$5:$B$1700,"<=19",Allocations!$F$5:$F$1700,"LP",Allocations!$D$5:$D$1700,"Realized gain/(loss)")+SUMIFS(Allocations!$E$5:$E$1700,Allocations!$B$5:$B$1700,">15",Allocations!$B$5:$B$1700,"<=19",Allocations!$F$5:$F$1700,"LP",Allocations!$D$5:$D$1700,"Change in unrealized"))/F7) -> 0.1209697 | G16: =IF(G7=0,0,(SUMIFS(Allocations!$E$5:$E$1700,Allocations!$B$5:$B$1700,">19",Allocations!$B$5:$B$1700,"<=23",Allocations!$F$5:$F$1700,"LP",Allocations!$D$5:$D$1700,"Investment income")-(-(SUMIFS(Allocations!$E$5:$E$1700,Allocations!$B$5:$B$1700,">19",Allocations!$B$5:$B$1700,"<=23",Allocations!$F$5:$F$1700,"LP",Allocations!$D$5:$D$1700,"Management fee")+SUMIFS(Allocations!$E$5:$E$1700,Allocations!$B$5:$B$1700,">19",Allocations!$B$5:$B$1700,"<=23",Allocations!$F$5:$F$1700,"LP",Allocations!$D$5:$D$1700,"Other fund expenses")))+SUMIFS(Allocations!$E$5:$E$1700,Allocations!$B$5:$B$1700,">19",Allocations!$B$5:$B$1700,"<=23",Allocations!$F$5:$F$1700,"LP",Allocations!$D$5:$D$1700,"Realized gain/(loss)")+SUMIFS(Allocations!$E$5:$E$1700,Allocations!$B$5:$B$1700,">19",Allocations!$B$5:$B$1700,"<=23",Allocations!$F$5:$F$1700,"LP",Allocations!$D$5:$D$1700,"Change in unrealized"))/G7) -> 0.23774775 | H16: =IF(H7=0,0,(SUMIFS(Allocations!$E$5:$E$1700,Allocations!$B$5:$B$1700,">23",Allocations!$B$5:$B$1700,"<=27",Allocations!$F$5:$F$1700,"LP",Allocations!$D$5:$D$1700,"Investment income")-(-(SUMIFS(Allocations!$E$5:$E$1700,Allocations!$B$5:$B$1700,">23",Allocations!$B$5:$B$1700,"<=27",Allocations!$F$5:$F$1700,"LP",Allocations!$D$5:$D$1700,"Management fee")+SUMIFS(Allocations!$E$5:$E$1700,Allocations!$B$5:$B$1700,">23",Allocations!$B$5:$B$1700,"<=27",Allocations!$F$5:$F$1700,"LP",Allocations!$D$5:$D$1700,"Other fund expenses")))+SUMIFS(Allocations!$E$5:$E$1700,Allocations!$B$5:$B$1700,">23",Allocations!$B$5:$B$1700,"<=27",Allocations!$F$5:$F$1700,"LP",Allocations!$D$5:$D$1700,"Realized gain/(loss)")+SUMIFS(Allocations!$E$5:$E$1700,Allocations!$B$5:$B$1700,">23",Allocations!$B$5:$B$1700,"<=27",Allocations!$F$5:$F$1700,"LP",Allocations!$D$5:$D$1700,"Change in unrealized"))/H7) -> 0.089840776 | I16: =IF(I7=0,0,(SUMIFS(Allocations!$E$5:$E$1700,Allocations!$B$5:$B$1700,">27",Allocations!$B$5:$B$1700,"<=31",Allocations!$F$5:$F$1700,"LP",Allocations!$D$5:$D$1700,"Investment income")-(-(SUMIFS(Allocations!$E$5:$E$1700,Allocations!$B$5:$B$1700,">27",Allocations!$B$5:$B$1700,"<=31",Allocations!$F$5:$F$1700,"LP",Allocations!$D$5:$D$1700,"Management fee")+SUMIFS(Allocations!$E$5:$E$1700,Allocations!$B$5:$B$1700,">27",Allocations!$B$5:$B$1700,"<=31",Allocations!$F$5:$F$1700,"LP",Allocations!$D$5:$D$1700,"Other fund expenses")))+SUMIFS(Allocations!$E$5:$E$1700,Allocations!$B$5:$B$1700,">27",Allocations!$B$5:$B$1700,"<=31",Allocations!$F$5:$F$1700,"LP",Allocations!$D$5:$D$1700,"Realized gain/(loss)")+SUMIFS(Allocations!$E$5:$E$1700,Allocations!$B$5:$B$1700,">27",Allocations!$B$5:$B$1700,"<=31",Allocations!$F$5:$F$1700,"LP",Allocations!$D$5:$D$1700,"Change in unrealized"))/I7) -> 0.095321323 | J16: =IF(J7=0,0,(SUMIFS(Allocations!$E$5:$E$1700,Allocations!$B$5:$B$1700,">31",Allocations!$B$5:$B$1700,"<=35",Allocations!$F$5:$F$1700,"LP",Allocations!$D$5:$D$1700,"Investment income")-(-(SUMIFS(Allocations!$E$5:$E$1700,Allocations!$B$5:$B$1700,">31",Allocations!$B$5:$B$1700,"<=35",Allocations!$F$5:$F$1700,"LP",Allocations!$D$5:$D$1700,"Management fee")+SUMIFS(Allocations!$E$5:$E$1700,Allocations!$B$5:$B$1700,">31",Allocations!$B$5:$B$1700,"<=35",Allocations!$F$5:$F$1700,"LP",Allocations!$D$5:$D$1700,"Other fund expenses")))+SUMIFS(Allocations!$E$5:$E$1700,Allocations!$B$5:$B$1700,">31",Allocations!$B$5:$B$1700,"<=35",Allocations!$F$5:$F$1700,"LP",Allocations!$D$5:$D$1700,"Realized gain/(loss)")+SUMIFS(Allocations!$E$5:$E$1700,Allocations!$B$5:$B$1700,">31",Allocations!$B$5:$B$1700,"<=35",Allocations!$F$5:$F$1700,"LP",Allocations!$D$5:$D$1700,"Change in unrealized"))/J7) -> 0.3061968 | K16: =IF(K7=0,0,(SUMIFS(Allocations!$E$5:$E$1700,Allocations!$B$5:$B$1700,">35",Allocations!$B$5:$B$1700,"<=39",Allocations!$F$5:$F$1700,"LP",Allocations!$D$5:$D$1700,"Investment income")-(-(SUMIFS(Allocations!$E$5:$E$1700,Allocations!$B$5:$B$1700,">35",Allocations!$B$5:$B$1700,"<=39",Allocations!$F$5:$F$1700,"LP",Allocations!$D$5:$D$1700,"Management fee")+SUMIFS(Allocations!$E$5:$E$1700,Allocations!$B$5:$B$1700,">35",Allocations!$B$5:$B$1700,"<=39",Allocations!$F$5:$F$1700,"LP",Allocations!$D$5:$D$1700,"Other fund expenses")))+SUMIFS(Allocations!$E$5:$E$1700,Allocations!$B$5:$B$1700,">35",Allocations!$B$5:$B$1700,"<=39",Allocations!$F$5:$F$1700,"LP",Allocations!$D$5:$D$1700,"Realized gain/(loss)")+SUMIFS(Allocations!$E$5:$E$1700,Allocations!$B$5:$B$1700,">35",Allocations!$B$5:$B$1700,"<=39",Allocations!$F$5:$F$1700,"LP",Allocations!$D$5:$D$1700,"Change in unrealized"))/K7) -> 0.20652389 | L16: =IF(L7=0,0,(SUMIFS(Allocations!$E$5:$E$1700,Allocations!$B$5:$B$1700,">39",Allocations!$B$5:$B$1700,"<=43",Allocations!$F$5:$F$1700,"LP",Allocations!$D$5:$D$1700,"Investment income")-(-(SUMIFS(Allocations!$E$5:$E$1700,Allocations!$B$5:$B$1700,">39",Allocations!$B$5:$B$1700,"<=43",Allocations!$F$5:$F$1700,"LP",Allocations!$D$5:$D$1700,"Management fee")+SUMIFS(Allocations!$E$5:$E$1700,Allocations!$B$5:$B$1700,">39",Allocations!$B$5:$B$1700,"<=43",Allocations!$F$5:$F$1700,"LP",Allocations!$D$5:$D$1700,"Other fund expenses")))+SUMIFS(Allocations!$E$5:$E$1700,Allocations!$B$5:$B$1700,">39",Allocations!$B$5:$B$1700,"<=43",Allocations!$F$5:$F$1700,"LP",Allocations!$D$5:$D$1700,"Realized gain/(loss)")+SUMIFS(Allocations!$E$5:$E$1700,Allocations!$B$5:$B$1700,">39",Allocations!$B$5:$B$1700,"<=43",Allocations!$F$5:$F$1700,"LP",Allocations!$D$5:$D$1700,"Change in unrealized"))/L7) -> 0.74238754 | M16: =IF(M7=0,0,(SUMIFS(Allocations!$E$5:$E$1700,Allocations!$B$5:$B$1700,">43",Allocations!$B$5:$B$1700,"<=45",Allocations!$F$5:$F$1700,"LP",Allocations!$D$5:$D$1700,"Investment income")-(-(SUMIFS(Allocations!$E$5:$E$1700,Allocations!$B$5:$B$1700,">43",Allocations!$B$5:$B$1700,"<=45",Allocations!$F$5:$F$1700,"LP",Allocations!$D$5:$D$1700,"Management fee")+SUMIFS(Allocations!$E$5:$E$1700,Allocations!$B$5:$B$1700,">43",Allocations!$B$5:$B$1700,"<=45",Allocations!$F$5:$F$1700,"LP",Allocations!$D$5:$D$1700,"Other fund expenses")))+SUMIFS(Allocations!$E$5:$E$1700,Allocations!$B$5:$B$1700,">43",Allocations!$B$5:$B$1700,"<=45",Allocations!$F$5:$F$1700,"LP",Allocations!$D$5:$D$1700,"Realized gain/(loss)")+SUMIFS(Allocations!$E$5:$E$1700,Allocations!$B$5:$B$1700,">43",Allocations!$B$5:$B$1700,"<=45",Allocations!$F$5:$F$1700,"LP",Allocations!$D$5:$D$1700,"Change in unrealized"))/M7) -> -0.24405641
A17: Total return after carried interest | B17: =IF(B7=0,0,(SUMIFS(Allocations!$E$5:$E$1700,Allocations!$B$5:$B$1700,">-1",Allocations!$B$5:$B$1700,"<=3",Allocations!$F$5:$F$1700,"LP",Allocations!$D$5:$D$1700,"Investment income")-(-(SUMIFS(Allocations!$E$5:$E$1700,Allocations!$B$5:$B$1700,">-1",Allocations!$B$5:$B$1700,"<=3",Allocations!$F$5:$F$1700,"LP",Allocations!$D$5:$D$1700,"Management fee")+SUMIFS(Allocations!$E$5:$E$1700,Allocations!$B$5:$B$1700,">-1",Allocations!$B$5:$B$1700,"<=3",Allocations!$F$5:$F$1700,"LP",Allocations!$D$5:$D$1700,"Other fund expenses")))+SUMIFS(Allocations!$E$5:$E$1700,Allocations!$B$5:$B$1700,">-1",Allocations!$B$5:$B$1700,"<=3",Allocations!$F$5:$F$1700,"LP",Allocations!$D$5:$D$1700,"Realized gain/(loss)")+SUMIFS(Allocations!$E$5:$E$1700,Allocations!$B$5:$B$1700,">-1",Allocations!$B$5:$B$1700,"<=3",Allocations!$F$5:$F$1700,"LP",Allocations!$D$5:$D$1700,"Change in unrealized")-(-(SUMIFS(Allocations!$E$5:$E$1700,Allocations!$B$5:$B$1700,">-1",Allocations!$B$5:$B$1700,"<=3",Allocations!$F$5:$F$1700,"LP",Allocations!$D$5:$D$1700,"Carried interest"))))/B7) -> -0.13071971 | C17: =IF(C7=0,0,(SUMIFS(Allocations!$E$5:$E$1700,Allocations!$B$5:$B$1700,">3",Allocations!$B$5:$B$1700,"<=7",Allocations!$F$5:$F$1700,"LP",Allocations!$D$5:$D$1700,"Investment income")-(-(SUMIFS(Allocations!$E$5:$E$1700,Allocations!$B$5:$B$1700,">3",Allocations!$B$5:$B$1700,"<=7",Allocations!$F$5:$F$1700,"LP",Allocations!$D$5:$D$1700,"Management fee")+SUMIFS(Allocations!$E$5:$E$1700,Allocations!$B$5:$B$1700,">3",Allocations!$B$5:$B$1700,"<=7",Allocations!$F$5:$F$1700,"LP",Allocations!$D$5:$D$1700,"Other fund expenses")))+SUMIFS(Allocations!$E$5:$E$1700,Allocations!$B$5:$B$1700,">3",Allocations!$B$5:$B$1700,"<=7",Allocations!$F$5:$F$1700,"LP",Allocations!$D$5:$D$1700,"Realized gain/(loss)")+SUMIFS(Allocations!$E$5:$E$1700,Allocations!$B$5:$B$1700,">3",Allocations!$B$5:$B$1700,"<=7",Allocations!$F$5:$F$1700,"LP",Allocations!$D$5:$D$1700,"Change in unrealized")-(-(SUMIFS(Allocations!$E$5:$E$1700,Allocations!$B$5:$B$1700,">3",Allocations!$B$5:$B$1700,"<=7",Allocations!$F$5:$F$1700,"LP",Allocations!$D$5:$D$1700,"Carried interest"))))/C7) -> 0.030622864 | D17: =IF(D7=0,0,(SUMIFS(Allocations!$E$5:$E$1700,Allocations!$B$5:$B$1700,">7",Allocations!$B$5:$B$1700,"<=11",Allocations!$F$5:$F$1700,"LP",Allocations!$D$5:$D$1700,"Investment income")-(-(SUMIFS(Allocations!$E$5:$E$1700,Allocations!$B$5:$B$1700,">7",Allocations!$B$5:$B$1700,"<=11",Allocations!$F$5:$F$1700,"LP",Allocations!$D$5:$D$1700,"Management fee")+SUMIFS(Allocations!$E$5:$E$1700,Allocations!$B$5:$B$1700,">7",Allocations!$B$5:$B$1700,"<=11",Allocations!$F$5:$F$1700,"LP",Allocations!$D$5:$D$1700,"Other fund expenses")))+SUMIFS(Allocations!$E$5:$E$1700,Allocations!$B$5:$B$1700,">7",Allocations!$B$5:$B$1700,"<=11",Allocations!$F$5:$F$1700,"LP",Allocations!$D$5:$D$1700,"Realized gain/(loss)")+SUMIFS(Allocations!$E$5:$E$1700,Allocations!$B$5:$B$1700,">7",Allocations!$B$5:$B$1700,"<=11",Allocations!$F$5:$F$1700,"LP",Allocations!$D$5:$D$1700,"Change in unrealized")-(-(SUMIFS(Allocations!$E$5:$E$1700,Allocations!$B$5:$B$1700,">7",Allocations!$B$5:$B$1700,"<=11",Allocations!$F$5:$F$1700,"LP",Allocations!$D$5:$D$1700,"Carried interest"))))/D7) -> 0.14002443 | E17: =IF(E7=0,0,(SUMIFS(Allocations!$E$5:$E$1700,Allocations!$B$5:$B$1700,">11",Allocations!$B$5:$B$1700,"<=15",Allocations!$F$5:$F$1700,"LP",Allocations!$D$5:$D$1700,"Investment income")-(-(SUMIFS(Allocations!$E$5:$E$1700,Allocations!$B$5:$B$1700,">11",Allocations!$B$5:$B$1700,"<=15",Allocations!$F$5:$F$1700,"LP",Allocations!$D$5:$D$1700,"Management fee")+SUMIFS(Allocations!$E$5:$E$1700,Allocations!$B$5:$B$1700,">11",Allocations!$B$5:$B$1700,"<=15",Allocations!$F$5:$F$1700,"LP",Allocations!$D$5:$D$1700,"Other fund expenses")))+SUMIFS(Allocations!$E$5:$E$1700,Allocations!$B$5:$B$1700,">11",Allocations!$B$5:$B$1700,"<=15",Allocations!$F$5:$F$1700,"LP",Allocations!$D$5:$D$1700,"Realized gain/(loss)")+SUMIFS(Allocations!$E$5:$E$1700,Allocations!$B$5:$B$1700,">11",Allocations!$B$5:$B$1700,"<=15",Allocations!$F$5:$F$1700,"LP",Allocations!$D$5:$D$1700,"Change in unrealized")-(-(SUMIFS(Allocations!$E$5:$E$1700,Allocations!$B$5:$B$1700,">11",Allocations!$B$5:$B$1700,"<=15",Allocations!$F$5:$F$1700,"LP",Allocations!$D$5:$D$1700,"Carried interest"))))/E7) -> -0.016367503 | F17: =IF(F7=0,0,(SUMIFS(Allocations!$E$5:$E$1700,Allocations!$B$5:$B$1700,">15",Allocations!$B$5:$B$1700,"<=19",Allocations!$F$5:$F$1700,"LP",Allocations!$D$5:$D$1700,"Investment income")-(-(SUMIFS(Allocations!$E$5:$E$1700,Allocations!$B$5:$B$1700,">15",Allocations!$B$5:$B$1700,"<=19",Allocations!$F$5:$F$1700,"LP",Allocations!$D$5:$D$1700,"Management fee")+SUMIFS(Allocations!$E$5:$E$1700,Allocations!$B$5:$B$1700,">15",Allocations!$B$5:$B$1700,"<=19",Allocations!$F$5:$F$1700,"LP",Allocations!$D$5:$D$1700,"Other fund expenses")))+SUMIFS(Allocations!$E$5:$E$1700,Allocations!$B$5:$B$1700,">15",Allocations!$B$5:$B$1700,"<=19",Allocations!$F$5:$F$1700,"LP",Allocations!$D$5:$D$1700,"Realized gain/(loss)")+SUMIFS(Allocations!$E$5:$E$1700,Allocations!$B$5:$B$1700,">15",Allocations!$B$5:$B$1700,"<=19",Allocations!$F$5:$F$1700,"LP",Allocations!$D$5:$D$1700,"Change in unrealized")-(-(SUMIFS(Allocations!$E$5:$E$1700,Allocations!$B$5:$B$1700,">15",Allocations!$B$5:$B$1700,"<=19",Allocations!$F$5:$F$1700,"LP",Allocations!$D$5:$D$1700,"Carried interest"))))/F7) -> 0.1209697 | G17: =IF(G7=0,0,(SUMIFS(Allocations!$E$5:$E$1700,Allocations!$B$5:$B$1700,">19",Allocations!$B$5:$B$1700,"<=23",Allocations!$F$5:$F$1700,"LP",Allocations!$D$5:$D$1700,"Investment income")-(-(SUMIFS(Allocations!$E$5:$E$1700,Allocations!$B$5:$B$1700,">19",Allocations!$B$5:$B$1700,"<=23",Allocations!$F$5:$F$1700,"LP",Allocations!$D$5:$D$1700,"Management fee")+SUMIFS(Allocations!$E$5:$E$1700,Allocations!$B$5:$B$1700,">19",Allocations!$B$5:$B$1700,"<=23",Allocations!$F$5:$F$1700,"LP",Allocations!$D$5:$D$1700,"Other fund expenses")))+SUMIFS(Allocations!$E$5:$E$1700,Allocations!$B$5:$B$1700,">19",Allocations!$B$5:$B$1700,"<=23",Allocations!$F$5:$F$1700,"LP",Allocations!$D$5:$D$1700,"Realized gain/(loss)")+SUMIFS(Allocations!$E$5:$E$1700,Allocations!$B$5:$B$1700,">19",Allocations!$B$5:$B$1700,"<=23",Allocations!$F$5:$F$1700,"LP",Allocations!$D$5:$D$1700,"Change in unrealized")-(-(SUMIFS(Allocations!$E$5:$E$1700,Allocations!$B$5:$B$1700,">19",Allocations!$B$5:$B$1700,"<=23",Allocations!$F$5:$F$1700,"LP",Allocations!$D$5:$D$1700,"Carried interest"))))/G7) -> 0.14894668 | H17: =IF(H7=0,0,(SUMIFS(Allocations!$E$5:$E$1700,Allocations!$B$5:$B$1700,">23",Allocations!$B$5:$B$1700,"<=27",Allocations!$F$5:$F$1700,"LP",Allocations!$D$5:$D$1700,"Investment income")-(-(SUMIFS(Allocations!$E$5:$E$1700,Allocations!$B$5:$B$1700,">23",Allocations!$B$5:$B$1700,"<=27",Allocations!$F$5:$F$1700,"LP",Allocations!$D$5:$D$1700,"Management fee")+SUMIFS(Allocations!$E$5:$E$1700,Allocations!$B$5:$B$1700,">23",Allocations!$B$5:$B$1700,"<=27",Allocations!$F$5:$F$1700,"LP",Allocations!$D$5:$D$1700,"Other fund expenses")))+SUMIFS(Allocations!$E$5:$E$1700,Allocations!$B$5:$B$1700,">23",Allocations!$B$5:$B$1700,"<=27",Allocations!$F$5:$F$1700,"LP",Allocations!$D$5:$D$1700,"Realized gain/(loss)")+SUMIFS(Allocations!$E$5:$E$1700,Allocations!$B$5:$B$1700,">23",Allocations!$B$5:$B$1700,"<=27",Allocations!$F$5:$F$1700,"LP",Allocations!$D$5:$D$1700,"Change in unrealized")-(-(SUMIFS(Allocations!$E$5:$E$1700,Allocations!$B$5:$B$1700,">23",Allocations!$B$5:$B$1700,"<=27",Allocations!$F$5:$F$1700,"LP",Allocations!$D$5:$D$1700,"Carried interest"))))/H7) -> 0.07187267 | I17: =IF(I7=0,0,(SUMIFS(Allocations!$E$5:$E$1700,Allocations!$B$5:$B$1700,">27",Allocations!$B$5:$B$1700,"<=31",Allocations!$F$5:$F$1700,"LP",Allocations!$D$5:$D$1700,"Investment income")-(-(SUMIFS(Allocations!$E$5:$E$1700,Allocations!$B$5:$B$1700,">27",Allocations!$B$5:$B$1700,"<=31",Allocations!$F$5:$F$1700,"LP",Allocations!$D$5:$D$1700,"Management fee")+SUMIFS(Allocations!$E$5:$E$1700,Allocations!$B$5:$B$1700,">27",Allocations!$B$5:$B$1700,"<=31",Allocations!$F$5:$F$1700,"LP",Allocations!$D$5:$D$1700,"Other fund expenses")))+SUMIFS(Allocations!$E$5:$E$1700,Allocations!$B$5:$B$1700,">27",Allocations!$B$5:$B$1700,"<=31",Allocations!$F$5:$F$1700,"LP",Allocations!$D$5:$D$1700,"Realized gain/(loss)")+SUMIFS(Allocations!$E$5:$E$1700,Allocations!$B$5:$B$1700,">27",Allocations!$B$5:$B$1700,"<=31",Allocations!$F$5:$F$1700,"LP",Allocations!$D$5:$D$1700,"Change in unrealized")-(-(SUMIFS(Allocations!$E$5:$E$1700,Allocations!$B$5:$B$1700,">27",Allocations!$B$5:$B$1700,"<=31",Allocations!$F$5:$F$1700,"LP",Allocations!$D$5:$D$1700,"Carried interest"))))/I7) -> 0.076257388 | J17: =IF(J7=0,0,(SUMIFS(Allocations!$E$5:$E$1700,Allocations!$B$5:$B$1700,">31",Allocations!$B$5:$B$1700,"<=35",Allocations!$F$5:$F$1700,"LP",Allocations!$D$5:$D$1700,"Investment income")-(-(SUMIFS(Allocations!$E$5:$E$1700,Allocations!$B$5:$B$1700,">31",Allocations!$B$5:$B$1700,"<=35",Allocations!$F$5:$F$1700,"LP",Allocations!$D$5:$D$1700,"Management fee")+SUMIFS(Allocations!$E$5:$E$1700,Allocations!$B$5:$B$1700,">31",Allocations!$B$5:$B$1700,"<=35",Allocations!$F$5:$F$1700,"LP",Allocations!$D$5:$D$1700,"Other fund expenses")))+SUMIFS(Allocations!$E$5:$E$1700,Allocations!$B$5:$B$1700,">31",Allocations!$B$5:$B$1700,"<=35",Allocations!$F$5:$F$1700,"LP",Allocations!$D$5:$D$1700,"Realized gain/(loss)")+SUMIFS(Allocations!$E$5:$E$1700,Allocations!$B$5:$B$1700,">31",Allocations!$B$5:$B$1700,"<=35",Allocations!$F$5:$F$1700,"LP",Allocations!$D$5:$D$1700,"Change in unrealized")-(-(SUMIFS(Allocations!$E$5:$E$1700,Allocations!$B$5:$B$1700,">31",Allocations!$B$5:$B$1700,"<=35",Allocations!$F$5:$F$1700,"LP",Allocations!$D$5:$D$1700,"Carried interest"))))/J7) -> 0.24495879 | K17: =IF(K7=0,0,(SUMIFS(Allocations!$E$5:$E$1700,Allocations!$B$5:$B$1700,">35",Allocations!$B$5:$B$1700,"<=39",Allocations!$F$5:$F$1700,"LP",Allocations!$D$5:$D$1700,"Investment income")-(-(SUMIFS(Allocations!$E$5:$E$1700,Allocations!$B$5:$B$1700,">35",Allocations!$B$5:$B$1700,"<=39",Allocations!$F$5:$F$1700,"LP",Allocations!$D$5:$D$1700,"Management fee")+SUMIFS(Allocations!$E$5:$E$1700,Allocations!$B$5:$B$1700,">35",Allocations!$B$5:$B$1700,"<=39",Allocations!$F$5:$F$1700,"LP",Allocations!$D$5:$D$1700,"Other fund expenses")))+SUMIFS(Allocations!$E$5:$E$1700,Allocations!$B$5:$B$1700,">35",Allocations!$B$5:$B$1700,"<=39",Allocations!$F$5:$F$1700,"LP",Allocations!$D$5:$D$1700,"Realized gain/(loss)")+SUMIFS(Allocations!$E$5:$E$1700,Allocations!$B$5:$B$1700,">35",Allocations!$B$5:$B$1700,"<=39",Allocations!$F$5:$F$1700,"LP",Allocations!$D$5:$D$1700,"Change in unrealized")-(-(SUMIFS(Allocations!$E$5:$E$1700,Allocations!$B$5:$B$1700,">35",Allocations!$B$5:$B$1700,"<=39",Allocations!$F$5:$F$1700,"LP",Allocations!$D$5:$D$1700,"Carried interest"))))/K7) -> 0.16517927 | L17: =IF(L7=0,0,(SUMIFS(Allocations!$E$5:$E$1700,Allocations!$B$5:$B$1700,">39",Allocations!$B$5:$B$1700,"<=43",Allocations!$F$5:$F$1700,"LP",Allocations!$D$5:$D$1700,"Investment income")-(-(SUMIFS(Allocations!$E$5:$E$1700,Allocations!$B$5:$B$1700,">39",Allocations!$B$5:$B$1700,"<=43",Allocations!$F$5:$F$1700,"LP",Allocations!$D$5:$D$1700,"Management fee")+SUMIFS(Allocations!$E$5:$E$1700,Allocations!$B$5:$B$1700,">39",Allocations!$B$5:$B$1700,"<=43",Allocations!$F$5:$F$1700,"LP",Allocations!$D$5:$D$1700,"Other fund expenses")))+SUMIFS(Allocations!$E$5:$E$1700,Allocations!$B$5:$B$1700,">39",Allocations!$B$5:$B$1700,"<=43",Allocations!$F$5:$F$1700,"LP",Allocations!$D$5:$D$1700,"Realized gain/(loss)")+SUMIFS(Allocations!$E$5:$E$1700,Allocations!$B$5:$B$1700,">39",Allocations!$B$5:$B$1700,"<=43",Allocations!$F$5:$F$1700,"LP",Allocations!$D$5:$D$1700,"Change in unrealized")-(-(SUMIFS(Allocations!$E$5:$E$1700,Allocations!$B$5:$B$1700,">39",Allocations!$B$5:$B$1700,"<=43",Allocations!$F$5:$F$1700,"LP",Allocations!$D$5:$D$1700,"Carried interest"))))/L7) -> 0.59384937 | M17: =IF(M7=0,0,(SUMIFS(Allocations!$E$5:$E$1700,Allocations!$B$5:$B$1700,">43",Allocations!$B$5:$B$1700,"<=45",Allocations!$F$5:$F$1700,"LP",Allocations!$D$5:$D$1700,"Investment income")-(-(SUMIFS(Allocations!$E$5:$E$1700,Allocations!$B$5:$B$1700,">43",Allocations!$B$5:$B$1700,"<=45",Allocations!$F$5:$F$1700,"LP",Allocations!$D$5:$D$1700,"Management fee")+SUMIFS(Allocations!$E$5:$E$1700,Allocations!$B$5:$B$1700,">43",Allocations!$B$5:$B$1700,"<=45",Allocations!$F$5:$F$1700,"LP",Allocations!$D$5:$D$1700,"Other fund expenses")))+SUMIFS(Allocations!$E$5:$E$1700,Allocations!$B$5:$B$1700,">43",Allocations!$B$5:$B$1700,"<=45",Allocations!$F$5:$F$1700,"LP",Allocations!$D$5:$D$1700,"Realized gain/(loss)")+SUMIFS(Allocations!$E$5:$E$1700,Allocations!$B$5:$B$1700,">43",Allocations!$B$5:$B$1700,"<=45",Allocations!$F$5:$F$1700,"LP",Allocations!$D$5:$D$1700,"Change in unrealized")-(-(SUMIFS(Allocations!$E$5:$E$1700,Allocations!$B$5:$B$1700,">43",Allocations!$B$5:$B$1700,"<=45",Allocations!$F$5:$F$1700,"LP",Allocations!$D$5:$D$1700,"Carried interest"))))/M7) -> -0.19514562
A19: INTERNAL RATE OF RETURN
A20: IRR since inception, annualized (LP, net of all fees and carried interest) | B20: =IF(B28=0,0,(1+B28)^4-1) -> -0.15329425 | C20: =IF(C28=0,0,(1+C28)^4-1) -> -0.01507423 | D20: =IF(D28=0,0,(1+D28)^4-1) -> 0.080558912 | E20: =IF(E28=0,0,(1+E28)^4-1) -> 0.03710203 | F20: =IF(F28=0,0,(1+F28)^4-1) -> 0.066147922 | G20: =IF(G28=0,0,(1+G28)^4-1) -> 0.082541481 | H20: =IF(H28=0,0,(1+H28)^4-1) -> 0.081538693 | I20: =IF(I28=0,0,(1+I28)^4-1) -> 0.081332148 | ... M20: =IF(M28=0,0,(1+M28)^4-1) -> 0.10052644
A22: Note - the LP class excludes the general partner (fee-free, 2.0% commitment) and Stanmere Carry I, LLC. Expenses, carried interest and results are the amounts allocated to the six limited partners only.
A23: Note - carried interest is the ASC 946 assumed-liquidation accrual: the carry that would be payable if the fund liquidated at net asset value on the reporting date. It reverses when net asset value falls, which is why some years show a credit.
A24: Note - in the wind-down years the average net asset base is small relative to the results still running through it, so FY2029 and FY2030 ratios and total returns are arithmetically correct but not comparable with a full investment year. FY2030 covers only the six months to the 30 June 2030 term end. The since-inception IRR on row 20 is the measure that stays meaningful across the whole life of the fund.
A26: LP CASH FLOWS SUPPORTING THE SINCE-INCEPTION IRR (quarterly; the closing year holds LP net assets as a terminal value)
A27: Quarter | B27: FY2019 | C27: FY2020 | D27: FY2021 | E27: FY2022 | F27: FY2023 | G27: FY2024 | H27: FY2025 | I27: FY2026 | J27: FY2027 | K27: FY2028 | L27: FY2029 | M27: FY2030
A28: Quarterly IRR | B28: =IFERROR(IRR(B30:B33,0.03),0) -> -0.040747087 | C28: =IFERROR(IRR(C30:C37,0.03),0) -> -0.0037900499 | D28: =IFERROR(IRR(D30:D41,0.03),0) -> 0.019558412 | E28: =IFERROR(IRR(E30:E45,0.03),0) -> 0.0091491786 | F28: =IFERROR(IRR(F30:F49,0.03),0) -> 0.016141916 | G28: =IFERROR(IRR(G30:G53,0.03),0) -> 0.020025753 | H28: =IFERROR(IRR(H30:H57,0.03),0) -> 0.019789451 | I28: =IFERROR(IRR(I30:I61,0.03),0) -> 0.01974076 | J28: =IFERROR(IRR(J30:J65,0.03),0) -> 0.022869652 | K28: =IFERROR(IRR(K30:K69,0.03),0) -> 0.023272109 | L28: =IFERROR(IRR(L30:L73,0.03),0) -> 0.024263563 | M28: =IFERROR(IRR(M30:M75,0.03),0) -> 0.024236197
A30: 2019Q1 | B30: =-SUMIFS(Allocations!$E$5:$E$1700,Allocations!$B$5:$B$1700,0,Allocations!$F$5:$F$1700,"LP",Allocations!$D$5:$D$1700,"Capital contributions")+SUMIFS(Allocations!$E$5:$E$1700,Allocations!$B$5:$B$1700,0,Allocations!$F$5:$F$1700,"LP",Allocations!$D$5:$D$1700,"Distributions") -> -2970833.3 | C30: =-SUMIFS(Allocations!$E$5:$E$1700,Allocations!$B$5:$B$1700,0,Allocations!$F$5:$F$1700,"LP",Allocations!$D$5:$D$1700,"Capital contributions")+SUMIFS(Allocations!$E$5:$E$1700,Allocations!$B$5:$B$1700,0,Allocations!$F$5:$F$1700,"LP",Allocations!$D$5:$D$1700,"Distributions") -> -2970833.3 | D30: =-SUMIFS(Allocations!$E$5:$E$1700,Allocations!$B$5:$B$1700,0,Allocations!$F$5:$F$1700,"LP",Allocations!$D$5:$D$1700,"Capital contributions")+SUMIFS(Allocations!$E$5:$E$1700,Allocations!$B$5:$B$1700,0,Allocations!$F$5:$F$1700,"LP",Allocations!$D$5:$D$1700,"Distributions") -> -2970833.3 | E30: =-SUMIFS(Allocations!$E$5:$E$1700,Allocations!$B$5:$B$1700,0,Allocations!$F$5:$F$1700,"LP",Allocations!$D$5:$D$1700,"Capital contributions")+SUMIFS(Allocations!$E$5:$E$1700,Allocations!$B$5:$B$1700,0,Allocations!$F$5:$F$1700,"LP",Allocations!$D$5:$D$1700,"Distributions") -> -2970833.3 | F30: =-SUMIFS(Allocations!$E$5:$E$1700,Allocations!$B$5:$B$1700,0,Allocations!$F$5:$F$1700,"LP",Allocations!$D$5:$D$1700,"Capital contributions")+SUMIFS(Allocations!$E$5:$E$1700,Allocations!$B$5:$B$1700,0,Allocations!$F$5:$F$1700,"LP",Allocations!$D$5:$D$1700,"Distributions") -> -2970833.3 | G30: =-SUMIFS(Allocations!$E$5:$E$1700,Allocations!$B$5:$B$1700,0,Allocations!$F$5:$F$1700,"LP",Allocations!$D$5:$D$1700,"Capital contributions")+SUMIFS(Allocations!$E$5:$E$1700,Allocations!$B$5:$B$1700,0,Allocations!$F$5:$F$1700,"LP",Allocations!$D$5:$D$1700,"Distributions") -> -2970833.3 | H30: =-SUMIFS(Allocations!$E$5:$E$1700,Allocations!$B$5:$B$1700,0,Allocations!$F$5:$F$1700,"LP",Allocations!$D$5:$D$1700,"Capital contributions")+SUMIFS(Allocations!$E$5:$E$1700,Allocations!$B$5:$B$1700,0,Allocations!$F$5:$F$1700,"LP",Allocations!$D$5:$D$1700,"Distributions") -> -2970833.3 | I30: =-SUMIFS(Allocations!$E$5:$E$1700,Allocations!$B$5:$B$1700,0,Allocations!$F$5:$F$1700,"LP",Allocations!$D$5:$D$1700,"Capital contributions")+SUMIFS(Allocations!$E$5:$E$1700,Allocations!$B$5:$B$1700,0,Allocations!$F$5:$F$1700,"LP",Allocations!$D$5:$D$1700,"Distributions") -> -2970833.3 | ... M30: =-SUMIFS(Allocations!$E$5:$E$1700,Allocations!$B$5:$B$1700,0,Allocations!$F$5:$F$1700,"LP",Allocations!$D$5:$D$1700,"Capital contributions")+SUMIFS(Allocations!$E$5:$E$1700,Allocations!$B$5:$B$1700,0,Allocations!$F$5:$F$1700,"LP",Allocations!$D$5:$D$1700,"Distributions") -> -2970833.3
A31: 2019Q2 | B31: =-SUMIFS(Allocations!$E$5:$E$1700,Allocations!$B$5:$B$1700,1,Allocations!$F$5:$F$1700,"LP",Allocations!$D$5:$D$1700,"Capital contributions")+SUMIFS(Allocations!$E$5:$E$1700,Allocations!$B$5:$B$1700,1,Allocations!$F$5:$F$1700,"LP",Allocations!$D$5:$D$1700,"Distributions") -> -40920833 | C31: =-SUMIFS(Allocations!$E$5:$E$1700,Allocations!$B$5:$B$1700,1,Allocations!$F$5:$F$1700,"LP",Allocations!$D$5:$D$1700,"Capital contributions")+SUMIFS(Allocations!$E$5:$E$1700,Allocations!$B$5:$B$1700,1,Allocations!$F$5:$F$1700,"LP",Allocations!$D$5:$D$1700,"Distributions") -> -40920833 | D31: =-SUMIFS(Allocations!$E$5:$E$1700,Allocations!$B$5:$B$1700,1,Allocations!$F$5:$F$1700,"LP",Allocations!$D$5:$D$1700,"Capital contributions")+SUMIFS(Allocations!$E$5:$E$1700,Allocations!$B$5:$B$1700,1,Allocations!$F$5:$F$1700,"LP",Allocations!$D$5:$D$1700,"Distributions") -> -40920833 | E31: =-SUMIFS(Allocations!$E$5:$E$1700,Allocations!$B$5:$B$1700,1,Allocations!$F$5:$F$1700,"LP",Allocations!$D$5:$D$1700,"Capital contributions")+SUMIFS(Allocations!$E$5:$E$1700,Allocations!$B$5:$B$1700,1,Allocations!$F$5:$F$1700,"LP",Allocations!$D$5:$D$1700,"Distributions") -> -40920833 | F31: =-SUMIFS(Allocations!$E$5:$E$1700,Allocations!$B$5:$B$1700,1,Allocations!$F$5:$F$1700,"LP",Allocations!$D$5:$D$1700,"Capital contributions")+SUMIFS(Allocations!$E$5:$E$1700,Allocations!$B$5:$B$1700,1,Allocations!$F$5:$F$1700,"LP",Allocations!$D$5:$D$1700,"Distributions") -> -40920833 | G31: =-SUMIFS(Allocations!$E$5:$E$1700,Allocations!$B$5:$B$1700,1,Allocations!$F$5:$F$1700,"LP",Allocations!$D$5:$D$1700,"Capital contributions")+SUMIFS(Allocations!$E$5:$E$1700,Allocations!$B$5:$B$1700,1,Allocations!$F$5:$F$1700,"LP",Allocations!$D$5:$D$1700,"Distributions") -> -40920833 | H31: =-SUMIFS(Allocations!$E$5:$E$1700,Allocations!$B$5:$B$1700,1,Allocations!$F$5:$F$1700,"LP",Allocations!$D$5:$D$1700,"Capital contributions")+SUMIFS(Allocations!$E$5:$E$1700,Allocations!$B$5:$B$1700,1,Allocations!$F$5:$F$1700,"LP",Allocations!$D$5:$D$1700,"Distributions") -> -40920833 | I31: =-SUMIFS(Allocations!$E$5:$E$1700,Allocations!$B$5:$B$1700,1,Allocations!$F$5:$F$1700,"LP",Allocations!$D$5:$D$1700,"Capital contributions")+SUMIFS(Allocations!$E$5:$E$1700,Allocations!$B$5:$B$1700,1,Allocations!$F$5:$F$1700,"LP",Allocations!$D$5:$D$1700,"Distributions") -> -40920833 | ... M31: =-SUMIFS(Allocations!$E$5:$E$1700,Allocations!$B$5:$B$1700,1,Allocations!$F$5:$F$1700,"LP",Allocations!$D$5:$D$1700,"Capital contributions")+SUMIFS(Allocations!$E$5:$E$1700,Allocations!$B$5:$B$1700,1,Allocations!$F$5:$F$1700,"LP",Allocations!$D$5:$D$1700,"Distributions") -> -40920833
A32: 2019Q3 | B32: =-SUMIFS(Allocations!$E$5:$E$1700,Allocations!$B$5:$B$1700,2,Allocations!$F$5:$F$1700,"LP",Allocations!$D$5:$D$1700,"Capital contributions")+SUMIFS(Allocations!$E$5:$E$1700,Allocations!$B$5:$B$1700,2,Allocations!$F$5:$F$1700,"LP",Allocations!$D$5:$D$1700,"Distributions") -> -670833.33 | C32: =-SUMIFS(Allocations!$E$5:$E$1700,Allocations!$B$5:$B$1700,2,Allocations!$F$5:$F$1700,"LP",Allocations!$D$5:$D$1700,"Capital contributions")+SUMIFS(Allocations!$E$5:$E$1700,Allocations!$B$5:$B$1700,2,Allocations!$F$5:$F$1700,"LP",Allocations!$D$5:$D$1700,"Distributions") -> -670833.33 | D32: =-SUMIFS(Allocations!$E$5:$E$1700,Allocations!$B$5:$B$1700,2,Allocations!$F$5:$F$1700,"LP",Allocations!$D$5:$D$1700,"Capital contributions")+SUMIFS(Allocations!$E$5:$E$1700,Allocations!$B$5:$B$1700,2,Allocations!$F$5:$F$1700,"LP",Allocations!$D$5:$D$1700,"Distributions") -> -670833.33 | E32: =-SUMIFS(Allocations!$E$5:$E$1700,Allocations!$B$5:$B$1700,2,Allocations!$F$5:$F$1700,"LP",Allocations!$D$5:$D$1700,"Capital contributions")+SUMIFS(Allocations!$E$5:$E$1700,Allocations!$B$5:$B$1700,2,Allocations!$F$5:$F$1700,"LP",Allocations!$D$5:$D$1700,"Distributions") -> -670833.33 | F32: =-SUMIFS(Allocations!$E$5:$E$1700,Allocations!$B$5:$B$1700,2,Allocations!$F$5:$F$1700,"LP",Allocations!$D$5:$D$1700,"Capital contributions")+SUMIFS(Allocations!$E$5:$E$1700,Allocations!$B$5:$B$1700,2,Allocations!$F$5:$F$1700,"LP",Allocations!$D$5:$D$1700,"Distributions") -> -670833.33 | G32: =-SUMIFS(Allocations!$E$5:$E$1700,Allocations!$B$5:$B$1700,2,Allocations!$F$5:$F$1700,"LP",Allocations!$D$5:$D$1700,"Capital contributions")+SUMIFS(Allocations!$E$5:$E$1700,Allocations!$B$5:$B$1700,2,Allocations!$F$5:$F$1700,"LP",Allocations!$D$5:$D$1700,"Distributions") -> -670833.33 | H32: =-SUMIFS(Allocations!$E$5:$E$1700,Allocations!$B$5:$B$1700,2,Allocations!$F$5:$F$1700,"LP",Allocations!$D$5:$D$1700,"Capital contributions")+SUMIFS(Allocations!$E$5:$E$1700,Allocations!$B$5:$B$1700,2,Allocations!$F$5:$F$1700,"LP",Allocations!$D$5:$D$1700,"Distributions") -> -670833.33 | I32: =-SUMIFS(Allocations!$E$5:$E$1700,Allocations!$B$5:$B$1700,2,Allocations!$F$5:$F$1700,"LP",Allocations!$D$5:$D$1700,"Capital contributions")+SUMIFS(Allocations!$E$5:$E$1700,Allocations!$B$5:$B$1700,2,Allocations!$F$5:$F$1700,"LP",Allocations!$D$5:$D$1700,"Distributions") -> -670833.33 | ... M32: =-SUMIFS(Allocations!$E$5:$E$1700,Allocations!$B$5:$B$1700,2,Allocations!$F$5:$F$1700,"LP",Allocations!$D$5:$D$1700,"Capital contributions")+SUMIFS(Allocations!$E$5:$E$1700,Allocations!$B$5:$B$1700,2,Allocations!$F$5:$F$1700,"LP",Allocations!$D$5:$D$1700,"Distributions") -> -670833.33
A33: 2019Q4 | B33: =-SUMIFS(Allocations!$E$5:$E$1700,Allocations!$B$5:$B$1700,3,Allocations!$F$5:$F$1700,"LP",Allocations!$D$5:$D$1700,"Capital contributions")+SUMIFS(Allocations!$E$5:$E$1700,Allocations!$B$5:$B$1700,3,Allocations!$F$5:$F$1700,"LP",Allocations!$D$5:$D$1700,"Distributions")+B6 -> 40919736 | C33: =-SUMIFS(Allocations!$E$5:$E$1700,Allocations!$B$5:$B$1700,3,Allocations!$F$5:$F$1700,"LP",Allocations!$D$5:$D$1700,"Capital contributions")+SUMIFS(Allocations!$E$5:$E$1700,Allocations!$B$5:$B$1700,3,Allocations!$F$5:$F$1700,"LP",Allocations!$D$5:$D$1700,"Distributions") -> -1618055.5 | D33: =-SUMIFS(Allocations!$E$5:$E$1700,Allocations!$B$5:$B$1700,3,Allocations!$F$5:$F$1700,"LP",Allocations!$D$5:$D$1700,"Capital contributions")+SUMIFS(Allocations!$E$5:$E$1700,Allocations!$B$5:$B$1700,3,Allocations!$F$5:$F$1700,"LP",Allocations!$D$5:$D$1700,"Distributions") -> -1618055.5 | E33: =-SUMIFS(Allocations!$E$5:$E$1700,Allocations!$B$5:$B$1700,3,Allocations!$F$5:$F$1700,"LP",Allocations!$D$5:$D$1700,"Capital contributions")+SUMIFS(Allocations!$E$5:$E$1700,Allocations!$B$5:$B$1700,3,Allocations!$F$5:$F$1700,"LP",Allocations!$D$5:$D$1700,"Distributions") -> -1618055.5 | F33: =-SUMIFS(Allocations!$E$5:$E$1700,Allocations!$B$5:$B$1700,3,Allocations!$F$5:$F$1700,"LP",Allocations!$D$5:$D$1700,"Capital contributions")+SUMIFS(Allocations!$E$5:$E$1700,Allocations!$B$5:$B$1700,3,Allocations!$F$5:$F$1700,"LP",Allocations!$D$5:$D$1700,"Distributions") -> -1618055.5 | G33: =-SUMIFS(Allocations!$E$5:$E$1700,Allocations!$B$5:$B$1700,3,Allocations!$F$5:$F$1700,"LP",Allocations!$D$5:$D$1700,"Capital contributions")+SUMIFS(Allocations!$E$5:$E$1700,Allocations!$B$5:$B$1700,3,Allocations!$F$5:$F$1700,"LP",Allocations!$D$5:$D$1700,"Distributions") -> -1618055.5 | H33: =-SUMIFS(Allocations!$E$5:$E$1700,Allocations!$B$5:$B$1700,3,Allocations!$F$5:$F$1700,"LP",Allocations!$D$5:$D$1700,"Capital contributions")+SUMIFS(Allocations!$E$5:$E$1700,Allocations!$B$5:$B$1700,3,Allocations!$F$5:$F$1700,"LP",Allocations!$D$5:$D$1700,"Distributions") -> -1618055.5 | I33: =-SUMIFS(Allocations!$E$5:$E$1700,Allocations!$B$5:$B$1700,3,Allocations!$F$5:$F$1700,"LP",Allocations!$D$5:$D$1700,"Capital contributions")+SUMIFS(Allocations!$E$5:$E$1700,Allocations!$B$5:$B$1700,3,Allocations!$F$5:$F$1700,"LP",Allocations!$D$5:$D$1700,"Distributions") -> -1618055.5 | J33: =-SUMIFS(Allocations!$E$5:$E$1700,Allocations!$B$5:$B$1700,3,Allocations!$F$5:$F$1700,"LP",Allocations!$D$5:$D$1700,"Capital contributions")+SUMIFS(Allocations!$E$5:$E$1700,Allocations!$B$5:$B$1700,3,Allocations!$F$5:$F$1700,"LP",Allocations!$D$5:$D$1700,"Distributions") -> -1618055.5 | ... M33: =-SUMIFS(Allocations!$E$5:$E$1700,Allocations!$B$5:$B$1700,3,Allocations!$F$5:$F$1700,"LP",Allocations!$D$5:$D$1700,"Capital contributions")+SUMIFS(Allocations!$E$5:$E$1700,Allocations!$B$5:$B$1700,3,Allocations!$F$5:$F$1700,"LP",Allocations!$D$5:$D$1700,"Distributions") -> -1618055.5
A34: 2020Q1 | C34: =-SUMIFS(Allocations!$E$5:$E$1700,Allocations!$B$5:$B$1700,4,Allocations!$F$5:$F$1700,"LP",Allocations!$D$5:$D$1700,"Capital contributions")+SUMIFS(Allocations!$E$5:$E$1700,Allocations!$B$5:$B$1700,4,Allocations!$F$5:$F$1700,"LP",Allocations!$D$5:$D$1700,"Distributions") -> -30138889 | D34: =-SUMIFS(Allocations!$E$5:$E$1700,Allocations!$B$5:$B$1700,4,Allocations!$F$5:$F$1700,"LP",Allocations!$D$5:$D$1700,"Capital contributions")+SUMIFS(Allocations!$E$5:$E$1700,Allocations!$B$5:$B$1700,4,Allocations!$F$5:$F$1700,"LP",Allocations!$D$5:$D$1700,"Distributions") -> -30138889 | E34: =-SUMIFS(Allocations!$E$5:$E$1700,Allocations!$B$5:$B$1700,4,Allocations!$F$5:$F$1700,"LP",Allocations!$D$5:$D$1700,"Capital contributions")+SUMIFS(Allocations!$E$5:$E$1700,Allocations!$B$5:$B$1700,4,Allocations!$F$5:$F$1700,"LP",Allocations!$D$5:$D$1700,"Distributions") -> -30138889 | F34: =-SUMIFS(Allocations!$E$5:$E$1700,Allocations!$B$5:$B$1700,4,Allocations!$F$5:$F$1700,"LP",Allocations!$D$5:$D$1700,"Capital contributions")+SUMIFS(Allocations!$E$5:$E$1700,Allocations!$B$5:$B$1700,4,Allocations!$F$5:$F$1700,"LP",Allocations!$D$5:$D$1700,"Distributions") -> -30138889 | G34: =-SUMIFS(Allocations!$E$5:$E$1700,Allocations!$B$5:$B$1700,4,Allocations!$F$5:$F$1700,"LP",Allocations!$D$5:$D$1700,"Capital contributions")+SUMIFS(Allocations!$E$5:$E$1700,Allocations!$B$5:$B$1700,4,Allocations!$F$5:$F$1700,"LP",Allocations!$D$5:$D$1700,"Distributions") -> -30138889 | H34: =-SUMIFS(Allocations!$E$5:$E$1700,Allocations!$B$5:$B$1700,4,Allocations!$F$5:$F$1700,"LP",Allocations!$D$5:$D$1700,"Capital contributions")+SUMIFS(Allocations!$E$5:$E$1700,Allocations!$B$5:$B$1700,4,Allocations!$F$5:$F$1700,"LP",Allocations!$D$5:$D$1700,"Distributions") -> -30138889 | I34: =-SUMIFS(Allocations!$E$5:$E$1700,Allocations!$B$5:$B$1700,4,Allocations!$F$5:$F$1700,"LP",Allocations!$D$5:$D$1700,"Capital contributions")+SUMIFS(Allocations!$E$5:$E$1700,Allocations!$B$5:$B$1700,4,Allocations!$F$5:$F$1700,"LP",Allocations!$D$5:$D$1700,"Distributions") -> -30138889 | J34: =-SUMIFS(Allocations!$E$5:$E$1700,Allocations!$B$5:$B$1700,4,Allocations!$F$5:$F$1700,"LP",Allocations!$D$5:$D$1700,"Capital contributions")+SUMIFS(Allocations!$E$5:$E$1700,Allocations!$B$5:$B$1700,4,Allocations!$F$5:$F$1700,"LP",Allocations!$D$5:$D$1700,"Distributions") -> -30138889 | ... M34: =-SUMIFS(Allocations!$E$5:$E$1700,Allocations!$B$5:$B$1700,4,Allocations!$F$5:$F$1700,"LP",Allocations!$D$5:$D$1700,"Capital contributions")+SUMIFS(Allocations!$E$5:$E$1700,Allocations!$B$5:$B$1700,4,Allocations!$F$5:$F$1700,"LP",Allocations!$D$5:$D$1700,"Distributions") -> -30138889
A35: 2020Q2 | C35: =-SUMIFS(Allocations!$E$5:$E$1700,Allocations!$B$5:$B$1700,5,Allocations!$F$5:$F$1700,"LP",Allocations!$D$5:$D$1700,"Capital contributions")+SUMIFS(Allocations!$E$5:$E$1700,Allocations!$B$5:$B$1700,5,Allocations!$F$5:$F$1700,"LP",Allocations!$D$5:$D$1700,"Distributions") -> -1982555.5 | D35: =-SUMIFS(Allocations!$E$5:$E$1700,Allocations!$B$5:$B$1700,5,Allocations!$F$5:$F$1700,"LP",Allocations!$D$5:$D$1700,"Capital contributions")+SUMIFS(Allocations!$E$5:$E$1700,Allocations!$B$5:$B$1700,5,Allocations!$F$5:$F$1700,"LP",Allocations!$D$5:$D$1700,"Distributions") -> -1982555.5 | E35: =-SUMIFS(Allocations!$E$5:$E$1700,Allocations!$B$5:$B$1700,5,Allocations!$F$5:$F$1700,"LP",Allocations!$D$5:$D$1700,"Capital contributions")+SUMIFS(Allocations!$E$5:$E$1700,Allocations!$B$5:$B$1700,5,Allocations!$F$5:$F$1700,"LP",Allocations!$D$5:$D$1700,"Distributions") -> -1982555.5 | F35: =-SUMIFS(Allocations!$E$5:$E$1700,Allocations!$B$5:$B$1700,5,Allocations!$F$5:$F$1700,"LP",Allocations!$D$5:$D$1700,"Capital contributions")+SUMIFS(Allocations!$E$5:$E$1700,Allocations!$B$5:$B$1700,5,Allocations!$F$5:$F$1700,"LP",Allocations!$D$5:$D$1700,"Distributions") -> -1982555.5 | G35: =-SUMIFS(Allocations!$E$5:$E$1700,Allocations!$B$5:$B$1700,5,Allocations!$F$5:$F$1700,"LP",Allocations!$D$5:$D$1700,"Capital contributions")+SUMIFS(Allocations!$E$5:$E$1700,Allocations!$B$5:$B$1700,5,Allocations!$F$5:$F$1700,"LP",Allocations!$D$5:$D$1700,"Distributions") -> -1982555.5 | H35: =-SUMIFS(Allocations!$E$5:$E$1700,Allocations!$B$5:$B$1700,5,Allocations!$F$5:$F$1700,"LP",Allocations!$D$5:$D$1700,"Capital contributions")+SUMIFS(Allocations!$E$5:$E$1700,Allocations!$B$5:$B$1700,5,Allocations!$F$5:$F$1700,"LP",Allocations!$D$5:$D$1700,"Distributions") -> -1982555.5 | I35: =-SUMIFS(Allocations!$E$5:$E$1700,Allocations!$B$5:$B$1700,5,Allocations!$F$5:$F$1700,"LP",Allocations!$D$5:$D$1700,"Capital contributions")+SUMIFS(Allocations!$E$5:$E$1700,Allocations!$B$5:$B$1700,5,Allocations!$F$5:$F$1700,"LP",Allocations!$D$5:$D$1700,"Distributions") -> -1982555.5 | J35: =-SUMIFS(Allocations!$E$5:$E$1700,Allocations!$B$5:$B$1700,5,Allocations!$F$5:$F$1700,"LP",Allocations!$D$5:$D$1700,"Capital contributions")+SUMIFS(Allocations!$E$5:$E$1700,Allocations!$B$5:$B$1700,5,Allocations!$F$5:$F$1700,"LP",Allocations!$D$5:$D$1700,"Distributions") -> -1982555.5 | ... M35: =-SUMIFS(Allocations!$E$5:$E$1700,Allocations!$B$5:$B$1700,5,Allocations!$F$5:$F$1700,"LP",Allocations!$D$5:$D$1700,"Capital contributions")+SUMIFS(Allocations!$E$5:$E$1700,Allocations!$B$5:$B$1700,5,Allocations!$F$5:$F$1700,"LP",Allocations!$D$5:$D$1700,"Distributions") -> -1982555.5
A36: 2020Q3 | C36: =-SUMIFS(Allocations!$E$5:$E$1700,Allocations!$B$5:$B$1700,6,Allocations!$F$5:$F$1700,"LP",Allocations!$D$5:$D$1700,"Capital contributions")+SUMIFS(Allocations!$E$5:$E$1700,Allocations!$B$5:$B$1700,6,Allocations!$F$5:$F$1700,"LP",Allocations!$D$5:$D$1700,"Distributions") -> -1372000 | D36: =-SUMIFS(Allocations!$E$5:$E$1700,Allocations!$B$5:$B$1700,6,Allocations!$F$5:$F$1700,"LP",Allocations!$D$5:$D$1700,"Capital contributions")+SUMIFS(Allocations!$E$5:$E$1700,Allocations!$B$5:$B$1700,6,Allocations!$F$5:$F$1700,"LP",Allocations!$D$5:$D$1700,"Distributions") -> -1372000 | E36: =-SUMIFS(Allocations!$E$5:$E$1700,Allocations!$B$5:$B$1700,6,Allocations!$F$5:$F$1700,"LP",Allocations!$D$5:$D$1700,"Capital contributions")+SUMIFS(Allocations!$E$5:$E$1700,Allocations!$B$5:$B$1700,6,Allocations!$F$5:$F$1700,"LP",Allocations!$D$5:$D$1700,"Distributions") -> -1372000 | F36: =-SUMIFS(Allocations!$E$5:$E$1700,Allocations!$B$5:$B$1700,6,Allocations!$F$5:$F$1700,"LP",Allocations!$D$5:$D$1700,"Capital contributions")+SUMIFS(Allocations!$E$5:$E$1700,Allocations!$B$5:$B$1700,6,Allocations!$F$5:$F$1700,"LP",Allocations!$D$5:$D$1700,"Distributions") -> -1372000 | G36: =-SUMIFS(Allocations!$E$5:$E$1700,Allocations!$B$5:$B$1700,6,Allocations!$F$5:$F$1700,"LP",Allocations!$D$5:$D$1700,"Capital contributions")+SUMIFS(Allocations!$E$5:$E$1700,Allocations!$B$5:$B$1700,6,Allocations!$F$5:$F$1700,"LP",Allocations!$D$5:$D$1700,"Distributions") -> -1372000 | H36: =-SUMIFS(Allocations!$E$5:$E$1700,Allocations!$B$5:$B$1700,6,Allocations!$F$5:$F$1700,"LP",Allocations!$D$5:$D$1700,"Capital contributions")+SUMIFS(Allocations!$E$5:$E$1700,Allocations!$B$5:$B$1700,6,Allocations!$F$5:$F$1700,"LP",Allocations!$D$5:$D$1700,"Distributions") -> -1372000 | I36: =-SUMIFS(Allocations!$E$5:$E$1700,Allocations!$B$5:$B$1700,6,Allocations!$F$5:$F$1700,"LP",Allocations!$D$5:$D$1700,"Capital contributions")+SUMIFS(Allocations!$E$5:$E$1700,Allocations!$B$5:$B$1700,6,Allocations!$F$5:$F$1700,"LP",Allocations!$D$5:$D$1700,"Distributions") -> -1372000 | J36: =-SUMIFS(Allocations!$E$5:$E$1700,Allocations!$B$5:$B$1700,6,Allocations!$F$5:$F$1700,"LP",Allocations!$D$5:$D$1700,"Capital contributions")+SUMIFS(Allocations!$E$5:$E$1700,Allocations!$B$5:$B$1700,6,Allocations!$F$5:$F$1700,"LP",Allocations!$D$5:$D$1700,"Distributions") -> -1372000 | ... M36: =-SUMIFS(Allocations!$E$5:$E$1700,Allocations!$B$5:$B$1700,6,Allocations!$F$5:$F$1700,"LP",Allocations!$D$5:$D$1700,"Capital contributions")+SUMIFS(Allocations!$E$5:$E$1700,Allocations!$B$5:$B$1700,6,Allocations!$F$5:$F$1700,"LP",Allocations!$D$5:$D$1700,"Distributions") -> -1372000
A37: 2020Q4 | C37: =-SUMIFS(Allocations!$E$5:$E$1700,Allocations!$B$5:$B$1700,7,Allocations!$F$5:$F$1700,"LP",Allocations!$D$5:$D$1700,"Capital contributions")+SUMIFS(Allocations!$E$5:$E$1700,Allocations!$B$5:$B$1700,7,Allocations!$F$5:$F$1700,"LP",Allocations!$D$5:$D$1700,"Distributions")+C6 -> 78275701 | D37: =-SUMIFS(Allocations!$E$5:$E$1700,Allocations!$B$5:$B$1700,7,Allocations!$F$5:$F$1700,"LP",Allocations!$D$5:$D$1700,"Capital contributions")+SUMIFS(Allocations!$E$5:$E$1700,Allocations!$B$5:$B$1700,7,Allocations!$F$5:$F$1700,"LP",Allocations!$D$5:$D$1700,"Distributions") -> -25774000 | E37: =-SUMIFS(Allocations!$E$5:$E$1700,Allocations!$B$5:$B$1700,7,Allocations!$F$5:$F$1700,"LP",Allocations!$D$5:$D$1700,"Capital contributions")+SUMIFS(Allocations!$E$5:$E$1700,Allocations!$B$5:$B$1700,7,Allocations!$F$5:$F$1700,"LP",Allocations!$D$5:$D$1700,"Distributions") -> -25774000 | F37: =-SUMIFS(Allocations!$E$5:$E$1700,Allocations!$B$5:$B$1700,7,Allocations!$F$5:$F$1700,"LP",Allocations!$D$5:$D$1700,"Capital contributions")+SUMIFS(Allocations!$E$5:$E$1700,Allocations!$B$5:$B$1700,7,Allocations!$F$5:$F$1700,"LP",Allocations!$D$5:$D$1700,"Distributions") -> -25774000 | G37: =-SUMIFS(Allocations!$E$5:$E$1700,Allocations!$B$5:$B$1700,7,Allocations!$F$5:$F$1700,"LP",Allocations!$D$5:$D$1700,"Capital contributions")+SUMIFS(Allocations!$E$5:$E$1700,Allocations!$B$5:$B$1700,7,Allocations!$F$5:$F$1700,"LP",Allocations!$D$5:$D$1700,"Distributions") -> -25774000 | H37: =-SUMIFS(Allocations!$E$5:$E$1700,Allocations!$B$5:$B$1700,7,Allocations!$F$5:$F$1700,"LP",Allocations!$D$5:$D$1700,"Capital contributions")+SUMIFS(Allocations!$E$5:$E$1700,Allocations!$B$5:$B$1700,7,Allocations!$F$5:$F$1700,"LP",Allocations!$D$5:$D$1700,"Distributions") -> -25774000 | I37: =-SUMIFS(Allocations!$E$5:$E$1700,Allocations!$B$5:$B$1700,7,Allocations!$F$5:$F$1700,"LP",Allocations!$D$5:$D$1700,"Capital contributions")+SUMIFS(Allocations!$E$5:$E$1700,Allocations!$B$5:$B$1700,7,Allocations!$F$5:$F$1700,"LP",Allocations!$D$5:$D$1700,"Distributions") -> -25774000 | J37: =-SUMIFS(Allocations!$E$5:$E$1700,Allocations!$B$5:$B$1700,7,Allocations!$F$5:$F$1700,"LP",Allocations!$D$5:$D$1700,"Capital contributions")+SUMIFS(Allocations!$E$5:$E$1700,Allocations!$B$5:$B$1700,7,Allocations!$F$5:$F$1700,"LP",Allocations!$D$5:$D$1700,"Distributions") -> -25774000 | K37: =-SUMIFS(Allocations!$E$5:$E$1700,Allocations!$B$5:$B$1700,7,Allocations!$F$5:$F$1700,"LP",Allocations!$D$5:$D$1700,"Capital contributions")+SUMIFS(Allocations!$E$5:$E$1700,Allocations!$B$5:$B$1700,7,Allocations!$F$5:$F$1700,"LP",Allocations!$D$5:$D$1700,"Distributions") -> -25774000 | ... M37: =-SUMIFS(Allocations!$E$5:$E$1700,Allocations!$B$5:$B$1700,7,Allocations!$F$5:$F$1700,"LP",Allocations!$D$5:$D$1700,"Capital contributions")+SUMIFS(Allocations!$E$5:$E$1700,Allocations!$B$5:$B$1700,7,Allocations!$F$5:$F$1700,"LP",Allocations!$D$5:$D$1700,"Distributions") -> -25774000
